Workbook
Name mycementtable: 'Cement Portfolio'!$B$1:$CI$79

Sheet Price Record
B1: Column1 | C1: Column2 | F1: Column6 | G1: Column8 | H1: Column11 | I1: Column16 | J1: Column17
K3: HMT | M3: IHT
A4: Match | B4: نام | C4: نماد | F4: دیروز | G4: آخرین معامله - مقدار | H4: قیمت پایانی - مقدار | I4: EPS | J4: P/E | K4: Market Cap | L4: Shares Hold | M4: Portfolio-AA | O4: MC -- | P4: MC ++ | Q4: Mcap Diff % | R4: Portfolio Diff % | S4: PP ++ | T4: PP -- | V4: دیروز | W4: آخرین معامله | X4: قیمت پایانی | Y4: EPS | Z4: P/E | AA4: Market Cap | AB4: Shares Hold | AC4: Portfolio-AA
A6: =IFERROR(MATCH(C6,'دیده بان بازار'!$A$5:$A$3994,0 )+4,"Closed") -> 1934 | B6: بين المللي ساروج بوشهر | C6: ساروج | D6: C | F6: =IFERROR(_xlfn.LET(_xlpm.lookup_result,_xlfn.XLOOKUP($C6,'دیده بان بازار'!$A$5:$A$3994,'دیده بان بازار'!F$5:F$3994),IF(ISERROR(_xlpm.lookup_result),V6,_xlpm.lookup_result)),V6) -> 55530 | G6: =IFERROR(_xlfn.LET(_xlpm.lookup_result,_xlfn.XLOOKUP($C6,'دیده بان بازار'!$A$5:$A$3994,'دیده بان بازار'!H$5:H$3994),IF(ISERROR(_xlpm.lookup_result),W6,_xlpm.lookup_result)),W6) -> 57190 | H6: =IFERROR(_xlfn.LET(_xlpm.lookup_result,_xlfn.XLOOKUP($C6,'دیده بان بازار'!$A$5:$A$3994,'دیده بان بازار'!K$5:K$3994),IF(ISERROR(_xlpm.lookup_result),X6,_xlpm.lookup_result)),X6) -> 57170 | I6: =IFERROR(_xlfn.LET(_xlpm.lookup_result,_xlfn.XLOOKUP($C6,'دیده بان بازار'!$A$5:$A$3994,'دیده بان بازار'!P$5:P$3994),IF(ISERROR(_xlpm.lookup_result),Y6,_xlpm.lookup_result)),Y6) -> 11890 | J6: =IFERROR(_xlfn.LET(_xlpm.lookup_result,_xlfn.XLOOKUP($C6,'دیده بان بازار'!$A$5:$A$3994,'دیده بان بازار'!Q$5:Q$3994),IF(ISERROR(_xlpm.lookup_result),Z6,_xlpm.lookup_result)),Z6) -> 4.81 | K6: =_xlfn.XLOOKUP(C6,Cement!$Q$7:$Q$35,Cement!$S$7:$S$35,"")/1000 -> 7.66346 | L6: =_xlfn.XLOOKUP(C6,'Cement Portfolio'!$O$8:$O$36,'Cement Portfolio'!$AP$8:$AP$36,"") -> 280000 | M6: =_xlfn.XLOOKUP(C6,'Cement Portfolio'!$O$8:$O$36,'Cement Portfolio'!$AQ$8:$AQ$36,"") -> 1587228.4 | O6: =IF(AND(Q6<0,R6<0,Q6<R6),Q6-R6,"") | P6: =IF(AND(Q6>=0,R6>=0,Q6>R6),Q6-R6,"") | Q6: =IFERROR(((K6-AA6)*100)/ABS($K$106),"") -> 0.081787075 | R6: =IFERROR((($AB6*$G6*0.9912*0.0001)-AC6)*100/ABS($AC$108),"") -> 2.8519501 | S6: =IF(AND(R6>0,Q6>0,R6>Q6),R6-Q6,"") -> 2.770163 | T6: =IF(AND(R6<0,Q6<0,R6<Q6),R6-Q6,"") | V6: 54640 | W6: 56100 | X6: 55530 | Y6: 11890 | Z6: 4.67 | AA6: 7.5174 | AB6: 280000 | AC6: 1556977
A7: =IFERROR(MATCH(C7,'دیده بان بازار'!$A$5:$A$3994,0 )+4,"Closed") -> 517 | B7: سيمان‌ شرق‌ | C7: سشرق | D7: C | F7: =IFERROR(_xlfn.LET(_xlpm.lookup_result,_xlfn.XLOOKUP($C7,'دیده بان بازار'!$A$5:$A$3994,'دیده بان بازار'!F$5:F$3994),IF(ISERROR(_xlpm.lookup_result),V7,_xlpm.lookup_result)),V7) -> 19150 | G7: =IFERROR(_xlfn.LET(_xlpm.lookup_result,_xlfn.XLOOKUP($C7,'دیده بان بازار'!$A$5:$A$3994,'دیده بان بازار'!H$5:H$3994),IF(ISERROR(_xlpm.lookup_result),W7,_xlpm.lookup_result)),W7) -> 19720 | H7: =IFERROR(_xlfn.LET(_xlpm.lookup_result,_xlfn.XLOOKUP($C7,'دیده بان بازار'!$A$5:$A$3994,'دیده بان بازار'!K$5:K$3994),IF(ISERROR(_xlpm.lookup_result),X7,_xlpm.lookup_result)),X7) -> 19720 | I7: =IFERROR(_xlfn.LET(_xlpm.lookup_result,_xlfn.XLOOKUP($C7,'دیده بان بازار'!$A$5:$A$3994,'دیده بان بازار'!P$5:P$3994),IF(ISERROR(_xlpm.lookup_result),Y7,_xlpm.lookup_result)),Y7) -> 3056 | J7: =IFERROR(_xlfn.LET(_xlpm.lookup_result,_xlfn.XLOOKUP($C7,'دیده بان بازار'!$A$5:$A$3994,'دیده بان بازار'!Q$5:Q$3994),IF(ISERROR(_xlpm.lookup_result),Z7,_xlpm.lookup_result)),Z7) -> 6.45 | K7: =_xlfn.XLOOKUP(C7,Cement!$Q$7:$Q$35,Cement!$S$7:$S$35,"")/1000 -> 12.2264 | L7: =_xlfn.XLOOKUP(C7,'Cement Portfolio'!$O$8:$O$36,'Cement Portfolio'!$AP$8:$AP$36,"") -> 100000 | M7: =_xlfn.XLOOKUP(C7,'Cement Portfolio'!$O$8:$O$36,'Cement Portfolio'!$AQ$8:$AQ$36,"") -> 195464.64 | O7: =IF(AND(Q7<0,R7<0,Q7<R7),Q7-R7,"") | P7: =IF(AND(Q7>=0,R7>=0,Q7>R7),Q7-R7,"") | Q7: =IFERROR(((K7-AA7)*100)/ABS($K$106),"") -> 0.18747304 | R7: =IFERROR((($AB7*$G7*0.9912*0.0001)-AC7)*100/ABS($AC$108),"") -> 1.5138136 | S7: =IF(AND(R7>0,Q7>0,R7>Q7),R7-Q7,"") -> 1.3263406 | T7: =IF(AND(R7<0,Q7<0,R7<Q7),R7-Q7,"") | V7: 18630 | W7: 19180 | X7: 19150 | Y7: 3056 | Z7: 6.27 | AA7: 11.8916 | AB7: 300000 | AC7: 570336.48
A8: =IFERROR(MATCH(C8,'دیده بان بازار'!$A$5:$A$3994,0 )+4,"Closed") -> 167 | B8: سيمان‌خاش‌ | C8: سخاش | D8: C | F8: =IFERROR(_xlfn.LET(_xlpm.lookup_result,_xlfn.XLOOKUP($C8,'دیده بان بازار'!$A$5:$A$3994,'دیده بان بازار'!F$5:F$3994),IF(ISERROR(_xlpm.lookup_result),V8,_xlpm.lookup_result)),V8) -> 11230 | G8: =IFERROR(_xlfn.LET(_xlpm.lookup_result,_xlfn.XLOOKUP($C8,'دیده بان بازار'!$A$5:$A$3994,'دیده بان بازار'!H$5:H$3994),IF(ISERROR(_xlpm.lookup_result),W8,_xlpm.lookup_result)),W8) -> 11560 | H8: =IFERROR(_xlfn.LET(_xlpm.lookup_result,_xlfn.XLOOKUP($C8,'دیده بان بازار'!$A$5:$A$3994,'دیده بان بازار'!K$5:K$3994),IF(ISERROR(_xlpm.lookup_result),X8,_xlpm.lookup_result)),X8) -> 11520 | I8: =IFERROR(_xlfn.LET(_xlpm.lookup_result,_xlfn.XLOOKUP($C8,'دیده بان بازار'!$A$5:$A$3994,'دیده بان بازار'!P$5:P$3994),IF(ISERROR(_xlpm.lookup_result),Y8,_xlpm.lookup_result)),Y8) -> 1929 | J8: =IFERROR(_xlfn.LET(_xlpm.lookup_result,_xlfn.XLOOKUP($C8,'دیده بان بازار'!$A$5:$A$3994,'دیده بان بازار'!Q$5:Q$3994),IF(ISERROR(_xlpm.lookup_result),Z8,_xlpm.lookup_result)),Z8) -> 5.97 | K8: =_xlfn.XLOOKUP(C8,Cement!$Q$7:$Q$35,Cement!$S$7:$S$35,"")/1000 -> 6.1268 | L8: =_xlfn.XLOOKUP(C8,'Cement Portfolio'!$O$8:$O$36,'Cement Portfolio'!$AP$8:$AP$36,"") -> 2650000 | M8: =_xlfn.XLOOKUP(C8,'Cement Portfolio'!$O$8:$O$36,'Cement Portfolio'!$AQ$8:$AQ$36,"") -> 3036442.1 | O8: =IF(AND(Q8<0,R8<0,Q8<R8),Q8-R8,"") | P8: =IF(AND(Q8>=0,R8>=0,Q8>R8),Q8-R8,"") | Q8: =IFERROR(((K8-AA8)*100)/ABS($K$106),"") -> 0.089032896 | R8: =IFERROR((($AB8*$G8*0.9912*0.0001)-AC8)*100/ABS($AC$108),"") -> 7.4289002 | S8: =IF(AND(R8>0,Q8>0,R8>Q8),R8-Q8,"") -> 7.3398673 | T8: =IF(AND(R8<0,Q8<0,R8<Q8),R8-Q8,"") | V8: 10960 | W8: 11260 | X8: 11230 | Y8: 1929 | Z8: 5.82 | AA8: 5.9678 | AB8: 2650000 | AC8: 2957641.7
A9: =IFERROR(MATCH(C9,'دیده بان بازار'!$A$5:$A$3994,0 )+4,"Closed") -> 1362 | B9: سيمان‌ بهبهان‌ | C9: سبهان | D9: C | F9: =IFERROR(_xlfn.LET(_xlpm.lookup_result,_xlfn.XLOOKUP($C9,'دیده بان بازار'!$A$5:$A$3994,'دیده بان بازار'!F$5:F$3994),IF(ISERROR(_xlpm.lookup_result),V9,_xlpm.lookup_result)),V9) -> 5310 | G9: =IFERROR(_xlfn.LET(_xlpm.lookup_result,_xlfn.XLOOKUP($C9,'دیده بان بازار'!$A$5:$A$3994,'دیده بان بازار'!H$5:H$3994),IF(ISERROR(_xlpm.lookup_result),W9,_xlpm.lookup_result)),W9) -> 5460 | H9: =IFERROR(_xlfn.LET(_xlpm.lookup_result,_xlfn.XLOOKUP($C9,'دیده بان بازار'!$A$5:$A$3994,'دیده بان بازار'!K$5:K$3994),IF(ISERROR(_xlpm.lookup_result),X9,_xlpm.lookup_result)),X9) -> 5460 | I9: =IFERROR(_xlfn.LET(_xlpm.lookup_result,_xlfn.XLOOKUP($C9,'دیده بان بازار'!$A$5:$A$3994,'دیده بان بازار'!P$5:P$3994),IF(ISERROR(_xlpm.lookup_result),Y9,_xlpm.lookup_result)),Y9) -> 989 | J9: =IFERROR(_xlfn.LET(_xlpm.lookup_result,_xlfn.XLOOKUP($C9,'دیده بان بازار'!$A$5:$A$3994,'دیده بان بازار'!Q$5:Q$3994),IF(ISERROR(_xlpm.lookup_result),Z9,_xlpm.lookup_result)),Z9) -> 5.52 | K9: =_xlfn.XLOOKUP(C9,Cement!$Q$7:$Q$35,Cement!$S$7:$S$35,"")/1000 -> 4.0404 | L9: =_xlfn.XLOOKUP(C9,'Cement Portfolio'!$O$8:$O$36,'Cement Portfolio'!$AP$8:$AP$36,"") -> 2400000 | M9: =_xlfn.XLOOKUP(C9,'Cement Portfolio'!$O$8:$O$36,'Cement Portfolio'!$AQ$8:$AQ$36,"") -> 1298868.5 | O9: =IF(AND(Q9<0,R9<0,Q9<R9),Q9-R9,"") | P9: =IF(AND(Q9>=0,R9>=0,Q9>R9),Q9-R9,"") | Q9: =IFERROR(((K9-AA9)*100)/ABS($K$106),"") -> 0.058011372 | R9: =IFERROR((($AB9*$G9*0.9912*0.0001)-AC9)*100/ABS($AC$108),"") -> 3.1397616 | S9: =IF(AND(R9>0,Q9>0,R9>Q9),R9-Q9,"") -> 3.0817502 | T9: =IF(AND(R9<0,Q9<0,R9<Q9),R9-Q9,"") | V9: 5170 | W9: 5320 | X9: 5310 | Y9: 989 | Z9: 5.37 | AA9: 3.9368 | AB9: 2400000 | AC9: 1265564.2
A10: =IFERROR(MATCH(C10,'دیده بان بازار'!$A$5:$A$3994,0 )+4,"Closed") -> 1658 | B10: سيمان‌ سپاهان‌ | C10: سپاها | D10: C | F10: =IFERROR(_xlfn.LET(_xlpm.lookup_result,_xlfn.XLOOKUP($C10,'دیده بان بازار'!$A$5:$A$3994,'دیده بان بازار'!F$5:F$3994),IF(ISERROR(_xlpm.lookup_result),V10,_xlpm.lookup_result)),V10) -> 18740 | G10: =IFERROR(_xlfn.LET(_xlpm.lookup_result,_xlfn.XLOOKUP($C10,'دیده بان بازار'!$A$5:$A$3994,'دیده بان بازار'!H$5:H$3994),IF(ISERROR(_xlpm.lookup_result),W10,_xlpm.lookup_result)),W10) -> 19300 | H10: =IFERROR(_xlfn.LET(_xlpm.lookup_result,_xlfn.XLOOKUP($C10,'دیده بان بازار'!$A$5:$A$3994,'دیده بان بازار'!K$5:K$3994),IF(ISERROR(_xlpm.lookup_result),X10,_xlpm.lookup_result)),X10) -> 19290 | I10: =IFERROR(_xlfn.LET(_xlpm.lookup_result,_xlfn.XLOOKUP($C10,'دیده بان بازار'!$A$5:$A$3994,'دیده بان بازار'!P$5:P$3994),IF(ISERROR(_xlpm.lookup_result),Y10,_xlpm.lookup_result)),Y10) -> 2433 | J10: =IFERROR(_xlfn.LET(_xlpm.lookup_result,_xlfn.XLOOKUP($C10,'دیده بان بازار'!$A$5:$A$3994,'دیده بان بازار'!Q$5:Q$3994),IF(ISERROR(_xlpm.lookup_result),Z10,_xlpm.lookup_result)),Z10) -> 7.93 | K10: =_xlfn.XLOOKUP(C10,Cement!$Q$7:$Q$35,Cement!$S$7:$S$35,"")/1000 -> 13.0275 | L10: =_xlfn.XLOOKUP(C10,'Cement Portfolio'!$O$8:$O$36,'Cement Portfolio'!$AP$8:$AP$36,"") -> 0 | M10: =_xlfn.XLOOKUP(C10,'Cement Portfolio'!$O$8:$O$36,'Cement Portfolio'!$AQ$8:$AQ$36,"") -> 0 | O10: =IF(AND(Q10<0,R10<0,Q10<R10),Q10-R10,"") | P10: =IF(AND(Q10>=0,R10>=0,Q10>R10),Q10-R10,"") -> 0.20410372 | Q10: =IFERROR(((K10-AA10)*100)/ABS($K$106),"") -> 0.20410372 | R10: =IFERROR((($AB10*$G10*0.9912*0.0001)-AC10)*100/ABS($AC$108),"") -> 0 | S10: =IF(AND(R10>0,Q10>0,R10>Q10),R10-Q10,"") | T10: =IF(AND(R10<0,Q10<0,R10<Q10),R10-Q10,"") | V10: 18220 | W10: 18760 | X10: 18740 | Y10: 2433 | Z10: 7.7 | AA10: 12.663 | AB10: 0 | AC10: 0
A11: =IFERROR(MATCH(C11,'دیده بان بازار'!$A$5:$A$3994,0 )+4,"Closed") -> 1754 | B11: سيمان‌ شاهرود | C11: سرود | D11: C | F11: =IFERROR(_xlfn.LET(_xlpm.lookup_result,_xlfn.XLOOKUP($C11,'دیده بان بازار'!$A$5:$A$3994,'دیده بان بازار'!F$5:F$3994),IF(ISERROR(_xlpm.lookup_result),V11,_xlpm.lookup_result)),V11) -> 16180 | G11: =IFERROR(_xlfn.LET(_xlpm.lookup_result,_xlfn.XLOOKUP($C11,'دیده بان بازار'!$A$5:$A$3994,'دیده بان بازار'!H$5:H$3994),IF(ISERROR(_xlpm.lookup_result),W11,_xlpm.lookup_result)),W11) -> 16660 | H11: =IFERROR(_xlfn.LET(_xlpm.lookup_result,_xlfn.XLOOKUP($C11,'دیده بان بازار'!$A$5:$A$3994,'دیده بان بازار'!K$5:K$3994),IF(ISERROR(_xlpm.lookup_result),X11,_xlpm.lookup_result)),X11) -> 16660 | I11: =IFERROR(_xlfn.LET(_xlpm.lookup_result,_xlfn.XLOOKUP($C11,'دیده بان بازار'!$A$5:$A$3994,'دیده بان بازار'!P$5:P$3994),IF(ISERROR(_xlpm.lookup_result),Y11,_xlpm.lookup_result)),Y11) -> 2424 | J11: =IFERROR(_xlfn.LET(_xlpm.lookup_result,_xlfn.XLOOKUP($C11,'دیده بان بازار'!$A$5:$A$3994,'دیده بان بازار'!Q$5:Q$3994),IF(ISERROR(_xlpm.lookup_result),Z11,_xlpm.lookup_result)),Z11) -> 6.87 | K11: =_xlfn.XLOOKUP(C11,Cement!$Q$7:$Q$35,Cement!$S$7:$S$35,"")/1000 -> 15.993698 | L11: =_xlfn.XLOOKUP(C11,'Cement Portfolio'!$O$8:$O$36,'Cement Portfolio'!$AP$8:$AP$36,"") -> 1000000 | M11: =_xlfn.XLOOKUP(C11,'Cement Portfolio'!$O$8:$O$36,'Cement Portfolio'!$AQ$8:$AQ$36,"") -> 1651339.2 | O11: =IF(AND(Q11<0,R11<0,Q11<R11),Q11-R11,"") | P11: =IF(AND(Q11>=0,R11>=0,Q11>R11),Q11-R11,"") | Q11: =IFERROR(((K11-AA11)*100)/ABS($K$106),"") -> 0.258029 | R11: =IFERROR((($AB11*$G11*0.9912*0.0001)-AC11)*100/ABS($AC$108),"") -> 4.4853737 | S11: =IF(AND(R11>0,Q11>0,R11>Q11),R11-Q11,"") -> 4.2273447 | T11: =IF(AND(R11<0,Q11<0,R11<Q11),R11-Q11,"") | V11: 15710 | W11: 16180 | X11: 16180 | Y11: 2424 | Z11: 6.67 | AA11: 15.532895 | AB11: 1000000 | AC11: 1603761.6
A12: =IFERROR(MATCH(C12,'دیده بان بازار'!$A$5:$A$3994,0 )+4,"Closed") -> 648 | B12: سيمان خوزستان | C12: سخوز | D12: C | F12: =IFERROR(_xlfn.LET(_xlpm.lookup_result,_xlfn.XLOOKUP($C12,'دیده بان بازار'!$A$5:$A$3994,'دیده بان بازار'!F$5:F$3994),IF(ISERROR(_xlpm.lookup_result),V12,_xlpm.lookup_result)),V12) -> 71630 | G12: =IFERROR(_xlfn.LET(_xlpm.lookup_result,_xlfn.XLOOKUP($C12,'دیده بان بازار'!$A$5:$A$3994,'دیده بان بازار'!H$5:H$3994),IF(ISERROR(_xlpm.lookup_result),W12,_xlpm.lookup_result)),W12) -> 73770 | H12: =IFERROR(_xlfn.LET(_xlpm.lookup_result,_xlfn.XLOOKUP($C12,'دیده بان بازار'!$A$5:$A$3994,'دیده بان بازار'!K$5:K$3994),IF(ISERROR(_xlpm.lookup_result),X12,_xlpm.lookup_result)),X12) -> 73770 | I12: =IFERROR(_xlfn.LET(_xlpm.lookup_result,_xlfn.XLOOKUP($C12,'دیده بان بازار'!$A$5:$A$3994,'دیده بان بازار'!P$5:P$3994),IF(ISERROR(_xlpm.lookup_result),Y12,_xlpm.lookup_result)),Y12) -> 15662 | J12: =IFERROR(_xlfn.LET(_xlpm.lookup_result,_xlfn.XLOOKUP($C12,'دیده بان بازار'!$A$5:$A$3994,'دیده بان بازار'!Q$5:Q$3994),IF(ISERROR(_xlpm.lookup_result),Z12,_xlpm.lookup_result)),Z12) -> 4.71 | K12: =_xlfn.XLOOKUP(C12,Cement!$Q$7:$Q$35,Cement!$S$7:$S$35,"")/1000 -> 10.3278 | L12: =_xlfn.XLOOKUP(C12,'Cement Portfolio'!$O$8:$O$36,'Cement Portfolio'!$AP$8:$AP$36,"") -> 0 | M12: =_xlfn.XLOOKUP(C12,'Cement Portfolio'!$O$8:$O$36,'Cement Portfolio'!$AQ$8:$AQ$36,"") -> 0 | O12: =IF(AND(Q12<0,R12<0,Q12<R12),Q12-R12,"") | P12: =IF(AND(Q12>=0,R12>=0,Q12>R12),Q12-R12,"") -> 0.16776261 | Q12: =IFERROR(((K12-AA12)*100)/ABS($K$106),"") -> 0.16776261 | R12: =IFERROR((($AB12*$G12*0.9912*0.0001)-AC12)*100/ABS($AC$108),"") -> 0 | S12: =IF(AND(R12>0,Q12>0,R12>Q12),R12-Q12,"") | T12: =IF(AND(R12<0,Q12<0,R12<Q12),R12-Q12,"") | V12: 69550 | W12: 71630 | X12: 71630 | Y12: 15662 | Z12: 4.57 | AA12: 10.0282 | AB12: 0 | AC12: 0
A13: =IFERROR(MATCH(C13,'دیده بان بازار'!$A$5:$A$3994,0 )+4,"Closed") -> 197 | B13: سيمان ‌اروميه‌ | C13: ساروم | D13: C | F13: =IFERROR(_xlfn.LET(_xlpm.lookup_result,_xlfn.XLOOKUP($C13,'دیده بان بازار'!$A$5:$A$3994,'دیده بان بازار'!F$5:F$3994),IF(ISERROR(_xlpm.lookup_result),V13,_xlpm.lookup_result)),V13) -> 199400 | G13: =IFERROR(_xlfn.LET(_xlpm.lookup_result,_xlfn.XLOOKUP($C13,'دیده بان بازار'!$A$5:$A$3994,'دیده بان بازار'!H$5:H$3994),IF(ISERROR(_xlpm.lookup_result),W13,_xlpm.lookup_result)),W13) -> 205300 | H13: =IFERROR(_xlfn.LET(_xlpm.lookup_result,_xlfn.XLOOKUP($C13,'دیده بان بازار'!$A$5:$A$3994,'دیده بان بازار'!K$5:K$3994),IF(ISERROR(_xlpm.lookup_result),X13,_xlpm.lookup_result)),X13) -> 205300 | I13: =IFERROR(_xlfn.LET(_xlpm.lookup_result,_xlfn.XLOOKUP($C13,'دیده بان بازار'!$A$5:$A$3994,'دیده بان بازار'!P$5:P$3994),IF(ISERROR(_xlpm.lookup_result),Y13,_xlpm.lookup_result)),Y13) -> 34336 | J13: =IFERROR(_xlfn.LET(_xlpm.lookup_result,_xlfn.XLOOKUP($C13,'دیده بان بازار'!$A$5:$A$3994,'دیده بان بازار'!Q$5:Q$3994),IF(ISERROR(_xlpm.lookup_result),Z13,_xlpm.lookup_result)),Z13) -> 5.98 | K13: =_xlfn.XLOOKUP(C13,Cement!$Q$7:$Q$35,Cement!$S$7:$S$35,"")/1000 -> 20.53 | L13: =_xlfn.XLOOKUP(C13,'Cement Portfolio'!$O$8:$O$36,'Cement Portfolio'!$AP$8:$AP$36,"") -> 90000 | M13: =_xlfn.XLOOKUP(C13,'Cement Portfolio'!$O$8:$O$36,'Cement Portfolio'!$AQ$8:$AQ$36,"") -> 1831440.2 | O13: =IF(AND(Q13<0,R13<0,Q13<R13),Q13-R13,"") | P13: =IF(AND(Q13>=0,R13>=0,Q13>R13),Q13-R13,"") | Q13: =IFERROR(((K13-AA13)*100)/ABS($K$106),"") -> 0.33037364 | R13: =IFERROR((($AB13*$G13*0.9912*0.0001)-AC13)*100/ABS($AC$108),"") -> 4.9619447 | S13: =IF(AND(R13>0,Q13>0,R13>Q13),R13-Q13,"") -> 4.631571 | T13: =IF(AND(R13<0,Q13<0,R13<Q13),R13-Q13,"") | V13: 193600 | W13: 199400 | X13: 199400 | Y13: 34336 | Z13: 5.81 | AA13: 19.94 | AB13: 90000 | AC13: 1778807.5
A14: =IFERROR(MATCH(C14,'دیده بان بازار'!$A$5:$A$3994,0 )+4,"Closed") -> 2060 | B14: سيمان‌ خزر | C14: سخزر | D14: C | F14: =IFERROR(_xlfn.LET(_xlpm.lookup_result,_xlfn.XLOOKUP($C14,'دیده بان بازار'!$A$5:$A$3994,'دیده بان بازار'!F$5:F$3994),IF(ISERROR(_xlpm.lookup_result),V14,_xlpm.lookup_result)),V14) -> 5370 | G14: =IFERROR(_xlfn.LET(_xlpm.lookup_result,_xlfn.XLOOKUP($C14,'دیده بان بازار'!$A$5:$A$3994,'دیده بان بازار'!H$5:H$3994),IF(ISERROR(_xlpm.lookup_result),W14,_xlpm.lookup_result)),W14) -> 5530 | H14: =IFERROR(_xlfn.LET(_xlpm.lookup_result,_xlfn.XLOOKUP($C14,'دیده بان بازار'!$A$5:$A$3994,'دیده بان بازار'!K$5:K$3994),IF(ISERROR(_xlpm.lookup_result),X14,_xlpm.lookup_result)),X14) -> 5530 | I14: =IFERROR(_xlfn.LET(_xlpm.lookup_result,_xlfn.XLOOKUP($C14,'دیده بان بازار'!$A$5:$A$3994,'دیده بان بازار'!P$5:P$3994),IF(ISERROR(_xlpm.lookup_result),Y14,_xlpm.lookup_result)),Y14) -> 822 | J14: =IFERROR(_xlfn.LET(_xlpm.lookup_result,_xlfn.XLOOKUP($C14,'دیده بان بازار'!$A$5:$A$3994,'دیده بان بازار'!Q$5:Q$3994),IF(ISERROR(_xlpm.lookup_result),Z14,_xlpm.lookup_result)),Z14) -> 6.73 | K14: =_xlfn.XLOOKUP(C14,Cement!$Q$7:$Q$35,Cement!$S$7:$S$35,"")/1000 -> 5.1429 | L14: =_xlfn.XLOOKUP(C14,'Cement Portfolio'!$O$8:$O$36,'Cement Portfolio'!$AP$8:$AP$36,"") -> 100000 | M14: =_xlfn.XLOOKUP(C14,'Cement Portfolio'!$O$8:$O$36,'Cement Portfolio'!$AQ$8:$AQ$36,"") -> 54813.36 | O14: =IF(AND(Q14<0,R14<0,Q14<R14),Q14-R14,"") | P14: =IF(AND(Q14>=0,R14>=0,Q14>R14),Q14-R14,"") | Q14: =IFERROR(((K14-AA14)*100)/ABS($K$106),"") -> 0.083321352 | R14: =IFERROR((($AB14*$G14*0.9912*0.0001)-AC14)*100/ABS($AC$108),"") -> 0.14951246 | S14: =IF(AND(R14>0,Q14>0,R14>Q14),R14-Q14,"") -> 0.066191104 | T14: =IF(AND(R14<0,Q14<0,R14<Q14),R14-Q14,"") | V14: 5220 | W14: 5370 | X14: 5370 | Y14: 822 | Z14: 6.53 | AA14: 4.9941 | AB14: 100000 | AC14: 53227.44
A15: =IFERROR(MATCH(C15,'دیده بان بازار'!$A$5:$A$3994,0 )+4,"Closed") -> 2027 | B15: سيمان باقران | C15: سباقر | D15: C | F15: =IFERROR(_xlfn.LET(_xlpm.lookup_result,_xlfn.XLOOKUP($C15,'دیده بان بازار'!$A$5:$A$3994,'دیده بان بازار'!F$5:F$3994),IF(ISERROR(_xlpm.lookup_result),V15,_xlpm.lookup_result)),V15) -> 235800 | G15: =IFERROR(_xlfn.LET(_xlpm.lookup_result,_xlfn.XLOOKUP($C15,'دیده بان بازار'!$A$5:$A$3994,'دیده بان بازار'!H$5:H$3994),IF(ISERROR(_xlpm.lookup_result),W15,_xlpm.lookup_result)),W15) -> 242800 | H15: =IFERROR(_xlfn.LET(_xlpm.lookup_result,_xlfn.XLOOKUP($C15,'دیده بان بازار'!$A$5:$A$3994,'دیده بان بازار'!K$5:K$3994),IF(ISERROR(_xlpm.lookup_result),X15,_xlpm.lookup_result)),X15) -> 242800 | I15: =IFERROR(_xlfn.LET(_xlpm.lookup_result,_xlfn.XLOOKUP($C15,'دیده بان بازار'!$A$5:$A$3994,'دیده بان بازار'!P$5:P$3994),IF(ISERROR(_xlpm.lookup_result),Y15,_xlpm.lookup_result)),Y15) -> 44486 | J15: =IFERROR(_xlfn.LET(_xlpm.lookup_result,_xlfn.XLOOKUP($C15,'دیده بان بازار'!$A$5:$A$3994,'دیده بان بازار'!Q$5:Q$3994),IF(ISERROR(_xlpm.lookup_result),Z15,_xlpm.lookup_result)),Z15) -> 5.46 | K15: =_xlfn.XLOOKUP(C15,Cement!$Q$7:$Q$35,Cement!$S$7:$S$35,"")/1000 -> 14.568 | L15: =_xlfn.XLOOKUP(C15,'Cement Portfolio'!$O$8:$O$36,'Cement Portfolio'!$AP$8:$AP$36,"") -> 230000 | M15: =_xlfn.XLOOKUP(C15,'Cement Portfolio'!$O$8:$O$36,'Cement Portfolio'!$AQ$8:$AQ$36,"") -> 5535257.3 | O15: =IF(AND(Q15<0,R15<0,Q15<R15),Q15-R15,"") | P15: =IF(AND(Q15>=0,R15>=0,Q15>R15),Q15-R15,"") | Q15: =IFERROR(((K15-AA15)*100)/ABS($K$106),"") -> 0.23518124 | R15: =IFERROR((($AB15*$G15*0.9912*0.0001)-AC15)*100/ABS($AC$108),"") -> 15.044691 | S15: =IF(AND(R15>0,Q15>0,R15>Q15),R15-Q15,"") -> 14.80951 | T15: =IF(AND(R15<0,Q15<0,R15<Q15),R15-Q15,"") | V15: 229000 | W15: 235800 | X15: 235800 | Y15: 44486 | Z15: 5.3 | AA15: 14.148 | AB15: 230000 | AC15: 5375674.1
A16: =IFERROR(MATCH(C16,'دیده بان بازار'!$A$5:$A$3994,0 )+4,"Closed") -> 2229 | B16: سیمان اردستان | C16: اردستان | D16: C | F16: =IFERROR(_xlfn.LET(_xlpm.lookup_result,_xlfn.XLOOKUP($C16,'دیده بان بازار'!$A$5:$A$3994,'دیده بان بازار'!F$5:F$3994),IF(ISERROR(_xlpm.lookup_result),V16,_xlpm.lookup_result)),V16) -> 25710 | G16: =IFERROR(_xlfn.LET(_xlpm.lookup_result,_xlfn.XLOOKUP($C16,'دیده بان بازار'!$A$5:$A$3994,'دیده بان بازار'!H$5:H$3994),IF(ISERROR(_xlpm.lookup_result),W16,_xlpm.lookup_result)),W16) -> 26480 | H16: =IFERROR(_xlfn.LET(_xlpm.lookup_result,_xlfn.XLOOKUP($C16,'دیده بان بازار'!$A$5:$A$3994,'دیده بان بازار'!K$5:K$3994),IF(ISERROR(_xlpm.lookup_result),X16,_xlpm.lookup_result)),X16) -> 26480 | I16: =IFERROR(_xlfn.LET(_xlpm.lookup_result,_xlfn.XLOOKUP($C16,'دیده بان بازار'!$A$5:$A$3994,'دیده بان بازار'!P$5:P$3994),IF(ISERROR(_xlpm.lookup_result),Y16,_xlpm.lookup_result)),Y16) -> 5074 | J16: =IFERROR(_xlfn.LET(_xlpm.lookup_result,_xlfn.XLOOKUP($C16,'دیده بان بازار'!$A$5:$A$3994,'دیده بان بازار'!Q$5:Q$3994),IF(ISERROR(_xlpm.lookup_result),Z16,_xlpm.lookup_result)),Z16) -> 5.22 | K16: =_xlfn.XLOOKUP(C16,Cement!$Q$7:$Q$35,Cement!$S$7:$S$35,"")/1000 -> 6.01096 | L16: =_xlfn.XLOOKUP(C16,'Cement Portfolio'!$O$8:$O$36,'Cement Portfolio'!$AP$8:$AP$36,"") -> 0 | M16: =_xlfn.XLOOKUP(C16,'Cement Portfolio'!$O$8:$O$36,'Cement Portfolio'!$AQ$8:$AQ$36,"") -> 0 | O16: =IF(AND(Q16<0,R16<0,Q16<R16),Q16-R16,"") | P16: =IF(AND(Q16>=0,R16>=0,Q16>R16),Q16-R16,"") -> 0.097874591 | Q16: =IFERROR(((K16-AA16)*100)/ABS($K$106),"") -> 0.097874591 | R16: =IFERROR((($AB16*$G16*0.9912*0.0001)-AC16)*100/ABS($AC$108),"") -> 0 | S16: =IF(AND(R16>0,Q16>0,R16>Q16),R16-Q16,"") | T16: =IF(AND(R16<0,Q16<0,R16<Q16),R16-Q16,"") | V16: 24970 | W16: 25710 | X16: 25710 | Y16: 5074 | Z16: 5.07 | AA16: 5.83617 | AB16: 0 | AC16: 0
A17: =IFERROR(MATCH(C17,'دیده بان بازار'!$A$5:$A$3994,0 )+4,"Closed") -> 1389 | B17: سيمان‌ شمال‌ | C17: سشمال | D17: C | F17: =IFERROR(_xlfn.LET(_xlpm.lookup_result,_xlfn.XLOOKUP($C17,'دیده بان بازار'!$A$5:$A$3994,'دیده بان بازار'!F$5:F$3994),IF(ISERROR(_xlpm.lookup_result),V17,_xlpm.lookup_result)),V17) -> 14190 | G17: =IFERROR(_xlfn.LET(_xlpm.lookup_result,_xlfn.XLOOKUP($C17,'دیده بان بازار'!$A$5:$A$3994,'دیده بان بازار'!H$5:H$3994),IF(ISERROR(_xlpm.lookup_result),W17,_xlpm.lookup_result)),W17) -> 14610 | H17: =IFERROR(_xlfn.LET(_xlpm.lookup_result,_xlfn.XLOOKUP($C17,'دیده بان بازار'!$A$5:$A$3994,'دیده بان بازار'!K$5:K$3994),IF(ISERROR(_xlpm.lookup_result),X17,_xlpm.lookup_result)),X17) -> 14610 | I17: =IFERROR(_xlfn.LET(_xlpm.lookup_result,_xlfn.XLOOKUP($C17,'دیده بان بازار'!$A$5:$A$3994,'دیده بان بازار'!P$5:P$3994),IF(ISERROR(_xlpm.lookup_result),Y17,_xlpm.lookup_result)),Y17) -> 2372 | J17: =IFERROR(_xlfn.LET(_xlpm.lookup_result,_xlfn.XLOOKUP($C17,'دیده بان بازار'!$A$5:$A$3994,'دیده بان بازار'!Q$5:Q$3994),IF(ISERROR(_xlpm.lookup_result),Z17,_xlpm.lookup_result)),Z17) -> 6.16 | K17: =_xlfn.XLOOKUP(C17,Cement!$Q$7:$Q$35,Cement!$S$7:$S$35,"")/1000 -> 7.305 | L17: =_xlfn.XLOOKUP(C17,'Cement Portfolio'!$O$8:$O$36,'Cement Portfolio'!$AP$8:$AP$36,"") -> 72765 | M17: =_xlfn.XLOOKUP(C17,'Cement Portfolio'!$O$8:$O$36,'Cement Portfolio'!$AQ$8:$AQ$36,"") -> 105374.14 | O17: =IF(AND(Q17<0,R17<0,Q17<R17),Q17-R17,"") | P17: =IF(AND(Q17>=0,R17>=0,Q17>R17),Q17-R17,"") | Q17: =IFERROR(((K17-AA17)*100)/ABS($K$106),"") -> 0.11759062 | R17: =IFERROR((($AB17*$G17*0.9912*0.0001)-AC17)*100/ABS($AC$108),"") -> 0.28558094 | S17: =IF(AND(R17>0,Q17>0,R17>Q17),R17-Q17,"") -> 0.16799032 | T17: =IF(AND(R17<0,Q17<0,R17<Q17),R17-Q17,"") | V17: 13780 | W17: 14190 | X17: 14190 | Y17: 2372 | Z17: 5.98 | AA17: 7.095 | AB17: 72765 | AC17: 102344.9
... A34: =IFERROR(MATCH(C34,'دیده بان بازار'!$A$5:$A$3994,0 )+4,"Closed") -> 2722 | B34: سيمان آرتا اردبيل | C34: ساربيل | D34: C | F34: =IFERROR(_xlfn.LET(_xlpm.lookup_result,_xlfn.XLOOKUP($C34,'دیده بان بازار'!$A$5:$A$3994,'دیده بان بازار'!F$5:F$3994),IF(ISERROR(_xlpm.lookup_result),V34,_xlpm.lookup_result)),V34) -> 81220 | G34: =IFERROR(_xlfn.LET(_xlpm.lookup_result,_xlfn.XLOOKUP($C34,'دیده بان بازار'!$A$5:$A$3994,'دیده بان بازار'!H$5:H$3994),IF(ISERROR(_xlpm.lookup_result),W34,_xlpm.lookup_result)),W34) -> 83650 | H34: =IFERROR(_xlfn.LET(_xlpm.lookup_result,_xlfn.XLOOKUP($C34,'دیده بان بازار'!$A$5:$A$3994,'دیده بان بازار'!K$5:K$3994),IF(ISERROR(_xlpm.lookup_result),X34,_xlpm.lookup_result)),X34) -> 83270 | I34: =IFERROR(_xlfn.LET(_xlpm.lookup_result,_xlfn.XLOOKUP($C34,'دیده بان بازار'!$A$5:$A$3994,'دیده بان بازار'!P$5:P$3994),IF(ISERROR(_xlpm.lookup_result),Y34,_xlpm.lookup_result)),Y34) -> 11188 | J34: =IFERROR(_xlfn.LET(_xlpm.lookup_result,_xlfn.XLOOKUP($C34,'دیده بان بازار'!$A$5:$A$3994,'دیده بان بازار'!Q$5:Q$3994),IF(ISERROR(_xlpm.lookup_result),Z34,_xlpm.lookup_result)),Z34) -> 7.44 | K34: =_xlfn.XLOOKUP(C34,Cement!$Q$7:$Q$35,Cement!$S$7:$S$35,"")/1000 -> 12.0456 | L34: =_xlfn.XLOOKUP(C34,'Cement Portfolio'!$O$8:$O$36,'Cement Portfolio'!$AP$8:$AP$36,"") -> 0 | M34: =_xlfn.XLOOKUP(C34,'Cement Portfolio'!$O$8:$O$36,'Cement Portfolio'!$AQ$8:$AQ$36,"") -> 0 | O34: =IF(AND(Q34<0,R34<0,Q34<R34),Q34-R34,"") | P34: =IF(AND(Q34>=0,R34>=0,Q34>R34),Q34-R34,"") -> 0.1830382 | Q34: =IFERROR(((K34-AA34)*100)/ABS($K$106),"") -> 0.1830382 | R34: =IFERROR((($AB34*$G34*0.9912*0.0001)-AC34)*100/ABS($AC$108),"") -> 0 | S34: =IF(AND(R34>0,Q34>0,R34>Q34),R34-Q34,"") | T34: =IF(AND(R34<0,Q34<0,R34<Q34),R34-Q34,"") | V34: 79440 | W34: 81380 | X34: 81220 | Y34: 11188 | Z34: 7.26 | AA34: 11.71872 | AB34: 0 | AC34: 0
A36: =IFERROR(MATCH(C36,'دیده بان بازار'!$A$5:$A$3994,0 )+4,"Closed") -> 2187 | B36: توليدي برنا باطري | C36: خبرنا | D36: =_xlfn.XLOOKUP(C36,MOPFRA!$R$7:$R$56,MOPFRA!$P$7:$P$56,"") -> AP | F36: =IFERROR(_xlfn.LET(_xlpm.lookup_result,_xlfn.XLOOKUP($C36,'دیده بان بازار'!$A$5:$A$3994,'دیده بان بازار'!F$5:F$3994),IF(ISERROR(_xlpm.lookup_result),V36,_xlpm.lookup_result)),V36) -> 6400 | G36: =IFERROR(_xlfn.LET(_xlpm.lookup_result,_xlfn.XLOOKUP($C36,'دیده بان بازار'!$A$5:$A$3994,'دیده بان بازار'!H$5:H$3994),IF(ISERROR(_xlpm.lookup_result),W36,_xlpm.lookup_result)),W36) -> 6590 | H36: =IFERROR(_xlfn.LET(_xlpm.lookup_result,_xlfn.XLOOKUP($C36,'دیده بان بازار'!$A$5:$A$3994,'دیده بان بازار'!K$5:K$3994),IF(ISERROR(_xlpm.lookup_result),X36,_xlpm.lookup_result)),X36) -> 6570 | I36: =IFERROR(_xlfn.LET(_xlpm.lookup_result,_xlfn.XLOOKUP($C36,'دیده بان بازار'!$A$5:$A$3994,'دیده بان بازار'!P$5:P$3994),IF(ISERROR(_xlpm.lookup_result),Y36,_xlpm.lookup_result)),Y36) -> 1058 | J36: =IFERROR(_xlfn.LET(_xlpm.lookup_result,_xlfn.XLOOKUP($C36,'دیده بان بازار'!$A$5:$A$3994,'دیده بان بازار'!Q$5:Q$3994),IF(ISERROR(_xlpm.lookup_result),Z36,_xlpm.lookup_result)),Z36) -> 6.21 | K36: =_xlfn.XLOOKUP(C36,MOPFRA!$R$7:$R$56,MOPFRA!$T$7:$T$56,"")/1000 -> 3.295 | L36: =_xlfn.XLOOKUP(C36,'MOPFRA Portfolio'!$P$8:$P$78,'MOPFRA Portfolio'!$AT$8:$AT$78,"") -> 535000 | M36: =_xlfn.XLOOKUP(C36,'MOPFRA Portfolio'!$P$8:$P$78,'MOPFRA Portfolio'!$AU$8:$AU$78,"") -> 349462.43 | O36: =IF(AND(Q36<0,R36<0,Q36<R36),Q36-R36,"") | P36: =IF(AND(Q36>=0,R36>=0,Q36>R36),Q36-R36,"") | Q36: =IFERROR(((K36-AA36)*100)/ABS($K$106),"") -> 0.058795309 | R36: =IFERROR((($AB36*$G36*0.9912*0.0001)-AC36)*100/ABS($AC$108),"") -> 1.0498578 | S36: =IF(AND(R36>0,Q36>0,R36>Q36),R36-Q36,"") -> 0.99106247 | T36: =IF(AND(R36<0,Q36<0,R36<Q36),R36-Q36,"") | V36: 6250 | W36: 6380 | X36: 6400 | Y36: 1058 | Z36: 6.05 | AA36: 3.19 | AB36: 535000 | AC36: 338326.3
A37: =IFERROR(MATCH(C37,'دیده بان بازار'!$A$5:$A$3994,0 )+4,"Closed") -> 1107 | B37: آلوميناي ايران | C37: آلومينا | D37: =_xlfn.XLOOKUP(C37,MOPFRA!$R$7:$R$56,MOPFRA!$P$7:$P$56,"") -> AL | F37: =IFERROR(_xlfn.LET(_xlpm.lookup_result,_xlfn.XLOOKUP($C37,'دیده بان بازار'!$A$5:$A$3994,'دیده بان بازار'!F$5:F$3994),IF(ISERROR(_xlpm.lookup_result),V37,_xlpm.lookup_result)),V37) -> 148500 | G37: =IFERROR(_xlfn.LET(_xlpm.lookup_result,_xlfn.XLOOKUP($C37,'دیده بان بازار'!$A$5:$A$3994,'دیده بان بازار'!H$5:H$3994),IF(ISERROR(_xlpm.lookup_result),W37,_xlpm.lookup_result)),W37) -> 152900 | H37: =IFERROR(_xlfn.LET(_xlpm.lookup_result,_xlfn.XLOOKUP($C37,'دیده بان بازار'!$A$5:$A$3994,'دیده بان بازار'!K$5:K$3994),IF(ISERROR(_xlpm.lookup_result),X37,_xlpm.lookup_result)),X37) -> 152900 | I37: =IFERROR(_xlfn.LET(_xlpm.lookup_result,_xlfn.XLOOKUP($C37,'دیده بان بازار'!$A$5:$A$3994,'دیده بان بازار'!P$5:P$3994),IF(ISERROR(_xlpm.lookup_result),Y37,_xlpm.lookup_result)),Y37) -> 16822 | J37: =IFERROR(_xlfn.LET(_xlpm.lookup_result,_xlfn.XLOOKUP($C37,'دیده بان بازار'!$A$5:$A$3994,'دیده بان بازار'!Q$5:Q$3994),IF(ISERROR(_xlpm.lookup_result),Z37,_xlpm.lookup_result)),Z37) -> 9.09 | K37: =_xlfn.XLOOKUP(C37,MOPFRA!$R$7:$R$56,MOPFRA!$T$7:$T$56,"")/1000 -> 30.576468 | L37: =_xlfn.XLOOKUP(C37,'MOPFRA Portfolio'!$P$8:$P$78,'MOPFRA Portfolio'!$AT$8:$AT$78,"") -> 0 | M37: =_xlfn.XLOOKUP(C37,'MOPFRA Portfolio'!$P$8:$P$78,'MOPFRA Portfolio'!$AU$8:$AU$78,"") -> 0 | P37: =IF(AND(Q37>=0,R37>=0,Q37>R37),Q37-R37,"") -> 0.49270377 | Q37: =IFERROR(((K37-AA37)*100)/ABS($K$106),"") -> 0.49270377 | R37: =IFERROR((($AB37*$G37*0.9912*0.0001)-AC37)*100/ABS($AC$108),"") -> 0 | V37: 144200 | W37: 148500 | X37: 148500 | Y37: 16822 | Z37: 8.83 | AA37: 29.69657 | AB37: 0 | AC37: 0
A38: =IFERROR(MATCH(C38,'دیده بان بازار'!$A$5:$A$3994,0 )+4,"Closed") -> 2932 | B38: پاكسان‌ | C38: شپاكسا | D38: =_xlfn.XLOOKUP(C38,MOPFRA!$R$7:$R$56,MOPFRA!$P$7:$P$56,"") -> DH | F38: =IFERROR(_xlfn.LET(_xlpm.lookup_result,_xlfn.XLOOKUP($C38,'دیده بان بازار'!$A$5:$A$3994,'دیده بان بازار'!F$5:F$3994),IF(ISERROR(_xlpm.lookup_result),V38,_xlpm.lookup_result)),V38) -> 3340 | G38: =IFERROR(_xlfn.LET(_xlpm.lookup_result,_xlfn.XLOOKUP($C38,'دیده بان بازار'!$A$5:$A$3994,'دیده بان بازار'!H$5:H$3994),IF(ISERROR(_xlpm.lookup_result),W38,_xlpm.lookup_result)),W38) -> 3440 | H38: =IFERROR(_xlfn.LET(_xlpm.lookup_result,_xlfn.XLOOKUP($C38,'دیده بان بازار'!$A$5:$A$3994,'دیده بان بازار'!K$5:K$3994),IF(ISERROR(_xlpm.lookup_result),X38,_xlpm.lookup_result)),X38) -> 3440 | I38: =IFERROR(_xlfn.LET(_xlpm.lookup_result,_xlfn.XLOOKUP($C38,'دیده بان بازار'!$A$5:$A$3994,'دیده بان بازار'!P$5:P$3994),IF(ISERROR(_xlpm.lookup_result),Y38,_xlpm.lookup_result)),Y38) -> 590 | J38: =IFERROR(_xlfn.LET(_xlpm.lookup_result,_xlfn.XLOOKUP($C38,'دیده بان بازار'!$A$5:$A$3994,'دیده بان بازار'!Q$5:Q$3994),IF(ISERROR(_xlpm.lookup_result),Z38,_xlpm.lookup_result)),Z38) -> 5.83 | K38: =_xlfn.XLOOKUP(C38,MOPFRA!$R$7:$R$56,MOPFRA!$T$7:$T$56,"")/1000 -> 6.1232 | L38: =_xlfn.XLOOKUP(C38,'MOPFRA Portfolio'!$P$8:$P$78,'MOPFRA Portfolio'!$AT$8:$AT$78,"") -> 2100000 | M38: =_xlfn.XLOOKUP(C38,'MOPFRA Portfolio'!$P$8:$P$78,'MOPFRA Portfolio'!$AU$8:$AU$78,"") -> 716042.88 | O38: =IF(AND(Q38<0,R38<0,Q38<R38),Q38-R38,"") | P38: =IF(AND(Q38>=0,R38>=0,Q38>R38),Q38-R38,"") | Q38: =IFERROR(((K38-AA38)*100)/ABS($K$106),"") -> 0.099672048 | R38: =IFERROR((($AB38*$G38*0.9912*0.0001)-AC38)*100/ABS($AC$108),"") -> 2.0557963 | S38: =IF(AND(R38>0,Q38>0,R38>Q38),R38-Q38,"") -> 1.9561242 | T38: =IF(AND(R38<0,Q38<0,R38<Q38),R38-Q38,"") | V38: 3250 | W38: 3340 | X38: 3340 | Y38: 590 | Z38: 5.66 | AA38: 5.9452 | AB38: 2200000 | AC38: 728333.76
A39: =IFERROR(MATCH(C39,'دیده بان بازار'!$A$5:$A$3994,0 )+4,"Closed") -> Closed | B39: صنايع بهداشتي ساينا | C39: ساينا | D39: =_xlfn.XLOOKUP(C39,MOPFRA!$R$7:$R$56,MOPFRA!$P$7:$P$56,"") -> DH | F39: =IFERROR(_xlfn.LET(_xlpm.lookup_result,_xlfn.XLOOKUP($C39,'دیده بان بازار'!$A$5:$A$3994,'دیده بان بازار'!F$5:F$3994),IF(ISERROR(_xlpm.lookup_result),V39,_xlpm.lookup_result)),V39) -> 9820 | G39: =IFERROR(_xlfn.LET(_xlpm.lookup_result,_xlfn.XLOOKUP($C39,'دیده بان بازار'!$A$5:$A$3994,'دیده بان بازار'!H$5:H$3994),IF(ISERROR(_xlpm.lookup_result),W39,_xlpm.lookup_result)),W39) -> 10110 | H39: =IFERROR(_xlfn.LET(_xlpm.lookup_result,_xlfn.XLOOKUP($C39,'دیده بان بازار'!$A$5:$A$3994,'دیده بان بازار'!K$5:K$3994),IF(ISERROR(_xlpm.lookup_result),X39,_xlpm.lookup_result)),X39) -> 10110 | I39: =IFERROR(_xlfn.LET(_xlpm.lookup_result,_xlfn.XLOOKUP($C39,'دیده بان بازار'!$A$5:$A$3994,'دیده بان بازار'!P$5:P$3994),IF(ISERROR(_xlpm.lookup_result),Y39,_xlpm.lookup_result)),Y39) -> 1886 | J39: =IFERROR(_xlfn.LET(_xlpm.lookup_result,_xlfn.XLOOKUP($C39,'دیده بان بازار'!$A$5:$A$3994,'دیده بان بازار'!Q$5:Q$3994),IF(ISERROR(_xlpm.lookup_result),Z39,_xlpm.lookup_result)),Z39) -> 5.36 | K39: =_xlfn.XLOOKUP(C39,MOPFRA!$R$7:$R$56,MOPFRA!$T$7:$T$56,"")/1000 -> 2.1231 | L39: =_xlfn.XLOOKUP(C39,'MOPFRA Portfolio'!$P$8:$P$78,'MOPFRA Portfolio'!$AT$8:$AT$78,"") -> 0 | M39: =_xlfn.XLOOKUP(C39,'MOPFRA Portfolio'!$P$8:$P$78,'MOPFRA Portfolio'!$AU$8:$AU$78,"") -> 0 | O39: =IF(AND(Q39<0,R39<0,Q39<R39),Q39-R39,"") | P39: =IF(AND(Q39>=0,R39>=0,Q39>R39),Q39-R39,"") | Q39: =IFERROR(((K39-AA39)*100)/ABS($K$106),"") -> 0 | R39: =IFERROR((($AB39*$G39*0.9912*0.0001)-AC39)*100/ABS($AC$108),"") -> 0 | S39: =IF(AND(R39>0,Q39>0,R39>Q39),R39-Q39,"") | T39: =IF(AND(R39<0,Q39<0,R39<Q39),R39-Q39,"") | V39: 9820 | W39: 10110 | X39: 10110 | Y39: 1886 | Z39: 5.36 | AA39: 2.1231 | AB39: 0 | AC39: 0
A40: =IFERROR(MATCH(C40,'دیده بان بازار'!$A$5:$A$3994,0 )+4,"Closed") -> 1697 | B40: گلتاش‌ | C40: شگل | D40: =_xlfn.XLOOKUP(C40,MOPFRA!$R$7:$R$56,MOPFRA!$P$7:$P$56,"") -> DH | F40: =IFERROR(_xlfn.LET(_xlpm.lookup_result,_xlfn.XLOOKUP($C40,'دیده بان بازار'!$A$5:$A$3994,'دیده بان بازار'!F$5:F$3994),IF(ISERROR(_xlpm.lookup_result),V40,_xlpm.lookup_result)),V40) -> 2839 | G40: =IFERROR(_xlfn.LET(_xlpm.lookup_result,_xlfn.XLOOKUP($C40,'دیده بان بازار'!$A$5:$A$3994,'دیده بان بازار'!H$5:H$3994),IF(ISERROR(_xlpm.lookup_result),W40,_xlpm.lookup_result)),W40) -> 2826 | H40: =IFERROR(_xlfn.LET(_xlpm.lookup_result,_xlfn.XLOOKUP($C40,'دیده بان بازار'!$A$5:$A$3994,'دیده بان بازار'!K$5:K$3994),IF(ISERROR(_xlpm.lookup_result),X40,_xlpm.lookup_result)),X40) -> 2816 | I40: =IFERROR(_xlfn.LET(_xlpm.lookup_result,_xlfn.XLOOKUP($C40,'دیده بان بازار'!$A$5:$A$3994,'دیده بان بازار'!P$5:P$3994),IF(ISERROR(_xlpm.lookup_result),Y40,_xlpm.lookup_result)),Y40) -> 352 | J40: =IFERROR(_xlfn.LET(_xlpm.lookup_result,_xlfn.XLOOKUP($C40,'دیده بان بازار'!$A$5:$A$3994,'دیده بان بازار'!Q$5:Q$3994),IF(ISERROR(_xlpm.lookup_result),Z40,_xlpm.lookup_result)),Z40) -> 8 | K40: =_xlfn.XLOOKUP(C40,MOPFRA!$R$7:$R$56,MOPFRA!$T$7:$T$56,"")/1000 -> 4.8042 | L40: =_xlfn.XLOOKUP(C40,'MOPFRA Portfolio'!$P$8:$P$78,'MOPFRA Portfolio'!$AT$8:$AT$78,"") -> 35288 | M40: =_xlfn.XLOOKUP(C40,'MOPFRA Portfolio'!$P$8:$P$78,'MOPFRA Portfolio'!$AU$8:$AU$78,"") -> 9884.6318 | P40: =IF(AND(Q40>=0,R40>=0,Q40>R40),Q40-R40,"") -> 0.01392908 | Q40: =IFERROR(((K40-AA40)*100)/ABS($K$106),"") -> 0.03046157 | R40: =IFERROR((($AB40*$G40*0.9912*0.0001)-AC40)*100/ABS($AC$108),"") -> 0.016532489 | V40: 2000 | W40: 2794 | X40: 2839 | Y40: 352 | Z40: 8.07 | AA40: 4.7498 | AB40: 55288 | AC40: 15311.529
A41: =IFERROR(MATCH(C41,'دیده بان بازار'!$A$5:$A$3994,0 )+4,"Closed") -> 1456 | B41: سالمين‌ | C41: غسالم | D41: =_xlfn.XLOOKUP(C41,MOPFRA!$R$7:$R$56,MOPFRA!$P$7:$P$56,"") -> F | F41: =IFERROR(_xlfn.LET(_xlpm.lookup_result,_xlfn.XLOOKUP($C41,'دیده بان بازار'!$A$5:$A$3994,'دیده بان بازار'!F$5:F$3994),IF(ISERROR(_xlpm.lookup_result),V41,_xlpm.lookup_result)),V41) -> 7910 | G41: =IFERROR(_xlfn.LET(_xlpm.lookup_result,_xlfn.XLOOKUP($C41,'دیده بان بازار'!$A$5:$A$3994,'دیده بان بازار'!H$5:H$3994),IF(ISERROR(_xlpm.lookup_result),W41,_xlpm.lookup_result)),W41) -> 8140 | H41: =IFERROR(_xlfn.LET(_xlpm.lookup_result,_xlfn.XLOOKUP($C41,'دیده بان بازار'!$A$5:$A$3994,'دیده بان بازار'!K$5:K$3994),IF(ISERROR(_xlpm.lookup_result),X41,_xlpm.lookup_result)),X41) -> 8140 | I41: =IFERROR(_xlfn.LET(_xlpm.lookup_result,_xlfn.XLOOKUP($C41,'دیده بان بازار'!$A$5:$A$3994,'دیده بان بازار'!P$5:P$3994),IF(ISERROR(_xlpm.lookup_result),Y41,_xlpm.lookup_result)),Y41) -> 1348 | J41: =IFERROR(_xlfn.LET(_xlpm.lookup_result,_xlfn.XLOOKUP($C41,'دیده بان بازار'!$A$5:$A$3994,'دیده بان بازار'!Q$5:Q$3994),IF(ISERROR(_xlpm.lookup_result),Z41,_xlpm.lookup_result)),Z41) -> 6.04 | K41: =_xlfn.XLOOKUP(C41,MOPFRA!$R$7:$R$56,MOPFRA!$T$7:$T$56,"")/1000 -> 4.884 | L41: =_xlfn.XLOOKUP(C41,'MOPFRA Portfolio'!$P$8:$P$78,'MOPFRA Portfolio'!$AT$8:$AT$78,"") -> 160000 | M41: =_xlfn.XLOOKUP(C41,'MOPFRA Portfolio'!$P$8:$P$78,'MOPFRA Portfolio'!$AU$8:$AU$78,"") -> 129093.89 | O41: =IF(AND(Q41<0,R41<0,Q41<R41),Q41-R41,"") | P41: =IF(AND(Q41>=0,R41>=0,Q41>R41),Q41-R41,"") | Q41: =IFERROR(((K41-AA41)*100)/ABS($K$106),"") -> 0.077273835 | R41: =IFERROR((($AB41*$G41*0.9912*0.0001)-AC41)*100/ABS($AC$108),"") -> 0.34387865 | S41: =IF(AND(R41>0,Q41>0,R41>Q41),R41-Q41,"") -> 0.26660482 | T41: =IF(AND(R41<0,Q41<0,R41<Q41),R41-Q41,"") | V41: 7680 | W41: 7910 | X41: 7910 | Y41: 1348 | Z41: 5.87 | AA41: 4.746 | AB41: 160000 | AC41: 125446.27
A42: =IFERROR(MATCH(C42,'دیده بان بازار'!$A$5:$A$3994,0 )+4,"Closed") -> 2099 | B42: شركت صنايع غذايي مينو شرق | C42: غمينو | D42: =_xlfn.XLOOKUP(C42,MOPFRA!$R$7:$R$56,MOPFRA!$P$7:$P$56,"") -> F | F42: =IFERROR(_xlfn.LET(_xlpm.lookup_result,_xlfn.XLOOKUP($C42,'دیده بان بازار'!$A$5:$A$3994,'دیده بان بازار'!F$5:F$3994),IF(ISERROR(_xlpm.lookup_result),V42,_xlpm.lookup_result)),V42) -> 8270 | G42: =IFERROR(_xlfn.LET(_xlpm.lookup_result,_xlfn.XLOOKUP($C42,'دیده بان بازار'!$A$5:$A$3994,'دیده بان بازار'!H$5:H$3994),IF(ISERROR(_xlpm.lookup_result),W42,_xlpm.lookup_result)),W42) -> 8410 | H42: =IFERROR(_xlfn.LET(_xlpm.lookup_result,_xlfn.XLOOKUP($C42,'دیده بان بازار'!$A$5:$A$3994,'دیده بان بازار'!K$5:K$3994),IF(ISERROR(_xlpm.lookup_result),X42,_xlpm.lookup_result)),X42) -> 8370 | I42: =IFERROR(_xlfn.LET(_xlpm.lookup_result,_xlfn.XLOOKUP($C42,'دیده بان بازار'!$A$5:$A$3994,'دیده بان بازار'!P$5:P$3994),IF(ISERROR(_xlpm.lookup_result),Y42,_xlpm.lookup_result)),Y42) -> 1231 | J42: =IFERROR(_xlfn.LET(_xlpm.lookup_result,_xlfn.XLOOKUP($C42,'دیده بان بازار'!$A$5:$A$3994,'دیده بان بازار'!Q$5:Q$3994),IF(ISERROR(_xlpm.lookup_result),Z42,_xlpm.lookup_result)),Z42) -> 6.8 | K42: =_xlfn.XLOOKUP(C42,MOPFRA!$R$7:$R$56,MOPFRA!$T$7:$T$56,"")/1000 -> 5.887 | L42: =_xlfn.XLOOKUP(C42,'MOPFRA Portfolio'!$P$8:$P$78,'MOPFRA Portfolio'!$AT$8:$AT$78,"") -> 650000 | M42: =_xlfn.XLOOKUP(C42,'MOPFRA Portfolio'!$P$8:$P$78,'MOPFRA Portfolio'!$AU$8:$AU$78,"") -> 541839.48 | O42: =IF(AND(Q42<0,R42<0,Q42<R42),Q42-R42,"") | P42: =IF(AND(Q42>=0,R42>=0,Q42>R42),Q42-R42,"") | Q42: =IFERROR(((K42-AA42)*100)/ABS($K$106),"") -> 0.054875622 | R42: =IFERROR((($AB42*$G42*0.9912*0.0001)-AC42)*100/ABS($AC$108),"") -> 0.8503521 | S42: =IF(AND(R42>0,Q42>0,R42>Q42),R42-Q42,"") -> 0.79547647 | T42: =IF(AND(R42<0,Q42<0,R42<Q42),R42-Q42,"") | V42: 8050 | W42: 8270 | X42: 8270 | Y42: 1231 | Z42: 6.72 | AA42: 5.789 | AB42: 650000 | AC42: 532819.56
A43: =IFERROR(MATCH(C43,'دیده بان بازار'!$A$5:$A$3994,0 )+4,"Closed") -> 2106 | B43: توليدي‌مهرام‌ | C43: غمهرا | D43: =_xlfn.XLOOKUP(C43,MOPFRA!$R$7:$R$56,MOPFRA!$P$7:$P$56,"") -> F | F43: =IFERROR(_xlfn.LET(_xlpm.lookup_result,_xlfn.XLOOKUP($C43,'دیده بان بازار'!$A$5:$A$3994,'دیده بان بازار'!F$5:F$3994),IF(ISERROR(_xlpm.lookup_result),V43,_xlpm.lookup_result)),V43) -> 17340 | G43: =IFERROR(_xlfn.LET(_xlpm.lookup_result,_xlfn.XLOOKUP($C43,'دیده بان بازار'!$A$5:$A$3994,'دیده بان بازار'!H$5:H$3994),IF(ISERROR(_xlpm.lookup_result),W43,_xlpm.lookup_result)),W43) -> 17860 | H43: =IFERROR(_xlfn.LET(_xlpm.lookup_result,_xlfn.XLOOKUP($C43,'دیده بان بازار'!$A$5:$A$3994,'دیده بان بازار'!K$5:K$3994),IF(ISERROR(_xlpm.lookup_result),X43,_xlpm.lookup_result)),X43) -> 17850 | I43: =IFERROR(_xlfn.LET(_xlpm.lookup_result,_xlfn.XLOOKUP($C43,'دیده بان بازار'!$A$5:$A$3994,'دیده بان بازار'!P$5:P$3994),IF(ISERROR(_xlpm.lookup_result),Y43,_xlpm.lookup_result)),Y43) -> 2564 | J43: =IFERROR(_xlfn.LET(_xlpm.lookup_result,_xlfn.XLOOKUP($C43,'دیده بان بازار'!$A$5:$A$3994,'دیده بان بازار'!Q$5:Q$3994),IF(ISERROR(_xlpm.lookup_result),Z43,_xlpm.lookup_result)),Z43) -> 6.96 | K43: =_xlfn.XLOOKUP(C43,MOPFRA!$R$7:$R$56,MOPFRA!$T$7:$T$56,"")/1000 -> 8.93 | L43: =_xlfn.XLOOKUP(C43,'MOPFRA Portfolio'!$P$8:$P$78,'MOPFRA Portfolio'!$AT$8:$AT$78,"") -> 110000 | M43: =_xlfn.XLOOKUP(C43,'MOPFRA Portfolio'!$P$8:$P$78,'MOPFRA Portfolio'!$AU$8:$AU$78,"") -> 194731.15 | O43: =IF(AND(Q43<0,R43<0,Q43<R43),Q43-R43,"") | P43: =IF(AND(Q43>=0,R43>=0,Q43>R43),Q43-R43,"") | Q43: =IFERROR(((K43-AA43)*100)/ABS($K$106),"") -> 0.14558838 | R43: =IFERROR((($AB43*$G43*0.9912*0.0001)-AC43)*100/ABS($AC$108),"") -> 0.53450703 | S43: =IF(AND(R43>0,Q43>0,R43>Q43),R43-Q43,"") -> 0.38891865 | T43: =IF(AND(R43<0,Q43<0,R43<Q43),R43-Q43,"") | V43: 16840 | W43: 17340 | X43: 17340 | Y43: 2564 | Z43: 6.76 | AA43: 8.67 | AB43: 110000 | AC43: 189061.49
A44: =IFERROR(MATCH(C44,'دیده بان بازار'!$A$5:$A$3994,0 )+4,"Closed") -> 2376 | B44: صنعت غذايي كورش | C44: غكورش | D44: =_xlfn.XLOOKUP(C44,MOPFRA!$R$7:$R$56,MOPFRA!$P$7:$P$56,"") -> F | F44: =IFERROR(_xlfn.LET(_xlpm.lookup_result,_xlfn.XLOOKUP($C44,'دیده بان بازار'!$A$5:$A$3994,'دیده بان بازار'!F$5:F$3994),IF(ISERROR(_xlpm.lookup_result),V44,_xlpm.lookup_result)),V44) -> 18640 | G44: =IFERROR(_xlfn.LET(_xlpm.lookup_result,_xlfn.XLOOKUP($C44,'دیده بان بازار'!$A$5:$A$3994,'دیده بان بازار'!H$5:H$3994),IF(ISERROR(_xlpm.lookup_result),W44,_xlpm.lookup_result)),W44) -> 19190 | H44: =IFERROR(_xlfn.LET(_xlpm.lookup_result,_xlfn.XLOOKUP($C44,'دیده بان بازار'!$A$5:$A$3994,'دیده بان بازار'!K$5:K$3994),IF(ISERROR(_xlpm.lookup_result),X44,_xlpm.lookup_result)),X44) -> 19170 | I44: =IFERROR(_xlfn.LET(_xlpm.lookup_result,_xlfn.XLOOKUP($C44,'دیده بان بازار'!$A$5:$A$3994,'دیده بان بازار'!P$5:P$3994),IF(ISERROR(_xlpm.lookup_result),Y44,_xlpm.lookup_result)),Y44) -> 2993 | J44: =IFERROR(_xlfn.LET(_xlpm.lookup_result,_xlfn.XLOOKUP($C44,'دیده بان بازار'!$A$5:$A$3994,'دیده بان بازار'!Q$5:Q$3994),IF(ISERROR(_xlpm.lookup_result),Z44,_xlpm.lookup_result)),Z44) -> 6.4 | K44: =_xlfn.XLOOKUP(C44,MOPFRA!$R$7:$R$56,MOPFRA!$T$7:$T$56,"")/1000 -> 84.436 | L44: =_xlfn.XLOOKUP(C44,'MOPFRA Portfolio'!$P$8:$P$78,'MOPFRA Portfolio'!$AT$8:$AT$78,"") -> 0 | M44: =_xlfn.XLOOKUP(C44,'MOPFRA Portfolio'!$P$8:$P$78,'MOPFRA Portfolio'!$AU$8:$AU$78,"") -> 0 | P44: =IF(AND(Q44>=0,R44>=0,Q44>R44),Q44-R44,"") -> 1.453644 | Q44: =IFERROR(((K44-AA44)*100)/ABS($K$106),"") -> 1.453644 | R44: =IFERROR((($AB44*$G44*0.9912*0.0001)-AC44)*100/ABS($AC$108),"") -> 0 | V44: 18110 | W44: 18600 | X44: 18640 | Y44: 2993 | Z44: 6.23 | AA44: 81.84 | AB44: 0 | AC44: 0
A45: =IFERROR(MATCH(C45,'دیده بان بازار'!$A$5:$A$3994,0 )+4,"Closed") -> 254 | B45: صنعتي زر ماكارون | C45: غزر | D45: =_xlfn.XLOOKUP(C45,MOPFRA!$R$7:$R$56,MOPFRA!$P$7:$P$56,"") -> F | F45: =IFERROR(_xlfn.LET(_xlpm.lookup_result,_xlfn.XLOOKUP($C45,'دیده بان بازار'!$A$5:$A$3994,'دیده بان بازار'!F$5:F$3994),IF(ISERROR(_xlpm.lookup_result),V45,_xlpm.lookup_result)),V45) -> 3264 | G45: =IFERROR(_xlfn.LET(_xlpm.lookup_result,_xlfn.XLOOKUP($C45,'دیده بان بازار'!$A$5:$A$3994,'دیده بان بازار'!H$5:H$3994),IF(ISERROR(_xlpm.lookup_result),W45,_xlpm.lookup_result)),W45) -> 3361 | H45: =IFERROR(_xlfn.LET(_xlpm.lookup_result,_xlfn.XLOOKUP($C45,'دیده بان بازار'!$A$5:$A$3994,'دیده بان بازار'!K$5:K$3994),IF(ISERROR(_xlpm.lookup_result),X45,_xlpm.lookup_result)),X45) -> 3361 | I45: =IFERROR(_xlfn.LET(_xlpm.lookup_result,_xlfn.XLOOKUP($C45,'دیده بان بازار'!$A$5:$A$3994,'دیده بان بازار'!P$5:P$3994),IF(ISERROR(_xlpm.lookup_result),Y45,_xlpm.lookup_result)),Y45) -> 620 | J45: =IFERROR(_xlfn.LET(_xlpm.lookup_result,_xlfn.XLOOKUP($C45,'دیده بان بازار'!$A$5:$A$3994,'دیده بان بازار'!Q$5:Q$3994),IF(ISERROR(_xlpm.lookup_result),Z45,_xlpm.lookup_result)),Z45) -> 5.42 | K45: =_xlfn.XLOOKUP(C45,MOPFRA!$R$7:$R$56,MOPFRA!$T$7:$T$56,"")/1000 -> 14.4523 | L45: =_xlfn.XLOOKUP(C45,'MOPFRA Portfolio'!$P$8:$P$78,'MOPFRA Portfolio'!$AT$8:$AT$78,"") -> 0 | M45: =_xlfn.XLOOKUP(C45,'MOPFRA Portfolio'!$P$8:$P$78,'MOPFRA Portfolio'!$AU$8:$AU$78,"") -> 0 | P45: =IF(AND(Q45>=0,R45>=0,Q45>R45),Q45-R45,"") -> 0.23355737 | Q45: =IFERROR(((K45-AA45)*100)/ABS($K$106),"") -> 0.23355737 | R45: =IFERROR((($AB45*$G45*0.9912*0.0001)-AC45)*100/ABS($AC$108),"") -> 0 | V45: 3169 | W45: 3264 | X45: 3264 | Y45: 620 | Z45: 5.26 | AA45: 14.0352 | AB45: 0 | AC45: 0
A46: =IFERROR(MATCH(C46,'دیده بان بازار'!$A$5:$A$3994,0 )+4,"Closed") -> 1749 | B46: كشاورزي و دامپروري فجر اصفهان | C46: زفجر | D46: =_xlfn.XLOOKUP(C46,MOPFRA!$R$7:$R$56,MOPFRA!$P$7:$P$56,"") -> F | F46: =IFERROR(_xlfn.LET(_xlpm.lookup_result,_xlfn.XLOOKUP($C46,'دیده بان بازار'!$A$5:$A$3994,'دیده بان بازار'!F$5:F$3994),IF(ISERROR(_xlpm.lookup_result),V46,_xlpm.lookup_result)),V46) -> 44440 | G46: =IFERROR(_xlfn.LET(_xlpm.lookup_result,_xlfn.XLOOKUP($C46,'دیده بان بازار'!$A$5:$A$3994,'دیده بان بازار'!H$5:H$3994),IF(ISERROR(_xlpm.lookup_result),W46,_xlpm.lookup_result)),W46) -> 45770 | H46: =IFERROR(_xlfn.LET(_xlpm.lookup_result,_xlfn.XLOOKUP($C46,'دیده بان بازار'!$A$5:$A$3994,'دیده بان بازار'!K$5:K$3994),IF(ISERROR(_xlpm.lookup_result),X46,_xlpm.lookup_result)),X46) -> 45770 | I46: =IFERROR(_xlfn.LET(_xlpm.lookup_result,_xlfn.XLOOKUP($C46,'دیده بان بازار'!$A$5:$A$3994,'دیده بان بازار'!P$5:P$3994),IF(ISERROR(_xlpm.lookup_result),Y46,_xlpm.lookup_result)),Y46) -> 7903 | J46: =IFERROR(_xlfn.LET(_xlpm.lookup_result,_xlfn.XLOOKUP($C46,'دیده بان بازار'!$A$5:$A$3994,'دیده بان بازار'!Q$5:Q$3994),IF(ISERROR(_xlpm.lookup_result),Z46,_xlpm.lookup_result)),Z46) -> 5.79 | K46: =_xlfn.XLOOKUP(C46,MOPFRA!$R$7:$R$56,MOPFRA!$T$7:$T$56,"")/1000 -> 4.1193 | L46: =_xlfn.XLOOKUP(C46,'MOPFRA Portfolio'!$P$8:$P$78,'MOPFRA Portfolio'!$AT$8:$AT$78,"") -> 10000 | M46: =_xlfn.XLOOKUP(C46,'MOPFRA Portfolio'!$P$8:$P$78,'MOPFRA Portfolio'!$AU$8:$AU$78,"") -> 45367.224 | P46: =IF(AND(Q46>=0,R46>=0,Q46>R46),Q46-R46,"") | Q46: =IFERROR(((K46-AA46)*100)/ABS($K$106),"") -> 0.063498934 | R46: =IFERROR((($AB46*$G46*0.9912*0.0001)-AC46)*100/ABS($AC$108),"") -> 0.11774106 | V46: 43220 | W46: 44510 | X46: 44440 | Y46: 7903 | Z46: 5.62 | AA46: 4.0059 | AB46: 10000 | AC46: 44118.312
A47: =IFERROR(MATCH(C47,'دیده بان بازار'!$A$5:$A$3994,0 )+4,"Closed") -> 2338 | B47: صنايع الكترونيك ماديران | C47: الكتروماد | D47: =_xlfn.XLOOKUP(C47,MOPFRA!$R$7:$R$56,MOPFRA!$P$7:$P$56,"") -> HH | F47: =IFERROR(_xlfn.LET(_xlpm.lookup_result,_xlfn.XLOOKUP($C47,'دیده بان بازار'!$A$5:$A$3994,'دیده بان بازار'!F$5:F$3994),IF(ISERROR(_xlpm.lookup_result),V47,_xlpm.lookup_result)),V47) -> 3520 | G47: =IFERROR(_xlfn.LET(_xlpm.lookup_result,_xlfn.XLOOKUP($C47,'دیده بان بازار'!$A$5:$A$3994,'دیده بان بازار'!H$5:H$3994),IF(ISERROR(_xlpm.lookup_result),W47,_xlpm.lookup_result)),W47) -> 3620 | H47: =IFERROR(_xlfn.LET(_xlpm.lookup_result,_xlfn.XLOOKUP($C47,'دیده بان بازار'!$A$5:$A$3994,'دیده بان بازار'!K$5:K$3994),IF(ISERROR(_xlpm.lookup_result),X47,_xlpm.lookup_result)),X47) -> 3620 | I47: =IFERROR(_xlfn.LET(_xlpm.lookup_result,_xlfn.XLOOKUP($C47,'دیده بان بازار'!$A$5:$A$3994,'دیده بان بازار'!P$5:P$3994),IF(ISERROR(_xlpm.lookup_result),Y47,_xlpm.lookup_result)),Y47) -> 957 | J47: =IFERROR(_xlfn.LET(_xlpm.lookup_result,_xlfn.XLOOKUP($C47,'دیده بان بازار'!$A$5:$A$3994,'دیده بان بازار'!Q$5:Q$3994),IF(ISERROR(_xlpm.lookup_result),Z47,_xlpm.lookup_result)),Z47) -> 3.78 | K47: =_xlfn.XLOOKUP(C47,MOPFRA!$R$7:$R$56,MOPFRA!$T$7:$T$56,"")/1000 -> 3.258 | L47: =_xlfn.XLOOKUP(C47,'MOPFRA Portfolio'!$P$8:$P$78,'MOPFRA Portfolio'!$AT$8:$AT$78,"") -> 600000 | M47: =_xlfn.XLOOKUP(C47,'MOPFRA Portfolio'!$P$8:$P$78,'MOPFRA Portfolio'!$AU$8:$AU$78,"") -> 215288.64 | O47: =IF(AND(Q47<0,R47<0,Q47<R47),Q47-R47,"") | P47: =IF(AND(Q47>=0,R47>=0,Q47>R47),Q47-R47,"") | Q47: =IFERROR(((K47-AA47)*100)/ABS($K$106),"") -> 0.050395979 | R47: =IFERROR((($AB47*$G47*0.9912*0.0001)-AC47)*100/ABS($AC$108),"") -> 0.28033586 | S47: =IF(AND(R47>0,Q47>0,R47>Q47),R47-Q47,"") -> 0.22993988 | T47: =IF(AND(R47<0,Q47<0,R47<Q47),R47-Q47,"") | V47: 3420 | W47: 3520 | X47: 3520 | Y47: 957 | Z47: 3.68 | AA47: 3.168 | AB47: 300000 | AC47: 104670.72
A48: =IFERROR(MATCH(C48,'دیده بان بازار'!$A$5:$A$3994,0 )+4,"Closed") -> 1191 | B48: پارس‌ خزر | C48: لخزر | D48: =_xlfn.XLOOKUP(C48,MOPFRA!$R$7:$R$56,MOPFRA!$P$7:$P$56,"") -> HL | F48: =IFERROR(_xlfn.LET(_xlpm.lookup_result,_xlfn.XLOOKUP($C48,'دیده بان بازار'!$A$5:$A$3994,'دیده بان بازار'!F$5:F$3994),IF(ISERROR(_xlpm.lookup_result),V48,_xlpm.lookup_result)),V48) -> 3290 | G48: =IFERROR(_xlfn.LET(_xlpm.lookup_result,_xlfn.XLOOKUP($C48,'دیده بان بازار'!$A$5:$A$3994,'دیده بان بازار'!H$5:H$3994),IF(ISERROR(_xlpm.lookup_result),W48,_xlpm.lookup_result)),W48) -> 3380 | H48: =IFERROR(_xlfn.LET(_xlpm.lookup_result,_xlfn.XLOOKUP($C48,'دیده بان بازار'!$A$5:$A$3994,'دیده بان بازار'!K$5:K$3994),IF(ISERROR(_xlpm.lookup_result),X48,_xlpm.lookup_result)),X48) -> 3380 | I48: =IFERROR(_xlfn.LET(_xlpm.lookup_result,_xlfn.XLOOKUP($C48,'دیده بان بازار'!$A$5:$A$3994,'دیده بان بازار'!P$5:P$3994),IF(ISERROR(_xlpm.lookup_result),Y48,_xlpm.lookup_result)),Y48) -> 1120 | J48: =IFERROR(_xlfn.LET(_xlpm.lookup_result,_xlfn.XLOOKUP($C48,'دیده بان بازار'!$A$5:$A$3994,'دیده بان بازار'!Q$5:Q$3994),IF(ISERROR(_xlpm.lookup_result),Z48,_xlpm.lookup_result)),Z48) -> 3.02 | K48: =_xlfn.XLOOKUP(C48,MOPFRA!$R$7:$R$56,MOPFRA!$T$7:$T$56,"")/1000 -> 3.38 | L48: =_xlfn.XLOOKUP(C48,'MOPFRA Portfolio'!$P$8:$P$78,'MOPFRA Portfolio'!$AT$8:$AT$78,"") -> 0 | M48: =_xlfn.XLOOKUP(C48,'MOPFRA Portfolio'!$P$8:$P$78,'MOPFRA Portfolio'!$AU$8:$AU$78,"") -> 0 | O48: =IF(AND(Q48<0,R48<0,Q48<R48),Q48-R48,"") | P48: =IF(AND(Q48>=0,R48>=0,Q48>R48),Q48-R48,"") -> 0.050395979 | Q48: =IFERROR(((K48-AA48)*100)/ABS($K$106),"") -> 0.050395979 | R48: =IFERROR((($AB48*$G48*0.9912*0.0001)-AC48)*100/ABS($AC$108),"") -> 0 | S48: =IF(AND(R48>0,Q48>0,R48>Q48),R48-Q48,"") | T48: =IF(AND(R48<0,Q48<0,R48<Q48),R48-Q48,"") | V48: 3200 | W48: 3290 | X48: 3290 | Y48: 1120 | Z48: 2.94 | AA48: 3.29 | AB48: 0 | AC48: 0
A49: =IFERROR(MATCH(C49,'دیده بان بازار'!$A$5:$A$3994,0 )+4,"Closed") -> 1875 | B49: توسعه فن افزار توسن | C49: فن‌ افزار | D49: =_xlfn.XLOOKUP(C49,MOPFRA!$R$7:$R$56,MOPFRA!$P$7:$P$56,"") -> IT | F49: =IFERROR(_xlfn.LET(_xlpm.lookup_result,_xlfn.XLOOKUP($C49,'دیده بان بازار'!$A$5:$A$3994,'دیده بان بازار'!F$5:F$3994),IF(ISERROR(_xlpm.lookup_result),V49,_xlpm.lookup_result)),V49) -> 7230 | G49: =IFERROR(_xlfn.LET(_xlpm.lookup_result,_xlfn.XLOOKUP($C49,'دیده بان بازار'!$A$5:$A$3994,'دیده بان بازار'!H$5:H$3994),IF(ISERROR(_xlpm.lookup_result),W49,_xlpm.lookup_result)),W49) -> 7440 | H49: =IFERROR(_xlfn.LET(_xlpm.lookup_result,_xlfn.XLOOKUP($C49,'دیده بان بازار'!$A$5:$A$3994,'دیده بان بازار'!K$5:K$3994),IF(ISERROR(_xlpm.lookup_result),X49,_xlpm.lookup_result)),X49) -> 7440 | I49: =IFERROR(_xlfn.LET(_xlpm.lookup_result,_xlfn.XLOOKUP($C49,'دیده بان بازار'!$A$5:$A$3994,'دیده بان بازار'!P$5:P$3994),IF(ISERROR(_xlpm.lookup_result),Y49,_xlpm.lookup_result)),Y49) -> 1478 | J49: =IFERROR(_xlfn.LET(_xlpm.lookup_result,_xlfn.XLOOKUP($C49,'دیده بان بازار'!$A$5:$A$3994,'دیده بان بازار'!Q$5:Q$3994),IF(ISERROR(_xlpm.lookup_result),Z49,_xlpm.lookup_result)),Z49) -> 5.03 | K49: =_xlfn.XLOOKUP(C49,MOPFRA!$R$7:$R$56,MOPFRA!$T$7:$T$56,"")/1000 -> 4.464 | L49: =_xlfn.XLOOKUP(C49,'MOPFRA Portfolio'!$P$8:$P$78,'MOPFRA Portfolio'!$AT$8:$AT$78,"") -> 0 | M49: =_xlfn.XLOOKUP(C49,'MOPFRA Portfolio'!$P$8:$P$78,'MOPFRA Portfolio'!$AU$8:$AU$78,"") -> 0 | O49: =IF(AND(Q49<0,R49<0,Q49<R49),Q49-R49,"") | P49: =IF(AND(Q49>=0,R49>=0,Q49>R49),Q49-R49,"") -> 0.070554371 | Q49: =IFERROR(((K49-AA49)*100)/ABS($K$106),"") -> 0.070554371 | R49: =IFERROR((($AB49*$G49*0.9912*0.0001)-AC49)*100/ABS($AC$108),"") -> 0 | S49: =IF(AND(R49>0,Q49>0,R49>Q49),R49-Q49,"") | T49: =IF(AND(R49<0,Q49<0,R49<Q49),R49-Q49,"") | V49: 7020 | W49: 7230 | X49: 7230 | Y49: 1478 | Z49: 4.89 | AA49: 4.338 | AB49: 0 | AC49: 0
A50: =IFERROR(MATCH(C50,'دیده بان بازار'!$A$5:$A$3994,0 )+4,"Closed") -> 2917 | B50: گروه‌صنعتي‌سپاهان‌ | C50: فسپا | D50: =_xlfn.XLOOKUP(C50,MOPFRA!$R$7:$R$56,MOPFRA!$P$7:$P$56,"") -> M | F50: =IFERROR(_xlfn.LET(_xlpm.lookup_result,_xlfn.XLOOKUP($C50,'دیده بان بازار'!$A$5:$A$3994,'دیده بان بازار'!F$5:F$3994),IF(ISERROR(_xlpm.lookup_result),V50,_xlpm.lookup_result)),V50) -> 4510 | G50: =IFERROR(_xlfn.LET(_xlpm.lookup_result,_xlfn.XLOOKUP($C50,'دیده بان بازار'!$A$5:$A$3994,'دیده بان بازار'!H$5:H$3994),IF(ISERROR(_xlpm.lookup_result),W50,_xlpm.lookup_result)),W50) -> 4640 | H50: =IFERROR(_xlfn.LET(_xlpm.lookup_result,_xlfn.XLOOKUP($C50,'دیده بان بازار'!$A$5:$A$3994,'دیده بان بازار'!K$5:K$3994),IF(ISERROR(_xlpm.lookup_result),X50,_xlpm.lookup_result)),X50) -> 4640 | I50: =IFERROR(_xlfn.LET(_xlpm.lookup_result,_xlfn.XLOOKUP($C50,'دیده بان بازار'!$A$5:$A$3994,'دیده بان بازار'!P$5:P$3994),IF(ISERROR(_xlpm.lookup_result),Y50,_xlpm.lookup_result)),Y50) -> 1216 | J50: =IFERROR(_xlfn.LET(_xlpm.lookup_result,_xlfn.XLOOKUP($C50,'دیده بان بازار'!$A$5:$A$3994,'دیده بان بازار'!Q$5:Q$3994),IF(ISERROR(_xlpm.lookup_result),Z50,_xlpm.lookup_result)),Z50) -> 3.82 | K50: =_xlfn.XLOOKUP(C50,MOPFRA!$R$7:$R$56,MOPFRA!$T$7:$T$56,"")/1000 -> 5.8 | L50: =_xlfn.XLOOKUP(C50,'MOPFRA Portfolio'!$P$8:$P$78,'MOPFRA Portfolio'!$AT$8:$AT$78,"") -> 800000 | M50: =_xlfn.XLOOKUP(C50,'MOPFRA Portfolio'!$P$8:$P$78,'MOPFRA Portfolio'!$AU$8:$AU$78,"") -> 367933.44 | O50: =IF(AND(Q50<0,R50<0,Q50<R50),Q50-R50,"") | P50: =IF(AND(Q50>=0,R50>=0,Q50>R50),Q50-R50,"") | Q50: =IFERROR(((K50-AA50)*100)/ABS($K$106),"") -> 0.09099274 | R50: =IFERROR((($AB50*$G50*0.9912*0.0001)-AC50)*100/ABS($AC$108),"") -> 0.97183097 | S50: =IF(AND(R50>0,Q50>0,R50>Q50),R50-Q50,"") -> 0.88083823 | T50: =IF(AND(R50<0,Q50<0,R50<Q50),R50-Q50,"") | V50: 4380 | W50: 4510 | X50: 4510 | Y50: 1216 | Z50: 3.71 | AA50: 5.6375 | AB50: 800000 | AC50: 357624.96
A51: =IFERROR(MATCH(C51,'دیده بان بازار'!$A$5:$A$3994,0 )+4,"Closed") -> 211 | B51: فولاد اميركبيركاشان | C51: فجر | D51: =_xlfn.XLOOKUP(C51,MOPFRA!$R$7:$R$56,MOPFRA!$P$7:$P$56,"") -> M | F51: =IFERROR(_xlfn.LET(_xlpm.lookup_result,_xlfn.XLOOKUP($C51,'دیده بان بازار'!$A$5:$A$3994,'دیده بان بازار'!F$5:F$3994),IF(ISERROR(_xlpm.lookup_result),V51,_xlpm.lookup_result)),V51) -> 4840 | G51: =IFERROR(_xlfn.LET(_xlpm.lookup_result,_xlfn.XLOOKUP($C51,'دیده بان بازار'!$A$5:$A$3994,'دیده بان بازار'!H$5:H$3994),IF(ISERROR(_xlpm.lookup_result),W51,_xlpm.lookup_result)),W51) -> 4980 | H51: =IFERROR(_xlfn.LET(_xlpm.lookup_result,_xlfn.XLOOKUP($C51,'دیده بان بازار'!$A$5:$A$3994,'دیده بان بازار'!K$5:K$3994),IF(ISERROR(_xlpm.lookup_result),X51,_xlpm.lookup_result)),X51) -> 4980 | I51: =IFERROR(_xlfn.LET(_xlpm.lookup_result,_xlfn.XLOOKUP($C51,'دیده بان بازار'!$A$5:$A$3994,'دیده بان بازار'!P$5:P$3994),IF(ISERROR(_xlpm.lookup_result),Y51,_xlpm.lookup_result)),Y51) -> 1065 | J51: =IFERROR(_xlfn.LET(_xlpm.lookup_result,_xlfn.XLOOKUP($C51,'دیده بان بازار'!$A$5:$A$3994,'دیده بان بازار'!Q$5:Q$3994),IF(ISERROR(_xlpm.lookup_result),Z51,_xlpm.lookup_result)),Z51) -> 4.68 | K51: =_xlfn.XLOOKUP(C51,MOPFRA!$R$7:$R$56,MOPFRA!$T$7:$T$56,"")/1000 -> 9.96 | L51: =_xlfn.XLOOKUP(C51,'MOPFRA Portfolio'!$P$8:$P$78,'MOPFRA Portfolio'!$AT$8:$AT$78,"") -> 500000 | M51: =_xlfn.XLOOKUP(C51,'MOPFRA Portfolio'!$P$8:$P$78,'MOPFRA Portfolio'!$AU$8:$AU$78,"") -> 246808.8 | O51: =IF(AND(Q51<0,R51<0,Q51<R51),Q51-R51,"") | P51: =IF(AND(Q51>=0,R51>=0,Q51>R51),Q51-R51,"") | Q51: =IFERROR(((K51-AA51)*100)/ABS($K$106),"") -> 0.15678749 | R51: =IFERROR((($AB51*$G51*0.9912*0.0001)-AC51)*100/ABS($AC$108),"") -> 0.654117 | S51: =IF(AND(R51>0,Q51>0,R51>Q51),R51-Q51,"") -> 0.49732951 | T51: =IF(AND(R51<0,Q51<0,R51<Q51),R51-Q51,"") | V51: 4700 | W51: 4840 | X51: 4840 | Y51: 1065 | Z51: 4.54 | AA51: 9.68 | AB51: 500000 | AC51: 239870.4
A52: =IFERROR(MATCH(C52,'دیده بان بازار'!$A$5:$A$3994,0 )+4,"Closed") -> Closed | B52: فولاد مباركه اصفهان | C52: فولاد | D52: =_xlfn.XLOOKUP(C52,MOPFRA!$R$7:$R$56,MOPFRA!$P$7:$P$56,"") -> M | F52: =IFERROR(_xlfn.LET(_xlpm.lookup_result,_xlfn.XLOOKUP($C52,'دیده بان بازار'!$A$5:$A$3994,'دیده بان بازار'!F$5:F$3994),IF(ISERROR(_xlpm.lookup_result),V52,_xlpm.lookup_result)),V52) -> 2604 | G52: =IFERROR(_xlfn.LET(_xlpm.lookup_result,_xlfn.XLOOKUP($C52,'دیده بان بازار'!$A$5:$A$3994,'دیده بان بازار'!H$5:H$3994),IF(ISERROR(_xlpm.lookup_result),W52,_xlpm.lookup_result)),W52) -> 2549 | H52: =IFERROR(_xlfn.LET(_xlpm.lookup_result,_xlfn.XLOOKUP($C52,'دیده بان بازار'!$A$5:$A$3994,'دیده بان بازار'!K$5:K$3994),IF(ISERROR(_xlpm.lookup_result),X52,_xlpm.lookup_result)),X52) -> 2549 | I52: =IFERROR(_xlfn.LET(_xlpm.lookup_result,_xlfn.XLOOKUP($C52,'دیده بان بازار'!$A$5:$A$3994,'دیده بان بازار'!P$5:P$3994),IF(ISERROR(_xlpm.lookup_result),Y52,_xlpm.lookup_result)),Y52) -> 518 | J52: =IFERROR(_xlfn.LET(_xlpm.lookup_result,_xlfn.XLOOKUP($C52,'دیده بان بازار'!$A$5:$A$3994,'دیده بان بازار'!Q$5:Q$3994),IF(ISERROR(_xlpm.lookup_result),Z52,_xlpm.lookup_result)),Z52) -> 5.03 | K52: =_xlfn.XLOOKUP(C52,MOPFRA!$R$7:$R$56,MOPFRA!$T$7:$T$56,"")/1000 -> 493.2315 | L52: =_xlfn.XLOOKUP(C52,'MOPFRA Portfolio'!$P$8:$P$78,'MOPFRA Portfolio'!$AT$8:$AT$78,"") -> 0 | M52: =_xlfn.XLOOKUP(C52,'MOPFRA Portfolio'!$P$8:$P$78,'MOPFRA Portfolio'!$AU$8:$AU$78,"") -> 0 | O52: =IF(AND(Q52<0,R52<0,Q52<R52),Q52-R52,"") | P52: =IF(AND(Q52>=0,R52>=0,Q52>R52),Q52-R52,"") | Q52: =IFERROR(((K52-AA52)*100)/ABS($K$106),"") -> 0 | R52: =IFERROR((($AB52*$G52*0.9912*0.0001)-AC52)*100/ABS($AC$108),"") -> 0 | S52: =IF(AND(R52>0,Q52>0,R52>Q52),R52-Q52,"") | T52: =IF(AND(R52<0,Q52<0,R52<Q52),R52-Q52,"") | V52: 2604 | W52: 2549 | X52: 2549 | Y52: 518 | Z52: 5.03 | AA52: 493.2315 | AB52: 0 | AC52: 0
A53: =IFERROR(MATCH(C53,'دیده بان بازار'!$A$5:$A$3994,0 )+4,"Closed") -> 2285 | B53: پارس فولاد سبزوار | C53: فسبزوار | D53: =_xlfn.XLOOKUP(C53,MOPFRA!$R$7:$R$56,MOPFRA!$P$7:$P$56,"") -> M | F53: =IFERROR(_xlfn.LET(_xlpm.lookup_result,_xlfn.XLOOKUP($C53,'دیده بان بازار'!$A$5:$A$3994,'دیده بان بازار'!F$5:F$3994),IF(ISERROR(_xlpm.lookup_result),V53,_xlpm.lookup_result)),V53) -> 65760 | G53: =IFERROR(_xlfn.LET(_xlpm.lookup_result,_xlfn.XLOOKUP($C53,'دیده بان بازار'!$A$5:$A$3994,'دیده بان بازار'!H$5:H$3994),IF(ISERROR(_xlpm.lookup_result),W53,_xlpm.lookup_result)),W53) -> 67730 | H53: =IFERROR(_xlfn.LET(_xlpm.lookup_result,_xlfn.XLOOKUP($C53,'دیده بان بازار'!$A$5:$A$3994,'دیده بان بازار'!K$5:K$3994),IF(ISERROR(_xlpm.lookup_result),X53,_xlpm.lookup_result)),X53) -> 67620 | I53: =IFERROR(_xlfn.LET(_xlpm.lookup_result,_xlfn.XLOOKUP($C53,'دیده بان بازار'!$A$5:$A$3994,'دیده بان بازار'!P$5:P$3994),IF(ISERROR(_xlpm.lookup_result),Y53,_xlpm.lookup_result)),Y53) -> 14832 | J53: =IFERROR(_xlfn.LET(_xlpm.lookup_result,_xlfn.XLOOKUP($C53,'دیده بان بازار'!$A$5:$A$3994,'دیده بان بازار'!Q$5:Q$3994),IF(ISERROR(_xlpm.lookup_result),Z53,_xlpm.lookup_result)),Z53) -> 4.56 | K53: =_xlfn.XLOOKUP(C53,MOPFRA!$R$7:$R$56,MOPFRA!$T$7:$T$56,"")/1000 -> 27.092 | L53: =_xlfn.XLOOKUP(C53,'MOPFRA Portfolio'!$P$8:$P$78,'MOPFRA Portfolio'!$AT$8:$AT$78,"") -> 45000 | M53: =_xlfn.XLOOKUP(C53,'MOPFRA Portfolio'!$P$8:$P$78,'MOPFRA Portfolio'!$AU$8:$AU$78,"") -> 302102.89 | O53: =IF(AND(Q53<0,R53<0,Q53<R53),Q53-R53,"") | P53: =IF(AND(Q53>=0,R53>=0,Q53>R53),Q53-R53,"") | Q53: =IFERROR(((K53-AA53)*100)/ABS($K$106),"") -> 0.36733069 | R53: =IFERROR((($AB53*$G53*0.9912*0.0001)-AC53)*100/ABS($AC$108),"") -> 0.68962621 | S53: =IF(AND(R53>0,Q53>0,R53>Q53),R53-Q53,"") -> 0.32229551 | T53: =IF(AND(R53<0,Q53<0,R53<Q53),R53-Q53,"") | V53: 64170 | W53: 66090 | X53: 65760 | Y53: 14832 | Z53: 4.43 | AA53: 26.436 | AB53: 45000 | AC53: 294787.84
A54: =IFERROR(MATCH(C54,'دیده بان بازار'!$A$5:$A$3994,0 )+4,"Closed") -> 1128 | B54: صبا فولاد خليج فارس | C54: فصبا | D54: =_xlfn.XLOOKUP(C54,MOPFRA!$R$7:$R$56,MOPFRA!$P$7:$P$56,"") -> M | F54: =IFERROR(_xlfn.LET(_xlpm.lookup_result,_xlfn.XLOOKUP($C54,'دیده بان بازار'!$A$5:$A$3994,'دیده بان بازار'!F$5:F$3994),IF(ISERROR(_xlpm.lookup_result),V54,_xlpm.lookup_result)),V54) -> 2714 | G54: =IFERROR(_xlfn.LET(_xlpm.lookup_result,_xlfn.XLOOKUP($C54,'دیده بان بازار'!$A$5:$A$3994,'دیده بان بازار'!H$5:H$3994),IF(ISERROR(_xlpm.lookup_result),W54,_xlpm.lookup_result)),W54) -> 2795 | H54: =IFERROR(_xlfn.LET(_xlpm.lookup_result,_xlfn.XLOOKUP($C54,'دیده بان بازار'!$A$5:$A$3994,'دیده بان بازار'!K$5:K$3994),IF(ISERROR(_xlpm.lookup_result),X54,_xlpm.lookup_result)),X54) -> 2795 | I54: =IFERROR(_xlfn.LET(_xlpm.lookup_result,_xlfn.XLOOKUP($C54,'دیده بان بازار'!$A$5:$A$3994,'دیده بان بازار'!P$5:P$3994),IF(ISERROR(_xlpm.lookup_result),Y54,_xlpm.lookup_result)),Y54) -> 158 | J54: =IFERROR(_xlfn.LET(_xlpm.lookup_result,_xlfn.XLOOKUP($C54,'دیده بان بازار'!$A$5:$A$3994,'دیده بان بازار'!Q$5:Q$3994),IF(ISERROR(_xlpm.lookup_result),Z54,_xlpm.lookup_result)),Z54) -> 17.69 | K54: =_xlfn.XLOOKUP(C54,MOPFRA!$R$7:$R$56,MOPFRA!$T$7:$T$56,"")/1000 -> 13.975 | L54: =_xlfn.XLOOKUP(C54,'MOPFRA Portfolio'!$P$8:$P$78,'MOPFRA Portfolio'!$AT$8:$AT$78,"") -> 2678001 | M54: =_xlfn.XLOOKUP(C54,'MOPFRA Portfolio'!$P$8:$P$78,'MOPFRA Portfolio'!$AU$8:$AU$78,"") -> 741914.47 | O54: =IF(AND(Q54<0,R54<0,Q54<R54),Q54-R54,"") | P54: =IF(AND(Q54>=0,R54>=0,Q54>R54),Q54-R54,"") | Q54: =IFERROR(((K54-AA54)*100)/ABS($K$106),"") -> 0.21838258 | R54: =IFERROR((($AB54*$G54*0.9912*0.0001)-AC54)*100/ABS($AC$108),"") -> 1.9519232 | S54: =IF(AND(R54>0,Q54>0,R54>Q54),R54-Q54,"") -> 1.7335407 | T54: =IF(AND(R54<0,Q54<0,R54<Q54),R54-Q54,"") | V54: 2638 | W54: 2717 | X54: 2714 | Y54: 158 | Z54: 17.18 | AA54: 13.585 | AB54: 2678001 | AC54: 721209.88
A55: =IFERROR(MATCH(C55,'دیده بان بازار'!$A$5:$A$3994,0 )+4,"Closed") -> 2504 | B55: فولاد سيرجان ايرانيان | C55: سيسكو | D55: =_xlfn.XLOOKUP(C55,MOPFRA!$R$7:$R$56,MOPFRA!$P$7:$P$56,"") -> M | F55: =IFERROR(_xlfn.LET(_xlpm.lookup_result,_xlfn.XLOOKUP($C55,'دیده بان بازار'!$A$5:$A$3994,'دیده بان بازار'!F$5:F$3994),IF(ISERROR(_xlpm.lookup_result),V55,_xlpm.lookup_result)),V55) -> 3990 | G55: =IFERROR(_xlfn.LET(_xlpm.lookup_result,_xlfn.XLOOKUP($C55,'دیده بان بازار'!$A$5:$A$3994,'دیده بان بازار'!H$5:H$3994),IF(ISERROR(_xlpm.lookup_result),W55,_xlpm.lookup_result)),W55) -> 4100 | H55: =IFERROR(_xlfn.LET(_xlpm.lookup_result,_xlfn.XLOOKUP($C55,'دیده بان بازار'!$A$5:$A$3994,'دیده بان بازار'!K$5:K$3994),IF(ISERROR(_xlpm.lookup_result),X55,_xlpm.lookup_result)),X55) -> 4100 | I55: =IFERROR(_xlfn.LET(_xlpm.lookup_result,_xlfn.XLOOKUP($C55,'دیده بان بازار'!$A$5:$A$3994,'دیده بان بازار'!P$5:P$3994),IF(ISERROR(_xlpm.lookup_result),Y55,_xlpm.lookup_result)),Y55) -> 813 | J55: =IFERROR(_xlfn.LET(_xlpm.lookup_result,_xlfn.XLOOKUP($C55,'دیده بان بازار'!$A$5:$A$3994,'دیده بان بازار'!Q$5:Q$3994),IF(ISERROR(_xlpm.lookup_result),Z55,_xlpm.lookup_result)),Z55) -> 5.04 | K55: =_xlfn.XLOOKUP(C55,MOPFRA!$R$7:$R$56,MOPFRA!$T$7:$T$56,"")/1000 -> 51.25 | L55: =_xlfn.XLOOKUP(C55,'MOPFRA Portfolio'!$P$8:$P$78,'MOPFRA Portfolio'!$AT$8:$AT$78,"") -> 0 | M55: =_xlfn.XLOOKUP(C55,'MOPFRA Portfolio'!$P$8:$P$78,'MOPFRA Portfolio'!$AU$8:$AU$78,"") -> 0 | O55: =IF(AND(Q55<0,R55<0,Q55<R55),Q55-R55,"") | P55: =IF(AND(Q55>=0,R55>=0,Q55>R55),Q55-R55,"") -> 0.76993857 | Q55: =IFERROR(((K55-AA55)*100)/ABS($K$106),"") -> 0.76993857 | R55: =IFERROR((($AB55*$G55*0.9912*0.0001)-AC55)*100/ABS($AC$108),"") -> 0 | S55: =IF(AND(R55>0,Q55>0,R55>Q55),R55-Q55,"") | T55: =IF(AND(R55<0,Q55<0,R55<Q55),R55-Q55,"") | V55: 3880 | W55: 3990 | X55: 3990 | Y55: 813 | Z55: 4.91 | AA55: 49.875 | AB55: 0 | AC55: 0
A56: =IFERROR(MATCH(C56,'دیده بان بازار'!$A$5:$A$3994,0 )+4,"Closed") -> 616 | B56: ملي‌ صنايع‌ مس‌ ايران‌ | C56: فملي | D56: =_xlfn.XLOOKUP(C56,MOPFRA!$R$7:$R$56,MOPFRA!$P$7:$P$56,"") -> CO | F56: =IFERROR(_xlfn.LET(_xlpm.lookup_result,_xlfn.XLOOKUP($C56,'دیده بان بازار'!$A$5:$A$3994,'دیده بان بازار'!F$5:F$3994),IF(ISERROR(_xlpm.lookup_result),V56,_xlpm.lookup_result)),V56) -> 15750 | G56: =IFERROR(_xlfn.LET(_xlpm.lookup_result,_xlfn.XLOOKUP($C56,'دیده بان بازار'!$A$5:$A$3994,'دیده بان بازار'!H$5:H$3994),IF(ISERROR(_xlpm.lookup_result),W56,_xlpm.lookup_result)),W56) -> 16220 | H56: =IFERROR(_xlfn.LET(_xlpm.lookup_result,_xlfn.XLOOKUP($C56,'دیده بان بازار'!$A$5:$A$3994,'دیده بان بازار'!K$5:K$3994),IF(ISERROR(_xlpm.lookup_result),X56,_xlpm.lookup_result)),X56) -> 16220 | I56: =IFERROR(_xlfn.LET(_xlpm.lookup_result,_xlfn.XLOOKUP($C56,'دیده بان بازار'!$A$5:$A$3994,'دیده بان بازار'!P$5:P$3994),IF(ISERROR(_xlpm.lookup_result),Y56,_xlpm.lookup_result)),Y56) -> 1411 | J56: =IFERROR(_xlfn.LET(_xlpm.lookup_result,_xlfn.XLOOKUP($C56,'دیده بان بازار'!$A$5:$A$3994,'دیده بان بازار'!Q$5:Q$3994),IF(ISERROR(_xlpm.lookup_result),Z56,_xlpm.lookup_result)),Z56) -> 11.5 | K56: =_xlfn.XLOOKUP(C56,MOPFRA!$R$7:$R$56,MOPFRA!$T$7:$T$56,"")/1000 -> 2335.68 | L56: =_xlfn.XLOOKUP(C56,'MOPFRA Portfolio'!$P$8:$P$78,'MOPFRA Portfolio'!$AT$8:$AT$78,"") -> 0 | M56: =_xlfn.XLOOKUP(C56,'MOPFRA Portfolio'!$P$8:$P$78,'MOPFRA Portfolio'!$AU$8:$AU$78,"") -> 0 | O56: =IF(AND(Q56<0,R56<0,Q56<R56),Q56-R56,"") | P56: =IF(AND(Q56>=0,R56>=0,Q56>R56),Q56-R56,"") -> 37.897776 | Q56: =IFERROR(((K56-AA56)*100)/ABS($K$106),"") -> 37.897776 | R56: =IFERROR((($AB56*$G56*0.9912*0.0001)-AC56)*100/ABS($AC$108),"") -> 0 | S56: =IF(AND(R56>0,Q56>0,R56>Q56),R56-Q56,"") | T56: =IF(AND(R56<0,Q56<0,R56<Q56),R56-Q56,"") | V56: 15300 | W56: 15750 | X56: 15750 | Y56: 1411 | Z56: 11.16 | AA56: 2268 | AB56: 0 | AC56: 0
A57: =IFERROR(MATCH(C57,'دیده بان بازار'!$A$5:$A$3994,0 )+4,"Closed") -> 568 | B57: مس‌ شهيدباهنر | C57: فباهنر | D57: =_xlfn.XLOOKUP(C57,MOPFRA!$R$7:$R$56,MOPFRA!$P$7:$P$56,"") -> CO | F57: =IFERROR(_xlfn.LET(_xlpm.lookup_result,_xlfn.XLOOKUP($C57,'دیده بان بازار'!$A$5:$A$3994,'دیده بان بازار'!F$5:F$3994),IF(ISERROR(_xlpm.lookup_result),V57,_xlpm.lookup_result)),V57) -> 10490 | G57: =IFERROR(_xlfn.LET(_xlpm.lookup_result,_xlfn.XLOOKUP($C57,'دیده بان بازار'!$A$5:$A$3994,'دیده بان بازار'!H$5:H$3994),IF(ISERROR(_xlpm.lookup_result),W57,_xlpm.lookup_result)),W57) -> 10800 | H57: =IFERROR(_xlfn.LET(_xlpm.lookup_result,_xlfn.XLOOKUP($C57,'دیده بان بازار'!$A$5:$A$3994,'دیده بان بازار'!K$5:K$3994),IF(ISERROR(_xlpm.lookup_result),X57,_xlpm.lookup_result)),X57) -> 10800 | I57: =IFERROR(_xlfn.LET(_xlpm.lookup_result,_xlfn.XLOOKUP($C57,'دیده بان بازار'!$A$5:$A$3994,'دیده بان بازار'!P$5:P$3994),IF(ISERROR(_xlpm.lookup_result),Y57,_xlpm.lookup_result)),Y57) -> 1069 | J57: =IFERROR(_xlfn.LET(_xlpm.lookup_result,_xlfn.XLOOKUP($C57,'دیده بان بازار'!$A$5:$A$3994,'دیده بان بازار'!Q$5:Q$3994),IF(ISERROR(_xlpm.lookup_result),Z57,_xlpm.lookup_result)),Z57) -> 10.1 | K57: =_xlfn.XLOOKUP(C57,MOPFRA!$R$7:$R$56,MOPFRA!$T$7:$T$56,"")/1000 -> 26.549999 | L57: =_xlfn.XLOOKUP(C57,'MOPFRA Portfolio'!$P$8:$P$78,'MOPFRA Portfolio'!$AT$8:$AT$78,"") -> 0 | M57: =_xlfn.XLOOKUP(C57,'MOPFRA Portfolio'!$P$8:$P$78,'MOPFRA Portfolio'!$AU$8:$AU$78,"") -> 0 | O57: =IF(AND(Q57<0,R57<0,Q57<R57),Q57-R57,"") | P57: =IF(AND(Q57>=0,R57>=0,Q57>R57),Q57-R57,"") -> 0.41296703 | Q57: =IFERROR(((K57-AA57)*100)/ABS($K$106),"") -> 0.41296703 | R57: =IFERROR((($AB57*$G57*0.9912*0.0001)-AC57)*100/ABS($AC$108),"") -> 0 | S57: =IF(AND(R57>0,Q57>0,R57>Q57),R57-Q57,"") | T57: =IF(AND(R57<0,Q57<0,R57<Q57),R57-Q57,"") | V57: 10200 | W57: 10500 | X57: 10490 | Y57: 1069 | Z57: 9.81 | AA57: 25.812499 | AB57: 0 | AC57: 0
A58: =IFERROR(MATCH(C58,'دیده بان بازار'!$A$5:$A$3994,0 )+4,"Closed") -> 2799 | B58: فرآورده‌هاي‌نسوزآذر | C58: كاذر | D58: =_xlfn.XLOOKUP(C58,MOPFRA!$R$7:$R$56,MOPFRA!$P$7:$P$56,"") -> KN | F58: =IFERROR(_xlfn.LET(_xlpm.lookup_result,_xlfn.XLOOKUP($C58,'دیده بان بازار'!$A$5:$A$3994,'دیده بان بازار'!F$5:F$3994),IF(ISERROR(_xlpm.lookup_result),V58,_xlpm.lookup_result)),V58) -> 3540 | G58: =IFERROR(_xlfn.LET(_xlpm.lookup_result,_xlfn.XLOOKUP($C58,'دیده بان بازار'!$A$5:$A$3994,'دیده بان بازار'!H$5:H$3994),IF(ISERROR(_xlpm.lookup_result),W58,_xlpm.lookup_result)),W58) -> 3640 | H58: =IFERROR(_xlfn.LET(_xlpm.lookup_result,_xlfn.XLOOKUP($C58,'دیده بان بازار'!$A$5:$A$3994,'دیده بان بازار'!K$5:K$3994),IF(ISERROR(_xlpm.lookup_result),X58,_xlpm.lookup_result)),X58) -> 3640 | I58: =IFERROR(_xlfn.LET(_xlpm.lookup_result,_xlfn.XLOOKUP($C58,'دیده بان بازار'!$A$5:$A$3994,'دیده بان بازار'!P$5:P$3994),IF(ISERROR(_xlpm.lookup_result),Y58,_xlpm.lookup_result)),Y58) -> 612 | J58: =IFERROR(_xlfn.LET(_xlpm.lookup_result,_xlfn.XLOOKUP($C58,'دیده بان بازار'!$A$5:$A$3994,'دیده بان بازار'!Q$5:Q$3994),IF(ISERROR(_xlpm.lookup_result),Z58,_xlpm.lookup_result)),Z58) -> 5.95 | K58: =_xlfn.XLOOKUP(C58,MOPFRA!$R$7:$R$56,MOPFRA!$T$7:$T$56,"")/1000 -> 1.456 | L58: =_xlfn.XLOOKUP(C58,'MOPFRA Portfolio'!$P$8:$P$78,'MOPFRA Portfolio'!$AT$8:$AT$78,"") -> 0 | M58: =_xlfn.XLOOKUP(C58,'MOPFRA Portfolio'!$P$8:$P$78,'MOPFRA Portfolio'!$AU$8:$AU$78,"") -> 0 | O58: =IF(AND(Q58<0,R58<0,Q58<R58),Q58-R58,"") | P58: =IF(AND(Q58>=0,R58>=0,Q58>R58),Q58-R58,"") -> 0.022398213 | Q58: =IFERROR(((K58-AA58)*100)/ABS($K$106),"") -> 0.022398213 | R58: =IFERROR((($AB58*$G58*0.9912*0.0001)-AC58)*100/ABS($AC$108),"") -> 0 | S58: =IF(AND(R58>0,Q58>0,R58>Q58),R58-Q58,"") | T58: =IF(AND(R58<0,Q58<0,R58<Q58),R58-Q58,"") | V58: 3440 | W58: 3540 | X58: 3540 | Y58: 612 | Z58: 5.78 | AA58: 1.416 | AB58: 0 | AC58: 0
A59: =IFERROR(MATCH(C59,'دیده بان بازار'!$A$5:$A$3994,0 )+4,"Closed") -> 1303 | B59: شيشه‌ همدان‌ | C59: كهمدا | D59: =_xlfn.XLOOKUP(C59,MOPFRA!$R$7:$R$56,MOPFRA!$P$7:$P$56,"") -> KN | F59: =IFERROR(_xlfn.LET(_xlpm.lookup_result,_xlfn.XLOOKUP($C59,'دیده بان بازار'!$A$5:$A$3994,'دیده بان بازار'!F$5:F$3994),IF(ISERROR(_xlpm.lookup_result),V59,_xlpm.lookup_result)),V59) -> 4770 | G59: =IFERROR(_xlfn.LET(_xlpm.lookup_result,_xlfn.XLOOKUP($C59,'دیده بان بازار'!$A$5:$A$3994,'دیده بان بازار'!H$5:H$3994),IF(ISERROR(_xlpm.lookup_result),W59,_xlpm.lookup_result)),W59) -> 4720 | H59: =IFERROR(_xlfn.LET(_xlpm.lookup_result,_xlfn.XLOOKUP($C59,'دیده بان بازار'!$A$5:$A$3994,'دیده بان بازار'!K$5:K$3994),IF(ISERROR(_xlpm.lookup_result),X59,_xlpm.lookup_result)),X59) -> 4690 | I59: =IFERROR(_xlfn.LET(_xlpm.lookup_result,_xlfn.XLOOKUP($C59,'دیده بان بازار'!$A$5:$A$3994,'دیده بان بازار'!P$5:P$3994),IF(ISERROR(_xlpm.lookup_result),Y59,_xlpm.lookup_result)),Y59) -> 742 | J59: =IFERROR(_xlfn.LET(_xlpm.lookup_result,_xlfn.XLOOKUP($C59,'دیده بان بازار'!$A$5:$A$3994,'دیده بان بازار'!Q$5:Q$3994),IF(ISERROR(_xlpm.lookup_result),Z59,_xlpm.lookup_result)),Z59) -> 6.32 | K59: =_xlfn.XLOOKUP(C59,MOPFRA!$R$7:$R$56,MOPFRA!$T$7:$T$56,"")/1000 -> 7.788 | L59: =_xlfn.XLOOKUP(C59,'MOPFRA Portfolio'!$P$8:$P$78,'MOPFRA Portfolio'!$AT$8:$AT$78,"") -> 0 | M59: =_xlfn.XLOOKUP(C59,'MOPFRA Portfolio'!$P$8:$P$78,'MOPFRA Portfolio'!$AU$8:$AU$78,"") -> 0 | O59: =IF(AND(Q59<0,R59<0,Q59<R59),Q59-R59,"") | P59: =IF(AND(Q59>=0,R59>=0,Q59>R59),Q59-R59,"") -> 0.027717789 | Q59: =IFERROR(((K59-AA59)*100)/ABS($K$106),"") -> 0.027717789 | R59: =IFERROR((($AB59*$G59*0.9912*0.0001)-AC59)*100/ABS($AC$108),"") -> 0 | S59: =IF(AND(R59>0,Q59>0,R59>Q59),R59-Q59,"") | T59: =IF(AND(R59<0,Q59<0,R59<Q59),R59-Q59,"") | V59: 4780 | W59: 4690 | X59: 4770 | Y59: 742 | Z59: 6.43 | AA59: 7.7385 | AB59: 0 | AC59: 0
A60: =IFERROR(MATCH(C60,'دیده بان بازار'!$A$5:$A$3994,0 )+4,"Closed") -> 500 | B60: معدنكاران نسوز | C60: كانسار | D60: =_xlfn.XLOOKUP(C60,MOPFRA!$R$7:$R$56,MOPFRA!$P$7:$P$56,"") -> KM | F60: =IFERROR(_xlfn.LET(_xlpm.lookup_result,_xlfn.XLOOKUP($C60,'دیده بان بازار'!$A$5:$A$3994,'دیده بان بازار'!F$5:F$3994),IF(ISERROR(_xlpm.lookup_result),V60,_xlpm.lookup_result)),V60) -> 13680 | G60: =IFERROR(_xlfn.LET(_xlpm.lookup_result,_xlfn.XLOOKUP($C60,'دیده بان بازار'!$A$5:$A$3994,'دیده بان بازار'!H$5:H$3994),IF(ISERROR(_xlpm.lookup_result),W60,_xlpm.lookup_result)),W60) -> 14060 | H60: =IFERROR(_xlfn.LET(_xlpm.lookup_result,_xlfn.XLOOKUP($C60,'دیده بان بازار'!$A$5:$A$3994,'دیده بان بازار'!K$5:K$3994),IF(ISERROR(_xlpm.lookup_result),X60,_xlpm.lookup_result)),X60) -> 14050 | I60: =IFERROR(_xlfn.LET(_xlpm.lookup_result,_xlfn.XLOOKUP($C60,'دیده بان بازار'!$A$5:$A$3994,'دیده بان بازار'!P$5:P$3994),IF(ISERROR(_xlpm.lookup_result),Y60,_xlpm.lookup_result)),Y60) -> 1506 | J60: =IFERROR(_xlfn.LET(_xlpm.lookup_result,_xlfn.XLOOKUP($C60,'دیده بان بازار'!$A$5:$A$3994,'دیده بان بازار'!Q$5:Q$3994),IF(ISERROR(_xlpm.lookup_result),Z60,_xlpm.lookup_result)),Z60) -> 9.33 | K60: =_xlfn.XLOOKUP(C60,MOPFRA!$R$7:$R$56,MOPFRA!$T$7:$T$56,"")/1000 -> 7.8736 | L60: =_xlfn.XLOOKUP(C60,'MOPFRA Portfolio'!$P$8:$P$78,'MOPFRA Portfolio'!$AT$8:$AT$78,"") -> 0 | M60: =_xlfn.XLOOKUP(C60,'MOPFRA Portfolio'!$P$8:$P$78,'MOPFRA Portfolio'!$AU$8:$AU$78,"") -> 0 | P60: =IF(AND(Q60>=0,R60>=0,Q60>R60),Q60-R60,"") -> 0.090936745 | Q60: =IFERROR(((K60-AA60)*100)/ABS($K$106),"") -> 0.090936745 | R60: =IFERROR((($AB60*$G60*0.9912*0.0001)-AC60)*100/ABS($AC$108),"") -> 0 | V60: 13370 | W60: 13770 | X60: 13680 | Y60: 1506 | Z60: 9.08 | AA60: 7.7112 | AB60: 0 | AC60: 0
A61: =IFERROR(MATCH(C61,'دیده بان بازار'!$A$5:$A$3994,0 )+4,"Closed") -> 2153 | B61: معدني‌وصنعتي‌چادرملو | C61: كچاد | D61: =_xlfn.XLOOKUP(C61,MOPFRA!$R$7:$R$56,MOPFRA!$P$7:$P$56,"") -> KM | F61: =IFERROR(_xlfn.LET(_xlpm.lookup_result,_xlfn.XLOOKUP($C61,'دیده بان بازار'!$A$5:$A$3994,'دیده بان بازار'!F$5:F$3994),IF(ISERROR(_xlpm.lookup_result),V61,_xlpm.lookup_result)),V61) -> 2328 | G61: =IFERROR(_xlfn.LET(_xlpm.lookup_result,_xlfn.XLOOKUP($C61,'دیده بان بازار'!$A$5:$A$3994,'دیده بان بازار'!H$5:H$3994),IF(ISERROR(_xlpm.lookup_result),W61,_xlpm.lookup_result)),W61) -> 2397 | H61: =IFERROR(_xlfn.LET(_xlpm.lookup_result,_xlfn.XLOOKUP($C61,'دیده بان بازار'!$A$5:$A$3994,'دیده بان بازار'!K$5:K$3994),IF(ISERROR(_xlpm.lookup_result),X61,_xlpm.lookup_result)),X61) -> 2397 | I61: =IFERROR(_xlfn.LET(_xlpm.lookup_result,_xlfn.XLOOKUP($C61,'دیده بان بازار'!$A$5:$A$3994,'دیده بان بازار'!P$5:P$3994),IF(ISERROR(_xlpm.lookup_result),Y61,_xlpm.lookup_result)),Y61) -> 288 | J61: =IFERROR(_xlfn.LET(_xlpm.lookup_result,_xlfn.XLOOKUP($C61,'دیده بان بازار'!$A$5:$A$3994,'دیده بان بازار'!Q$5:Q$3994),IF(ISERROR(_xlpm.lookup_result),Z61,_xlpm.lookup_result)),Z61) -> 8.32 | K61: =_xlfn.XLOOKUP(C61,MOPFRA!$R$7:$R$56,MOPFRA!$T$7:$T$56,"")/1000 -> 136.98855 | L61: =_xlfn.XLOOKUP(C61,'MOPFRA Portfolio'!$P$8:$P$78,'MOPFRA Portfolio'!$AT$8:$AT$78,"") -> 1300000 | M61: =_xlfn.XLOOKUP(C61,'MOPFRA Portfolio'!$P$8:$P$78,'MOPFRA Portfolio'!$AU$8:$AU$78,"") -> 308867.83 | O61: =IF(AND(Q61<0,R61<0,Q61<R61),Q61-R61,"") | P61: =IF(AND(Q61>=0,R61>=0,Q61>R61),Q61-R61,"") -> 1.3500421 | Q61: =IFERROR(((K61-AA61)*100)/ABS($K$106),"") -> 2.1760984 | R61: =IFERROR((($AB61*$G61*0.9912*0.0001)-AC61)*100/ABS($AC$108),"") -> 0.82605632 | S61: =IF(AND(R61>0,Q61>0,R61>Q61),R61-Q61,"") | T61: =IF(AND(R61<0,Q61<0,R61<Q61),R61-Q61,"") | V61: 2262 | W61: 2329 | X61: 2328 | Y61: 288 | Z61: 8.08 | AA61: 133.10235 | AB61: 1300000 | AC61: 300105.62
A62: =IFERROR(MATCH(C62,'دیده بان بازار'!$A$5:$A$3994,0 )+4,"Closed") -> 2677 | B62: توليدات پتروشيمي قائد بصير | C62: شبصير | D62: =_xlfn.XLOOKUP(C62,MOPFRA!$R$7:$R$56,MOPFRA!$P$7:$P$56,"") -> PAB | F62: =IFERROR(_xlfn.LET(_xlpm.lookup_result,_xlfn.XLOOKUP($C62,'دیده بان بازار'!$A$5:$A$3994,'دیده بان بازار'!F$5:F$3994),IF(ISERROR(_xlpm.lookup_result),V62,_xlpm.lookup_result)),V62) -> 10690 | G62: =IFERROR(_xlfn.LET(_xlpm.lookup_result,_xlfn.XLOOKUP($C62,'دیده بان بازار'!$A$5:$A$3994,'دیده بان بازار'!H$5:H$3994),IF(ISERROR(_xlpm.lookup_result),W62,_xlpm.lookup_result)),W62) -> 11010 | H62: =IFERROR(_xlfn.LET(_xlpm.lookup_result,_xlfn.XLOOKUP($C62,'دیده بان بازار'!$A$5:$A$3994,'دیده بان بازار'!K$5:K$3994),IF(ISERROR(_xlpm.lookup_result),X62,_xlpm.lookup_result)),X62) -> 11010 | I62: =IFERROR(_xlfn.LET(_xlpm.lookup_result,_xlfn.XLOOKUP($C62,'دیده بان بازار'!$A$5:$A$3994,'دیده بان بازار'!P$5:P$3994),IF(ISERROR(_xlpm.lookup_result),Y62,_xlpm.lookup_result)),Y62) -> 2884 | J62: =IFERROR(_xlfn.LET(_xlpm.lookup_result,_xlfn.XLOOKUP($C62,'دیده بان بازار'!$A$5:$A$3994,'دیده بان بازار'!Q$5:Q$3994),IF(ISERROR(_xlpm.lookup_result),Z62,_xlpm.lookup_result)),Z62) -> 3.82 | K62: =_xlfn.XLOOKUP(C62,MOPFRA!$R$7:$R$56,MOPFRA!$T$7:$T$56,"")/1000 -> 11.01 | L62: =_xlfn.XLOOKUP(C62,'MOPFRA Portfolio'!$P$8:$P$78,'MOPFRA Portfolio'!$AT$8:$AT$78,"") -> 750000 | M62: =_xlfn.XLOOKUP(C62,'MOPFRA Portfolio'!$P$8:$P$78,'MOPFRA Portfolio'!$AU$8:$AU$78,"") -> 818483.4 | O62: =IF(AND(Q62<0,R62<0,Q62<R62),Q62-R62,"") | P62: =IF(AND(Q62>=0,R62>=0,Q62>R62),Q62-R62,"") | Q62: =IFERROR(((K62-AA62)*100)/ABS($K$106),"") -> 0.1791857 | R62: =IFERROR((($AB62*$G62*0.9912*0.0001)-AC62)*100/ABS($AC$108),"") -> 2.2426868 | S62: =IF(AND(R62>0,Q62>0,R62>Q62),R62-Q62,"") -> 2.0635011 | T62: =IF(AND(R62<0,Q62<0,R62<Q62),R62-Q62,"") | V62: 10380 | W62: 10690 | X62: 10690 | Y62: 2884 | Z62: 3.71 | AA62: 10.69 | AB62: 750000 | AC62: 794694.6
A63: =IFERROR(MATCH(C63,'دیده بان بازار'!$A$5:$A$3994,0 )+4,"Closed") -> 2318 | B63: پتروشيمي اروند | C63: اروند | D63: =_xlfn.XLOOKUP(C63,MOPFRA!$R$7:$R$56,MOPFRA!$P$7:$P$56,"") -> PVC | F63: =IFERROR(_xlfn.LET(_xlpm.lookup_result,_xlfn.XLOOKUP($C63,'دیده بان بازار'!$A$5:$A$3994,'دیده بان بازار'!F$5:F$3994),IF(ISERROR(_xlpm.lookup_result),V63,_xlpm.lookup_result)),V63) -> 45260 | G63: =IFERROR(_xlfn.LET(_xlpm.lookup_result,_xlfn.XLOOKUP($C63,'دیده بان بازار'!$A$5:$A$3994,'دیده بان بازار'!H$5:H$3994),IF(ISERROR(_xlpm.lookup_result),W63,_xlpm.lookup_result)),W63) -> 46610 | H63: =IFERROR(_xlfn.LET(_xlpm.lookup_result,_xlfn.XLOOKUP($C63,'دیده بان بازار'!$A$5:$A$3994,'دیده بان بازار'!K$5:K$3994),IF(ISERROR(_xlpm.lookup_result),X63,_xlpm.lookup_result)),X63) -> 46590 | I63: =IFERROR(_xlfn.LET(_xlpm.lookup_result,_xlfn.XLOOKUP($C63,'دیده بان بازار'!$A$5:$A$3994,'دیده بان بازار'!P$5:P$3994),IF(ISERROR(_xlpm.lookup_result),Y63,_xlpm.lookup_result)),Y63) -> 3275 | J63: =IFERROR(_xlfn.LET(_xlpm.lookup_result,_xlfn.XLOOKUP($C63,'دیده بان بازار'!$A$5:$A$3994,'دیده بان بازار'!Q$5:Q$3994),IF(ISERROR(_xlpm.lookup_result),Z63,_xlpm.lookup_result)),Z63) -> 14.23 | K63: =_xlfn.XLOOKUP(C63,MOPFRA!$R$7:$R$56,MOPFRA!$T$7:$T$56,"")/1000 -> 55.932 | L63: =_xlfn.XLOOKUP(C63,'MOPFRA Portfolio'!$P$8:$P$78,'MOPFRA Portfolio'!$AT$8:$AT$78,"") -> 0 | M63: =_xlfn.XLOOKUP(C63,'MOPFRA Portfolio'!$P$8:$P$78,'MOPFRA Portfolio'!$AU$8:$AU$78,"") -> 0 | Q63: =IFERROR(((K63-AA63)*100)/ABS($K$106),"") -> 0.88024977 | R63: =IFERROR((($AB63*$G63*0.9912*0.0001)-AC63)*100/ABS($AC$108),"") -> 0 | V63: 43990 | W63: 45300 | X63: 45260 | Y63: 3275 | Z63: 13.82 | AA63: 54.36 | AB63: 0 | AC63: 0
A64: =IFERROR(MATCH(C64,'دیده بان بازار'!$A$5:$A$3994,0 )+4,"Closed") -> 163 | B64: پتروشيمي پرديس | C64: شپديس | D64: =_xlfn.XLOOKUP(C64,MOPFRA!$R$7:$R$56,MOPFRA!$P$7:$P$56,"") -> PUR | F64: =IFERROR(_xlfn.LET(_xlpm.lookup_result,_xlfn.XLOOKUP($C64,'دیده بان بازار'!$A$5:$A$3994,'دیده بان بازار'!F$5:F$3994),IF(ISERROR(_xlpm.lookup_result),V64,_xlpm.lookup_result)),V64) -> 10620 | G64: =IFERROR(_xlfn.LET(_xlpm.lookup_result,_xlfn.XLOOKUP($C64,'دیده بان بازار'!$A$5:$A$3994,'دیده بان بازار'!H$5:H$3994),IF(ISERROR(_xlpm.lookup_result),W64,_xlpm.lookup_result)),W64) -> 10930 | H64: =IFERROR(_xlfn.LET(_xlpm.lookup_result,_xlfn.XLOOKUP($C64,'دیده بان بازار'!$A$5:$A$3994,'دیده بان بازار'!K$5:K$3994),IF(ISERROR(_xlpm.lookup_result),X64,_xlpm.lookup_result)),X64) -> 10930 | I64: =IFERROR(_xlfn.LET(_xlpm.lookup_result,_xlfn.XLOOKUP($C64,'دیده بان بازار'!$A$5:$A$3994,'دیده بان بازار'!P$5:P$3994),IF(ISERROR(_xlpm.lookup_result),Y64,_xlpm.lookup_result)),Y64) -> 1879 | J64: =IFERROR(_xlfn.LET(_xlpm.lookup_result,_xlfn.XLOOKUP($C64,'دیده بان بازار'!$A$5:$A$3994,'دیده بان بازار'!Q$5:Q$3994),IF(ISERROR(_xlpm.lookup_result),Z64,_xlpm.lookup_result)),Z64) -> 5.82 | K64: =_xlfn.XLOOKUP(C64,MOPFRA!$R$7:$R$56,MOPFRA!$T$7:$T$56,"")/1000 -> 255.29507 | L64: =_xlfn.XLOOKUP(C64,'MOPFRA Portfolio'!$P$8:$P$78,'MOPFRA Portfolio'!$AT$8:$AT$78,"") -> 210000 | M64: =_xlfn.XLOOKUP(C64,'MOPFRA Portfolio'!$P$8:$P$78,'MOPFRA Portfolio'!$AU$8:$AU$78,"") -> 227510.14 | O64: =IF(AND(Q64<0,R64<0,Q64<R64),Q64-R64,"") | P64: =IF(AND(Q64>=0,R64>=0,Q64>R64),Q64-R64,"") -> 3.4461715 | Q64: =IFERROR(((K64-AA64)*100)/ABS($K$106),"") -> 4.0545003 | R64: =IFERROR((($AB64*$G64*0.9912*0.0001)-AC64)*100/ABS($AC$108),"") -> 0.60832881 | S64: =IF(AND(R64>0,Q64>0,R64>Q64),R64-Q64,"") | T64: =IF(AND(R64<0,Q64<0,R64<Q64),R64-Q64,"") | V64: 10320 | W64: 10620 | X64: 10620 | Y64: 1879 | Z64: 5.65 | AA64: 248.05431 | AB64: 210000 | AC64: 221057.42
A65: =IFERROR(MATCH(C65,'دیده بان بازار'!$A$5:$A$3994,0 )+4,"Closed") -> 2219 | B65: پتروشيمي‌شيراز | C65: شيراز | D65: =_xlfn.XLOOKUP(C65,MOPFRA!$R$7:$R$56,MOPFRA!$P$7:$P$56,"") -> PUR | F65: =IFERROR(_xlfn.LET(_xlpm.lookup_result,_xlfn.XLOOKUP($C65,'دیده بان بازار'!$A$5:$A$3994,'دیده بان بازار'!F$5:F$3994),IF(ISERROR(_xlpm.lookup_result),V65,_xlpm.lookup_result)),V65) -> 62800 | G65: =IFERROR(_xlfn.LET(_xlpm.lookup_result,_xlfn.XLOOKUP($C65,'دیده بان بازار'!$A$5:$A$3994,'دیده بان بازار'!H$5:H$3994),IF(ISERROR(_xlpm.lookup_result),W65,_xlpm.lookup_result)),W65) -> 64680 | H65: =IFERROR(_xlfn.LET(_xlpm.lookup_result,_xlfn.XLOOKUP($C65,'دیده بان بازار'!$A$5:$A$3994,'دیده بان بازار'!K$5:K$3994),IF(ISERROR(_xlpm.lookup_result),X65,_xlpm.lookup_result)),X65) -> 64680 | I65: =IFERROR(_xlfn.LET(_xlpm.lookup_result,_xlfn.XLOOKUP($C65,'دیده بان بازار'!$A$5:$A$3994,'دیده بان بازار'!P$5:P$3994),IF(ISERROR(_xlpm.lookup_result),Y65,_xlpm.lookup_result)),Y65) -> 9681 | J65: =IFERROR(_xlfn.LET(_xlpm.lookup_result,_xlfn.XLOOKUP($C65,'دیده بان بازار'!$A$5:$A$3994,'دیده بان بازار'!Q$5:Q$3994),IF(ISERROR(_xlpm.lookup_result),Z65,_xlpm.lookup_result)),Z65) -> 6.68 | K65: =_xlfn.XLOOKUP(C65,MOPFRA!$R$7:$R$56,MOPFRA!$T$7:$T$56,"")/1000 -> 98.9604 | L65: =_xlfn.XLOOKUP(C65,'MOPFRA Portfolio'!$P$8:$P$78,'MOPFRA Portfolio'!$AT$8:$AT$78,"") -> 20000 | M65: =_xlfn.XLOOKUP(C65,'MOPFRA Portfolio'!$P$8:$P$78,'MOPFRA Portfolio'!$AU$8:$AU$78,"") -> 128221.63 | O65: =IF(AND(Q65<0,R65<0,Q65<R65),Q65-R65,"") | P65: =IF(AND(Q65>=0,R65>=0,Q65>R65),Q65-R65,"") -> 1.2526028 | Q65: =IFERROR(((K65-AA65)*100)/ABS($K$106),"") -> 1.6020882 | R65: =IFERROR((($AB65*$G65*0.9912*0.0001)-AC65)*100/ABS($AC$108),"") -> 0.34948537 | S65: =IF(AND(R65>0,Q65>0,R65>Q65),R65-Q65,"") | T65: =IF(AND(R65<0,Q65<0,R65<Q65),R65-Q65,"") | V65: 60990 | W65: 62810 | X65: 62800 | Y65: 9681 | Z65: 6.49 | AA65: 96.0993 | AB65: 20000 | AC65: 124514.54
A66: =IFERROR(MATCH(C66,'دیده بان بازار'!$A$5:$A$3994,0 )+4,"Closed") -> 2386 | B66: پليمر آريا ساسول | C66: آريا | D66: =_xlfn.XLOOKUP(C66,MOPFRA!$R$7:$R$56,MOPFRA!$P$7:$P$56,"") -> PEP | F66: =IFERROR(_xlfn.LET(_xlpm.lookup_result,_xlfn.XLOOKUP($C66,'دیده بان بازار'!$A$5:$A$3994,'دیده بان بازار'!F$5:F$3994),IF(ISERROR(_xlpm.lookup_result),V66,_xlpm.lookup_result)),V66) -> 28170 | G66: =IFERROR(_xlfn.LET(_xlpm.lookup_result,_xlfn.XLOOKUP($C66,'دیده بان بازار'!$A$5:$A$3994,'دیده بان بازار'!H$5:H$3994),IF(ISERROR(_xlpm.lookup_result),W66,_xlpm.lookup_result)),W66) -> 29010 | H66: =IFERROR(_xlfn.LET(_xlpm.lookup_result,_xlfn.XLOOKUP($C66,'دیده بان بازار'!$A$5:$A$3994,'دیده بان بازار'!K$5:K$3994),IF(ISERROR(_xlpm.lookup_result),X66,_xlpm.lookup_result)),X66) -> 29000 | I66: =IFERROR(_xlfn.LET(_xlpm.lookup_result,_xlfn.XLOOKUP($C66,'دیده بان بازار'!$A$5:$A$3994,'دیده بان بازار'!P$5:P$3994),IF(ISERROR(_xlpm.lookup_result),Y66,_xlpm.lookup_result)),Y66) -> 4878 | J66: =IFERROR(_xlfn.LET(_xlpm.lookup_result,_xlfn.XLOOKUP($C66,'دیده بان بازار'!$A$5:$A$3994,'دیده بان بازار'!Q$5:Q$3994),IF(ISERROR(_xlpm.lookup_result),Z66,_xlpm.lookup_result)),Z66) -> 5.95 | K66: =_xlfn.XLOOKUP(C66,MOPFRA!$R$7:$R$56,MOPFRA!$T$7:$T$56,"")/1000 -> 99.732899 | L66: =_xlfn.XLOOKUP(C66,'MOPFRA Portfolio'!$P$8:$P$78,'MOPFRA Portfolio'!$AT$8:$AT$78,"") -> 0 | M66: =_xlfn.XLOOKUP(C66,'MOPFRA Portfolio'!$P$8:$P$78,'MOPFRA Portfolio'!$AU$8:$AU$78,"") -> 0 | O66: =IF(AND(Q66<0,R66<0,Q66<R66),Q66-R66,"") | P66: =IF(AND(Q66>=0,R66>=0,Q66>R66),Q66-R66,"") -> 1.5977991 | Q66: =IFERROR(((K66-AA66)*100)/ABS($K$106),"") -> 1.5977991 | R66: =IFERROR((($AB66*$G66*0.9912*0.0001)-AC66)*100/ABS($AC$108),"") -> 0 | S66: =IF(AND(R66>0,Q66>0,R66>Q66),R66-Q66,"") | T66: =IF(AND(R66<0,Q66<0,R66<Q66),R66-Q66,"") | V66: 27360 | W66: 28180 | X66: 28170 | Y66: 4878 | Z66: 5.77 | AA66: 96.879458 | AB66: 0 | AC66: 0
A67: =IFERROR(MATCH(C67,'دیده بان بازار'!$A$5:$A$3994,0 )+4,"Closed") -> 2437 | B67: پتروشيمي شازند | C67: شاراك | D67: =_xlfn.XLOOKUP(C67,MOPFRA!$R$7:$R$56,MOPFRA!$P$7:$P$56,"") -> PEP | F67: =IFERROR(_xlfn.LET(_xlpm.lookup_result,_xlfn.XLOOKUP($C67,'دیده بان بازار'!$A$5:$A$3994,'دیده بان بازار'!F$5:F$3994),IF(ISERROR(_xlpm.lookup_result),V67,_xlpm.lookup_result)),V67) -> 19050 | G67: =IFERROR(_xlfn.LET(_xlpm.lookup_result,_xlfn.XLOOKUP($C67,'دیده بان بازار'!$A$5:$A$3994,'دیده بان بازار'!H$5:H$3994),IF(ISERROR(_xlpm.lookup_result),W67,_xlpm.lookup_result)),W67) -> 19620 | H67: =IFERROR(_xlfn.LET(_xlpm.lookup_result,_xlfn.XLOOKUP($C67,'دیده بان بازار'!$A$5:$A$3994,'دیده بان بازار'!K$5:K$3994),IF(ISERROR(_xlpm.lookup_result),X67,_xlpm.lookup_result)),X67) -> 19620 | I67: =IFERROR(_xlfn.LET(_xlpm.lookup_result,_xlfn.XLOOKUP($C67,'دیده بان بازار'!$A$5:$A$3994,'دیده بان بازار'!P$5:P$3994),IF(ISERROR(_xlpm.lookup_result),Y67,_xlpm.lookup_result)),Y67) -> 3871 | J67: =IFERROR(_xlfn.LET(_xlpm.lookup_result,_xlfn.XLOOKUP($C67,'دیده بان بازار'!$A$5:$A$3994,'دیده بان بازار'!Q$5:Q$3994),IF(ISERROR(_xlpm.lookup_result),Z67,_xlpm.lookup_result)),Z67) -> 5.07 | K67: =_xlfn.XLOOKUP(C67,MOPFRA!$R$7:$R$56,MOPFRA!$T$7:$T$56,"")/1000 -> 33.354 | L67: =_xlfn.XLOOKUP(C67,'MOPFRA Portfolio'!$P$8:$P$78,'MOPFRA Portfolio'!$AT$8:$AT$78,"") -> 130000 | M67: =_xlfn.XLOOKUP(C67,'MOPFRA Portfolio'!$P$8:$P$78,'MOPFRA Portfolio'!$AU$8:$AU$78,"") -> 252815.47 | O67: =IF(AND(Q67<0,R67<0,Q67<R67),Q67-R67,"") | P67: =IF(AND(Q67>=0,R67>=0,Q67>R67),Q67-R67,"") | Q67: =IFERROR(((K67-AA67)*100)/ABS($K$106),"") -> 0.45692354 | R67: =IFERROR((($AB67*$G67*0.9912*0.0001)-AC67)*100/ABS($AC$108),"") -> 0.58309858 | S67: =IF(AND(R67>0,Q67>0,R67>Q67),R67-Q67,"") -> 0.12617504 | T67: =IF(AND(R67<0,Q67<0,R67<Q67),R67-Q67,"") | V67: 18590 | W67: 19140 | X67: 19050 | Y67: 3871 | Z67: 4.92 | AA67: 32.538 | AB67: 130000 | AC67: 246630.38
A68: =IFERROR(MATCH(C68,'دیده بان بازار'!$A$5:$A$3994,0 )+4,"Closed") -> 2825 | B68: پتروشيمي مارون | C68: مارون | D68: =_xlfn.XLOOKUP(C68,MOPFRA!$R$7:$R$56,MOPFRA!$P$7:$P$56,"") -> PEP | F68: =IFERROR(_xlfn.LET(_xlpm.lookup_result,_xlfn.XLOOKUP($C68,'دیده بان بازار'!$A$5:$A$3994,'دیده بان بازار'!F$5:F$3994),IF(ISERROR(_xlpm.lookup_result),V68,_xlpm.lookup_result)),V68) -> 54210 | G68: =IFERROR(_xlfn.LET(_xlpm.lookup_result,_xlfn.XLOOKUP($C68,'دیده بان بازار'!$A$5:$A$3994,'دیده بان بازار'!H$5:H$3994),IF(ISERROR(_xlpm.lookup_result),W68,_xlpm.lookup_result)),W68) -> 55830 | H68: =IFERROR(_xlfn.LET(_xlpm.lookup_result,_xlfn.XLOOKUP($C68,'دیده بان بازار'!$A$5:$A$3994,'دیده بان بازار'!K$5:K$3994),IF(ISERROR(_xlpm.lookup_result),X68,_xlpm.lookup_result)),X68) -> 55820 | I68: =IFERROR(_xlfn.LET(_xlpm.lookup_result,_xlfn.XLOOKUP($C68,'دیده بان بازار'!$A$5:$A$3994,'دیده بان بازار'!P$5:P$3994),IF(ISERROR(_xlpm.lookup_result),Y68,_xlpm.lookup_result)),Y68) -> 9454 | J68: =IFERROR(_xlfn.LET(_xlpm.lookup_result,_xlfn.XLOOKUP($C68,'دیده بان بازار'!$A$5:$A$3994,'دیده بان بازار'!Q$5:Q$3994),IF(ISERROR(_xlpm.lookup_result),Z68,_xlpm.lookup_result)),Z68) -> 5.9 | K68: =_xlfn.XLOOKUP(C68,MOPFRA!$R$7:$R$56,MOPFRA!$T$7:$T$56,"")/1000 -> 128.409 | L68: =_xlfn.XLOOKUP(C68,'MOPFRA Portfolio'!$P$8:$P$78,'MOPFRA Portfolio'!$AT$8:$AT$78,"") -> 0 | M68: =_xlfn.XLOOKUP(C68,'MOPFRA Portfolio'!$P$8:$P$78,'MOPFRA Portfolio'!$AU$8:$AU$78,"") -> 0 | O68: =IF(AND(Q68<0,R68<0,Q68<R68),Q68-R68,"") | P68: =IF(AND(Q68>=0,R68>=0,Q68>R68),Q68-R68,"") -> 2.1121515 | Q68: =IFERROR(((K68-AA68)*100)/ABS($K$106),"") -> 2.1121515 | R68: =IFERROR((($AB68*$G68*0.9912*0.0001)-AC68)*100/ABS($AC$108),"") -> 0 | S68: =IF(AND(R68>0,Q68>0,R68>Q68),R68-Q68,"") | T68: =IF(AND(R68<0,Q68<0,R68<Q68),R68-Q68,"") | V68: 52990 | W68: 54190 | X68: 54210 | Y68: 9454 | Z68: 5.73 | AA68: 124.637 | AB68: 0 | AC68: 0 | AD68: 0
A69: =IFERROR(MATCH(C69,'دیده بان بازار'!$A$5:$A$3994,0 )+4,"Closed") -> 1015 | B69: پتروشيمي تندگويان | C69: شگويا | D69: =_xlfn.XLOOKUP(C69,MOPFRA!$R$7:$R$56,MOPFRA!$P$7:$P$56,"") -> PET | F69: =IFERROR(_xlfn.LET(_xlpm.lookup_result,_xlfn.XLOOKUP($C69,'دیده بان بازار'!$A$5:$A$3994,'دیده بان بازار'!F$5:F$3994),IF(ISERROR(_xlpm.lookup_result),V69,_xlpm.lookup_result)),V69) -> 7820 | G69: =IFERROR(_xlfn.LET(_xlpm.lookup_result,_xlfn.XLOOKUP($C69,'دیده بان بازار'!$A$5:$A$3994,'دیده بان بازار'!H$5:H$3994),IF(ISERROR(_xlpm.lookup_result),W69,_xlpm.lookup_result)),W69) -> 8050 | H69: =IFERROR(_xlfn.LET(_xlpm.lookup_result,_xlfn.XLOOKUP($C69,'دیده بان بازار'!$A$5:$A$3994,'دیده بان بازار'!K$5:K$3994),IF(ISERROR(_xlpm.lookup_result),X69,_xlpm.lookup_result)),X69) -> 8020 | I69: =IFERROR(_xlfn.LET(_xlpm.lookup_result,_xlfn.XLOOKUP($C69,'دیده بان بازار'!$A$5:$A$3994,'دیده بان بازار'!P$5:P$3994),IF(ISERROR(_xlpm.lookup_result),Y69,_xlpm.lookup_result)),Y69) -> 1099 | J69: =IFERROR(_xlfn.LET(_xlpm.lookup_result,_xlfn.XLOOKUP($C69,'دیده بان بازار'!$A$5:$A$3994,'دیده بان بازار'!Q$5:Q$3994),IF(ISERROR(_xlpm.lookup_result),Z69,_xlpm.lookup_result)),Z69) -> 7.3 | K69: =_xlfn.XLOOKUP(C69,MOPFRA!$R$7:$R$56,MOPFRA!$T$7:$T$56,"")/1000 -> 27.37 | L69: =_xlfn.XLOOKUP(C69,'MOPFRA Portfolio'!$P$8:$P$78,'MOPFRA Portfolio'!$AT$8:$AT$78,"") -> 0 | M69: =_xlfn.XLOOKUP(C69,'MOPFRA Portfolio'!$P$8:$P$78,'MOPFRA Portfolio'!$AU$8:$AU$78,"") -> 0 | O69: =IF(AND(Q69<0,R69<0,Q69<R69),Q69-R69,"") | P69: =IF(AND(Q69>=0,R69>=0,Q69>R69),Q69-R69,"") -> 0.41884658 | Q69: =IFERROR(((K69-AA69)*100)/ABS($K$106),"") -> 0.41884658 | R69: =IFERROR((($AB69*$G69*0.9912*0.0001)-AC69)*100/ABS($AC$108),"") -> 0 | S69: =IF(AND(R69>0,Q69>0,R69>Q69),R69-Q69,"") | T69: =IF(AND(R69<0,Q69<0,R69<Q69),R69-Q69,"") | V69: 7610 | W69: 7830 | X69: 7820 | Y69: 1099 | Z69: 7.12 | AA69: 26.622 | AB69: 0 | AC69: 0
A70: =IFERROR(MATCH(C70,'دیده بان بازار'!$A$5:$A$3994,0 )+4,"Closed") -> 1321 | B70: داروسازي‌ فارابي‌ | C70: دفارا | D70: =_xlfn.XLOOKUP(C70,MOPFRA!$R$7:$R$56,MOPFRA!$P$7:$P$56,"") -> PH | F70: =IFERROR(_xlfn.LET(_xlpm.lookup_result,_xlfn.XLOOKUP($C70,'دیده بان بازار'!$A$5:$A$3994,'دیده بان بازار'!F$5:F$3994),IF(ISERROR(_xlpm.lookup_result),V70,_xlpm.lookup_result)),V70) -> 12420 | G70: =IFERROR(_xlfn.LET(_xlpm.lookup_result,_xlfn.XLOOKUP($C70,'دیده بان بازار'!$A$5:$A$3994,'دیده بان بازار'!H$5:H$3994),IF(ISERROR(_xlpm.lookup_result),W70,_xlpm.lookup_result)),W70) -> 12790 | H70: =IFERROR(_xlfn.LET(_xlpm.lookup_result,_xlfn.XLOOKUP($C70,'دیده بان بازار'!$A$5:$A$3994,'دیده بان بازار'!K$5:K$3994),IF(ISERROR(_xlpm.lookup_result),X70,_xlpm.lookup_result)),X70) -> 12790 | I70: =IFERROR(_xlfn.LET(_xlpm.lookup_result,_xlfn.XLOOKUP($C70,'دیده بان بازار'!$A$5:$A$3994,'دیده بان بازار'!P$5:P$3994),IF(ISERROR(_xlpm.lookup_result),Y70,_xlpm.lookup_result)),Y70) -> 1956 | J70: =IFERROR(_xlfn.LET(_xlpm.lookup_result,_xlfn.XLOOKUP($C70,'دیده بان بازار'!$A$5:$A$3994,'دیده بان بازار'!Q$5:Q$3994),IF(ISERROR(_xlpm.lookup_result),Z70,_xlpm.lookup_result)),Z70) -> 6.54 | K70: =_xlfn.XLOOKUP(C70,MOPFRA!$R$7:$R$56,MOPFRA!$T$7:$T$56,"")/1000 -> 11.774474 | L70: =_xlfn.XLOOKUP(C70,'MOPFRA Portfolio'!$P$8:$P$78,'MOPFRA Portfolio'!$AT$8:$AT$78,"") -> 0 | M70: =_xlfn.XLOOKUP(C70,'MOPFRA Portfolio'!$P$8:$P$78,'MOPFRA Portfolio'!$AU$8:$AU$78,"") -> 0 | O70: =IF(AND(Q70<0,R70<0,Q70<R70),Q70-R70,"") | P70: =IF(AND(Q70>=0,R70>=0,Q70>R70),Q70-R70,"") -> 0.18557815 | Q70: =IFERROR(((K70-AA70)*100)/ABS($K$106),"") -> 0.18557815 | R70: =IFERROR((($AB70*$G70*0.9912*0.0001)-AC70)*100/ABS($AC$108),"") -> 0 | S70: =IF(AND(R70>0,Q70>0,R70>Q70),R70-Q70,"") | T70: =IF(AND(R70<0,Q70<0,R70<Q70),R70-Q70,"") | V70: 12070 | W70: 12430 | X70: 12420 | Y70: 1956 | Z70: 6.35 | AA70: 11.443058 | AB70: 0 | AC70: 0
A71: =IFERROR(MATCH(C71,'دیده بان بازار'!$A$5:$A$3994,0 )+4,"Closed") -> 159 | B71: پارس‌ دارو | C71: دپارس | D71: =_xlfn.XLOOKUP(C71,MOPFRA!$R$7:$R$56,MOPFRA!$P$7:$P$56,"") -> PH | F71: =IFERROR(_xlfn.LET(_xlpm.lookup_result,_xlfn.XLOOKUP($C71,'دیده بان بازار'!$A$5:$A$3994,'دیده بان بازار'!F$5:F$3994),IF(ISERROR(_xlpm.lookup_result),V71,_xlpm.lookup_result)),V71) -> 48010 | G71: =IFERROR(_xlfn.LET(_xlpm.lookup_result,_xlfn.XLOOKUP($C71,'دیده بان بازار'!$A$5:$A$3994,'دیده بان بازار'!H$5:H$3994),IF(ISERROR(_xlpm.lookup_result),W71,_xlpm.lookup_result)),W71) -> 49450 | H71: =IFERROR(_xlfn.LET(_xlpm.lookup_result,_xlfn.XLOOKUP($C71,'دیده بان بازار'!$A$5:$A$3994,'دیده بان بازار'!K$5:K$3994),IF(ISERROR(_xlpm.lookup_result),X71,_xlpm.lookup_result)),X71) -> 49450 | I71: =IFERROR(_xlfn.LET(_xlpm.lookup_result,_xlfn.XLOOKUP($C71,'دیده بان بازار'!$A$5:$A$3994,'دیده بان بازار'!P$5:P$3994),IF(ISERROR(_xlpm.lookup_result),Y71,_xlpm.lookup_result)),Y71) -> 5324 | J71: =IFERROR(_xlfn.LET(_xlpm.lookup_result,_xlfn.XLOOKUP($C71,'دیده بان بازار'!$A$5:$A$3994,'دیده بان بازار'!Q$5:Q$3994),IF(ISERROR(_xlpm.lookup_result),Z71,_xlpm.lookup_result)),Z71) -> 9.29 | K71: =_xlfn.XLOOKUP(C71,MOPFRA!$R$7:$R$56,MOPFRA!$T$7:$T$56,"")/1000 -> 12.11525 | L71: =_xlfn.XLOOKUP(C71,'MOPFRA Portfolio'!$P$8:$P$78,'MOPFRA Portfolio'!$AT$8:$AT$78,"") -> 160000 | M71: =_xlfn.XLOOKUP(C71,'MOPFRA Portfolio'!$P$8:$P$78,'MOPFRA Portfolio'!$AU$8:$AU$78,"") -> 784237.44 | P71: =IF(AND(Q71>=0,R71>=0,Q71>R71),Q71-R71,"") | Q71: =IFERROR(((K71-AA71)*100)/ABS($K$106),"") -> 0.18383333 | R71: =IFERROR((($AB71*$G71*0.9912*0.0001)-AC71)*100/ABS($AC$108),"") -> 2.0034669 | V71: 46710 | W71: 48110 | X71: 48010 | Y71: 5324 | Z71: 9.02 | AA71: 11.78695 | AB71: 160000 | AC71: 762986.11
A72: =IFERROR(MATCH(C72,'دیده بان بازار'!$A$5:$A$3994,0 )+4,"Closed") -> 1548 | B72: دارويي و نهاده هاي زاگرس دارو | C72: دزاگرس | D72: =_xlfn.XLOOKUP(C72,MOPFRA!$R$7:$R$56,MOPFRA!$P$7:$P$56,"") -> PH | F72: =IFERROR(_xlfn.LET(_xlpm.lookup_result,_xlfn.XLOOKUP($C72,'دیده بان بازار'!$A$5:$A$3994,'دیده بان بازار'!F$5:F$3994),IF(ISERROR(_xlpm.lookup_result),V72,_xlpm.lookup_result)),V72) -> 20580 | G72: =IFERROR(_xlfn.LET(_xlpm.lookup_result,_xlfn.XLOOKUP($C72,'دیده بان بازار'!$A$5:$A$3994,'دیده بان بازار'!H$5:H$3994),IF(ISERROR(_xlpm.lookup_result),W72,_xlpm.lookup_result)),W72) -> 21190 | H72: =IFERROR(_xlfn.LET(_xlpm.lookup_result,_xlfn.XLOOKUP($C72,'دیده بان بازار'!$A$5:$A$3994,'دیده بان بازار'!K$5:K$3994),IF(ISERROR(_xlpm.lookup_result),X72,_xlpm.lookup_result)),X72) -> 21130 | I72: =IFERROR(_xlfn.LET(_xlpm.lookup_result,_xlfn.XLOOKUP($C72,'دیده بان بازار'!$A$5:$A$3994,'دیده بان بازار'!P$5:P$3994),IF(ISERROR(_xlpm.lookup_result),Y72,_xlpm.lookup_result)),Y72) -> 3000 | J72: =IFERROR(_xlfn.LET(_xlpm.lookup_result,_xlfn.XLOOKUP($C72,'دیده بان بازار'!$A$5:$A$3994,'دیده بان بازار'!Q$5:Q$3994),IF(ISERROR(_xlpm.lookup_result),Z72,_xlpm.lookup_result)),Z72) -> 7.04 | K72: =_xlfn.XLOOKUP(C72,MOPFRA!$R$7:$R$56,MOPFRA!$T$7:$T$56,"")/1000 -> 16.3163 | L72: =_xlfn.XLOOKUP(C72,'MOPFRA Portfolio'!$P$8:$P$78,'MOPFRA Portfolio'!$AT$8:$AT$78,"") -> 260000 | M72: =_xlfn.XLOOKUP(C72,'MOPFRA Portfolio'!$P$8:$P$78,'MOPFRA Portfolio'!$AU$8:$AU$78,"") -> 546091.73 | O72: =IF(AND(Q72<0,R72<0,Q72<R72),Q72-R72,"") | P72: =IF(AND(Q72>=0,R72>=0,Q72>R72),Q72-R72,"") | Q72: =IFERROR(((K72-AA72)*100)/ABS($K$106),"") -> 0.32768586 | R72: =IFERROR((($AB72*$G72*0.9912*0.0001)-AC72)*100/ABS($AC$108),"") -> 1.8464788 | S72: =IF(AND(R72>0,Q72>0,R72>Q72),R72-Q72,"") -> 1.518793 | T72: =IF(AND(R72<0,Q72<0,R72<Q72),R72-Q72,"") | V72: 20030 | W72: 20430 | X72: 20580 | Y72: 3000 | Z72: 6.86 | AA72: 15.7311 | AB72: 260000 | AC72: 526505.62
A73: =IFERROR(MATCH(C73,'دیده بان بازار'!$A$5:$A$3994,0 )+4,"Closed") -> 2385 | B73: كارخانجات‌داروپخش‌ | C73: دارو | D73: =_xlfn.XLOOKUP(C73,MOPFRA!$R$7:$R$56,MOPFRA!$P$7:$P$56,"") -> PH | F73: =IFERROR(_xlfn.LET(_xlpm.lookup_result,_xlfn.XLOOKUP($C73,'دیده بان بازار'!$A$5:$A$3994,'دیده بان بازار'!F$5:F$3994),IF(ISERROR(_xlpm.lookup_result),V73,_xlpm.lookup_result)),V73) -> 6900 | G73: =IFERROR(_xlfn.LET(_xlpm.lookup_result,_xlfn.XLOOKUP($C73,'دیده بان بازار'!$A$5:$A$3994,'دیده بان بازار'!H$5:H$3994),IF(ISERROR(_xlpm.lookup_result),W73,_xlpm.lookup_result)),W73) -> 7100 | H73: =IFERROR(_xlfn.LET(_xlpm.lookup_result,_xlfn.XLOOKUP($C73,'دیده بان بازار'!$A$5:$A$3994,'دیده بان بازار'!K$5:K$3994),IF(ISERROR(_xlpm.lookup_result),X73,_xlpm.lookup_result)),X73) -> 7090 | I73: =IFERROR(_xlfn.LET(_xlpm.lookup_result,_xlfn.XLOOKUP($C73,'دیده بان بازار'!$A$5:$A$3994,'دیده بان بازار'!P$5:P$3994),IF(ISERROR(_xlpm.lookup_result),Y73,_xlpm.lookup_result)),Y73) -> 841 | J73: =IFERROR(_xlfn.LET(_xlpm.lookup_result,_xlfn.XLOOKUP($C73,'دیده بان بازار'!$A$5:$A$3994,'دیده بان بازار'!Q$5:Q$3994),IF(ISERROR(_xlpm.lookup_result),Z73,_xlpm.lookup_result)),Z73) -> 8.43 | K73: =_xlfn.XLOOKUP(C73,MOPFRA!$R$7:$R$56,MOPFRA!$T$7:$T$56,"")/1000 -> 36.778 | L73: =_xlfn.XLOOKUP(C73,'MOPFRA Portfolio'!$P$8:$P$78,'MOPFRA Portfolio'!$AT$8:$AT$78,"") -> 1100000 | M73: =_xlfn.XLOOKUP(C73,'MOPFRA Portfolio'!$P$8:$P$78,'MOPFRA Portfolio'!$AU$8:$AU$78,"") -> 774127.2 | O73: =IF(AND(Q73<0,R73<0,Q73<R73),Q73-R73,"") | P73: =IF(AND(Q73>=0,R73>=0,Q73>R73),Q73-R73,"") | Q73: =IFERROR(((K73-AA73)*100)/ABS($K$106),"") -> 0.58011372 | R73: =IFERROR((($AB73*$G73*0.9912*0.0001)-AC73)*100/ABS($AC$108),"") -> 2.0557963 | S73: =IF(AND(R73>0,Q73>0,R73>Q73),R73-Q73,"") -> 1.4756826 | T73: =IF(AND(R73<0,Q73<0,R73<Q73),R73-Q73,"") | V73: 6700 | W73: 6900 | X73: 6900 | Y73: 841 | Z73: 8.2 | AA73: 35.742 | AB73: 1100000 | AC73: 752320.8
A74: =IFERROR(MATCH(C74,'دیده بان بازار'!$A$5:$A$3994,0 )+4,"Closed") -> 1152 | B74: داروسازي كاسپين تامين | C74: كاسپين | D74: =_xlfn.XLOOKUP(C74,MOPFRA!$R$7:$R$56,MOPFRA!$P$7:$P$56,"") -> PH | F74: =IFERROR(_xlfn.LET(_xlpm.lookup_result,_xlfn.XLOOKUP($C74,'دیده بان بازار'!$A$5:$A$3994,'دیده بان بازار'!F$5:F$3994),IF(ISERROR(_xlpm.lookup_result),V74,_xlpm.lookup_result)),V74) -> 30090 | G74: =IFERROR(_xlfn.LET(_xlpm.lookup_result,_xlfn.XLOOKUP($C74,'دیده بان بازار'!$A$5:$A$3994,'دیده بان بازار'!H$5:H$3994),IF(ISERROR(_xlpm.lookup_result),W74,_xlpm.lookup_result)),W74) -> 30990 | H74: =IFERROR(_xlfn.LET(_xlpm.lookup_result,_xlfn.XLOOKUP($C74,'دیده بان بازار'!$A$5:$A$3994,'دیده بان بازار'!K$5:K$3994),IF(ISERROR(_xlpm.lookup_result),X74,_xlpm.lookup_result)),X74) -> 30990 | I74: =IFERROR(_xlfn.LET(_xlpm.lookup_result,_xlfn.XLOOKUP($C74,'دیده بان بازار'!$A$5:$A$3994,'دیده بان بازار'!P$5:P$3994),IF(ISERROR(_xlpm.lookup_result),Y74,_xlpm.lookup_result)),Y74) -> 3831 | J74: =IFERROR(_xlfn.LET(_xlpm.lookup_result,_xlfn.XLOOKUP($C74,'دیده بان بازار'!$A$5:$A$3994,'دیده بان بازار'!Q$5:Q$3994),IF(ISERROR(_xlpm.lookup_result),Z74,_xlpm.lookup_result)),Z74) -> 8.09 | K74: =_xlfn.XLOOKUP(C74,MOPFRA!$R$7:$R$56,MOPFRA!$T$7:$T$56,"")/1000 -> 24.60606 | L74: =_xlfn.XLOOKUP(C74,'MOPFRA Portfolio'!$P$8:$P$78,'MOPFRA Portfolio'!$AT$8:$AT$78,"") -> 30000 | M74: =_xlfn.XLOOKUP(C74,'MOPFRA Portfolio'!$P$8:$P$78,'MOPFRA Portfolio'!$AU$8:$AU$78,"") -> 92151.864 | P74: =IF(AND(Q74>=0,R74>=0,Q74>R74),Q74-R74,"") -> 0.14619912 | Q74: =IFERROR(((K74-AA74)*100)/ABS($K$106),"") -> 0.39569803 | R74: =IFERROR((($AB74*$G74*0.9912*0.0001)-AC74)*100/ABS($AC$108),"") -> 0.24949891 | V74: 29230 | W74: 30100 | X74: 30090 | Y74: 3831 | Z74: 7.85 | AA74: 23.8994 | AB74: 30000 | AC74: 89505.36
A75: =IFERROR(MATCH(C75,'دیده بان بازار'!$A$5:$A$3994,0 )+4,"Closed") -> 2931 | B75: داروسازي‌ سينا | C75: دسينا | D75: PH | F75: =IFERROR(_xlfn.LET(_xlpm.lookup_result,_xlfn.XLOOKUP($C75,'دیده بان بازار'!$A$5:$A$3994,'دیده بان بازار'!F$5:F$3994),IF(ISERROR(_xlpm.lookup_result),V75,_xlpm.lookup_result)),V75) -> 69780 | G75: =IFERROR(_xlfn.LET(_xlpm.lookup_result,_xlfn.XLOOKUP($C75,'دیده بان بازار'!$A$5:$A$3994,'دیده بان بازار'!H$5:H$3994),IF(ISERROR(_xlpm.lookup_result),W75,_xlpm.lookup_result)),W75) -> 71870 | H75: =IFERROR(_xlfn.LET(_xlpm.lookup_result,_xlfn.XLOOKUP($C75,'دیده بان بازار'!$A$5:$A$3994,'دیده بان بازار'!K$5:K$3994),IF(ISERROR(_xlpm.lookup_result),X75,_xlpm.lookup_result)),X75) -> 71870 | I75: =IFERROR(_xlfn.LET(_xlpm.lookup_result,_xlfn.XLOOKUP($C75,'دیده بان بازار'!$A$5:$A$3994,'دیده بان بازار'!P$5:P$3994),IF(ISERROR(_xlpm.lookup_result),Y75,_xlpm.lookup_result)),Y75) -> 9289 | J75: =IFERROR(_xlfn.LET(_xlpm.lookup_result,_xlfn.XLOOKUP($C75,'دیده بان بازار'!$A$5:$A$3994,'دیده بان بازار'!Q$5:Q$3994),IF(ISERROR(_xlpm.lookup_result),Z75,_xlpm.lookup_result)),Z75) -> 7.74 | K75: =_xlfn.XLOOKUP(C75,MOPFRA!$R$7:$R$56,MOPFRA!$T$7:$T$56,"")/1000 -> 17.2488 | L75: =_xlfn.XLOOKUP(C75,'MOPFRA Portfolio'!$P$8:$P$78,'MOPFRA Portfolio'!$AT$8:$AT$78,"") -> 0 | M75: =_xlfn.XLOOKUP(C75,'MOPFRA Portfolio'!$P$8:$P$78,'MOPFRA Portfolio'!$AU$8:$AU$78,"") -> 0 | Q75: =IFERROR(((K75-AA75)*100)/ABS($K$106),"") -> 0.28087359 | R75: =IFERROR((($AB75*$G75*0.9912*0.0001)-AC75)*100/ABS($AC$108),"") -> 0 | V75: 67750 | W75: 69780 | X75: 69780 | Y75: 9289 | Z75: 7.51 | AA75: 16.7472 | AB75: 0 | AC75: 0
A76: =IFERROR(MATCH(C76,'دیده بان بازار'!$A$5:$A$3994,0 )+4,"Closed") -> 1506 | B76: توليدمواداوليه‌داروپخش‌ | C76: دتماد | D76: PH | F76: =IFERROR(_xlfn.LET(_xlpm.lookup_result,_xlfn.XLOOKUP($C76,'دیده بان بازار'!$A$5:$A$3994,'دیده بان بازار'!F$5:F$3994),IF(ISERROR(_xlpm.lookup_result),V76,_xlpm.lookup_result)),V76) -> 43470 | G76: =IFERROR(_xlfn.LET(_xlpm.lookup_result,_xlfn.XLOOKUP($C76,'دیده بان بازار'!$A$5:$A$3994,'دیده بان بازار'!H$5:H$3994),IF(ISERROR(_xlpm.lookup_result),W76,_xlpm.lookup_result)),W76) -> 44770 | H76: =IFERROR(_xlfn.LET(_xlpm.lookup_result,_xlfn.XLOOKUP($C76,'دیده بان بازار'!$A$5:$A$3994,'دیده بان بازار'!K$5:K$3994),IF(ISERROR(_xlpm.lookup_result),X76,_xlpm.lookup_result)),X76) -> 44670 | I76: =IFERROR(_xlfn.LET(_xlpm.lookup_result,_xlfn.XLOOKUP($C76,'دیده بان بازار'!$A$5:$A$3994,'دیده بان بازار'!P$5:P$3994),IF(ISERROR(_xlpm.lookup_result),Y76,_xlpm.lookup_result)),Y76) -> 5718 | J76: =IFERROR(_xlfn.LET(_xlpm.lookup_result,_xlfn.XLOOKUP($C76,'دیده بان بازار'!$A$5:$A$3994,'دیده بان بازار'!Q$5:Q$3994),IF(ISERROR(_xlpm.lookup_result),Z76,_xlpm.lookup_result)),Z76) -> 7.81 | K76: =_xlfn.XLOOKUP(C76,MOPFRA!$R$7:$R$56,MOPFRA!$T$7:$T$56,"")/1000 -> 12.5356 | L76: =_xlfn.XLOOKUP(C76,'MOPFRA Portfolio'!$P$8:$P$78,'MOPFRA Portfolio'!$AT$8:$AT$78,"") -> 0 | M76: =_xlfn.XLOOKUP(C76,'MOPFRA Portfolio'!$P$8:$P$78,'MOPFRA Portfolio'!$AU$8:$AU$78,"") -> 0 | Q76: =IFERROR(((K76-AA76)*100)/ABS($K$106),"") -> 0.18500924 | R76: =IFERROR((($AB76*$G76*0.9912*0.0001)-AC76)*100/ABS($AC$108),"") -> 0 | V76: 43190 | W76: 43590 | X76: 43470 | Y76: 5718 | Z76: 7.6 | AA76: 12.2052 | AB76: 0 | AC76: 0
A77: =IFERROR(MATCH(C77,'دیده بان بازار'!$A$5:$A$3994,0 )+4,"Closed") -> 2307 | B77: پالايش نفت تهران | C77: شتران | D77: =_xlfn.XLOOKUP(C77,MOPFRA!$R$7:$R$56,MOPFRA!$P$7:$P$56,"") -> R | F77: =IFERROR(_xlfn.LET(_xlpm.lookup_result,_xlfn.XLOOKUP($C77,'دیده بان بازار'!$A$5:$A$3994,'دیده بان بازار'!F$5:F$3994),IF(ISERROR(_xlpm.lookup_result),V77,_xlpm.lookup_result)),V77) -> 4380 | G77: =IFERROR(_xlfn.LET(_xlpm.lookup_result,_xlfn.XLOOKUP($C77,'دیده بان بازار'!$A$5:$A$3994,'دیده بان بازار'!H$5:H$3994),IF(ISERROR(_xlpm.lookup_result),W77,_xlpm.lookup_result)),W77) -> 4510 | H77: =IFERROR(_xlfn.LET(_xlpm.lookup_result,_xlfn.XLOOKUP($C77,'دیده بان بازار'!$A$5:$A$3994,'دیده بان بازار'!K$5:K$3994),IF(ISERROR(_xlpm.lookup_result),X77,_xlpm.lookup_result)),X77) -> 4510 | I77: =IFERROR(_xlfn.LET(_xlpm.lookup_result,_xlfn.XLOOKUP($C77,'دیده بان بازار'!$A$5:$A$3994,'دیده بان بازار'!P$5:P$3994),IF(ISERROR(_xlpm.lookup_result),Y77,_xlpm.lookup_result)),Y77) -> 1249 | J77: =IFERROR(_xlfn.LET(_xlpm.lookup_result,_xlfn.XLOOKUP($C77,'دیده بان بازار'!$A$5:$A$3994,'دیده بان بازار'!Q$5:Q$3994),IF(ISERROR(_xlpm.lookup_result),Z77,_xlpm.lookup_result)),Z77) -> 3.61 | K77: =_xlfn.XLOOKUP(C77,MOPFRA!$R$7:$R$56,MOPFRA!$T$7:$T$56,"")/1000 -> 294.2775 | L77: =_xlfn.XLOOKUP(C77,'MOPFRA Portfolio'!$P$8:$P$78,'MOPFRA Portfolio'!$AT$8:$AT$78,"") -> 1570000 | M77: =_xlfn.XLOOKUP(C77,'MOPFRA Portfolio'!$P$8:$P$78,'MOPFRA Portfolio'!$AU$8:$AU$78,"") -> 701838.98 | O77: =IF(AND(Q77<0,R77<0,Q77<R77),Q77-R77,"") | P77: =IF(AND(Q77>=0,R77>=0,Q77>R77),Q77-R77,"") -> 2.8426028 | Q77: =IFERROR(((K77-AA77)*100)/ABS($K$106),"") -> 4.749821 | R77: =IFERROR((($AB77*$G77*0.9912*0.0001)-AC77)*100/ABS($AC$108),"") -> 1.9072183 | S77: =IF(AND(R77>0,Q77>0,R77>Q77),R77-Q77,"") | T77: =IF(AND(R77<0,Q77<0,R77<Q77),R77-Q77,"") | V77: 4260 | W77: 4380 | X77: 4380 | Y77: 1249 | Z77: 3.51 | AA77: 285.795 | AB77: 1570000 | AC77: 681608.59
A78: =IFERROR(MATCH(C78,'دیده بان بازار'!$A$5:$A$3994,0 )+4,"Closed") -> 1436 | B78: پالايش نفت بندرعباس | C78: شبندر | D78: =_xlfn.XLOOKUP(C78,MOPFRA!$R$7:$R$56,MOPFRA!$P$7:$P$56,"") -> R | F78: =IFERROR(_xlfn.LET(_xlpm.lookup_result,_xlfn.XLOOKUP($C78,'دیده بان بازار'!$A$5:$A$3994,'دیده بان بازار'!F$5:F$3994),IF(ISERROR(_xlpm.lookup_result),V78,_xlpm.lookup_result)),V78) -> 12360 | G78: =IFERROR(_xlfn.LET(_xlpm.lookup_result,_xlfn.XLOOKUP($C78,'دیده بان بازار'!$A$5:$A$3994,'دیده بان بازار'!H$5:H$3994),IF(ISERROR(_xlpm.lookup_result),W78,_xlpm.lookup_result)),W78) -> 12730 | H78: =IFERROR(_xlfn.LET(_xlpm.lookup_result,_xlfn.XLOOKUP($C78,'دیده بان بازار'!$A$5:$A$3994,'دیده بان بازار'!K$5:K$3994),IF(ISERROR(_xlpm.lookup_result),X78,_xlpm.lookup_result)),X78) -> 12730 | I78: =IFERROR(_xlfn.LET(_xlpm.lookup_result,_xlfn.XLOOKUP($C78,'دیده بان بازار'!$A$5:$A$3994,'دیده بان بازار'!P$5:P$3994),IF(ISERROR(_xlpm.lookup_result),Y78,_xlpm.lookup_result)),Y78) -> 2555 | J78: =IFERROR(_xlfn.LET(_xlpm.lookup_result,_xlfn.XLOOKUP($C78,'دیده بان بازار'!$A$5:$A$3994,'دیده بان بازار'!Q$5:Q$3994),IF(ISERROR(_xlpm.lookup_result),Z78,_xlpm.lookup_result)),Z78) -> 4.98 | K78: =_xlfn.XLOOKUP(C78,MOPFRA!$R$7:$R$56,MOPFRA!$T$7:$T$56,"")/1000 -> 521.6134 | L78: =_xlfn.XLOOKUP(C78,'MOPFRA Portfolio'!$P$8:$P$78,'MOPFRA Portfolio'!$AT$8:$AT$78,"") -> 900000 | M78: =_xlfn.XLOOKUP(C78,'MOPFRA Portfolio'!$P$8:$P$78,'MOPFRA Portfolio'!$AU$8:$AU$78,"") -> 1135617.8 | O78: =IF(AND(Q78<0,R78<0,Q78<R78),Q78-R78,"") | P78: =IF(AND(Q78>=0,R78>=0,Q78>R78),Q78-R78,"") -> 5.3776416 | Q78: =IFERROR(((K78-AA78)*100)/ABS($K$106),"") -> 8.4893696 | R78: =IFERROR((($AB78*$G78*0.9912*0.0001)-AC78)*100/ABS($AC$108),"") -> 3.111728 | S78: =IF(AND(R78>0,Q78>0,R78>Q78),R78-Q78,"") | T78: =IF(AND(R78<0,Q78<0,R78<Q78),R78-Q78,"") | V78: 12000 | W78: 12360 | X78: 12360 | Y78: 2555 | Z78: 4.84 | AA78: 506.45261 | AB78: 900000 | AC78: 1102610.9
A79: =IFERROR(MATCH(C79,'دیده بان بازار'!$A$5:$A$3994,0 )+4,"Closed") -> 2114 | B79: پالايش نفت اصفهان | C79: شپنا | D79: =_xlfn.XLOOKUP(C79,MOPFRA!$R$7:$R$56,MOPFRA!$P$7:$P$56,"") -> R | F79: =IFERROR(_xlfn.LET(_xlpm.lookup_result,_xlfn.XLOOKUP($C79,'دیده بان بازار'!$A$5:$A$3994,'دیده بان بازار'!F$5:F$3994),IF(ISERROR(_xlpm.lookup_result),V79,_xlpm.lookup_result)),V79) -> 10920 | G79: =IFERROR(_xlfn.LET(_xlpm.lookup_result,_xlfn.XLOOKUP($C79,'دیده بان بازار'!$A$5:$A$3994,'دیده بان بازار'!H$5:H$3994),IF(ISERROR(_xlpm.lookup_result),W79,_xlpm.lookup_result)),W79) -> 11240 | H79: =IFERROR(_xlfn.LET(_xlpm.lookup_result,_xlfn.XLOOKUP($C79,'دیده بان بازار'!$A$5:$A$3994,'دیده بان بازار'!K$5:K$3994),IF(ISERROR(_xlpm.lookup_result),X79,_xlpm.lookup_result)),X79) -> 11240 | I79: =IFERROR(_xlfn.LET(_xlpm.lookup_result,_xlfn.XLOOKUP($C79,'دیده بان بازار'!$A$5:$A$3994,'دیده بان بازار'!P$5:P$3994),IF(ISERROR(_xlpm.lookup_result),Y79,_xlpm.lookup_result)),Y79) -> 1816 | J79: =IFERROR(_xlfn.LET(_xlpm.lookup_result,_xlfn.XLOOKUP($C79,'دیده بان بازار'!$A$5:$A$3994,'دیده بان بازار'!Q$5:Q$3994),IF(ISERROR(_xlpm.lookup_result),Z79,_xlpm.lookup_result)),Z79) -> 6.19 | K79: =_xlfn.XLOOKUP(C79,MOPFRA!$R$7:$R$56,MOPFRA!$T$7:$T$56,"")/1000 -> 705.01124 | L79: =_xlfn.XLOOKUP(C79,'MOPFRA Portfolio'!$P$8:$P$78,'MOPFRA Portfolio'!$AT$8:$AT$78,"") -> 1000000 | M79: =_xlfn.XLOOKUP(C79,'MOPFRA Portfolio'!$P$8:$P$78,'MOPFRA Portfolio'!$AU$8:$AU$78,"") -> 1114108.8 | O79: =IF(AND(Q79<0,R79<0,Q79<R79),Q79-R79,"") | P79: =IF(AND(Q79>=0,R79>=0,Q79>R79),Q79-R79,"") -> 8.248891 | Q79: =IFERROR(((K79-AA79)*100)/ABS($K$106),"") -> 11.23914 | R79: =IFERROR((($AB79*$G79*0.9912*0.0001)-AC79)*100/ABS($AC$108),"") -> 2.9902491 | S79: =IF(AND(R79>0,Q79>0,R79>Q79),R79-Q79,"") | T79: =IF(AND(R79<0,Q79<0,R79<Q79),R79-Q79,"") | V79: 10610 | W79: 10920 | X79: 10920 | Y79: 1816 | Z79: 6.01 | AA79: 684.93975 | AB79: 1000000 | AC79: 1082390.4
A80: =IFERROR(MATCH(C80,'دیده بان بازار'!$A$5:$A$3994,0 )+4,"Closed") -> 664 | B80: نفت ايرانول | C80: شرانل | D80: =_xlfn.XLOOKUP(C80,MOPFRA!$R$7:$R$56,MOPFRA!$P$7:$P$56,"") -> L | F80: =IFERROR(_xlfn.LET(_xlpm.lookup_result,_xlfn.XLOOKUP($C80,'دیده بان بازار'!$A$5:$A$3994,'دیده بان بازار'!F$5:F$3994),IF(ISERROR(_xlpm.lookup_result),V80,_xlpm.lookup_result)),V80) -> 84220 | G80: =IFERROR(_xlfn.LET(_xlpm.lookup_result,_xlfn.XLOOKUP($C80,'دیده بان بازار'!$A$5:$A$3994,'دیده بان بازار'!H$5:H$3994),IF(ISERROR(_xlpm.lookup_result),W80,_xlpm.lookup_result)),W80) -> 86740 | H80: =IFERROR(_xlfn.LET(_xlpm.lookup_result,_xlfn.XLOOKUP($C80,'دیده بان بازار'!$A$5:$A$3994,'دیده بان بازار'!K$5:K$3994),IF(ISERROR(_xlpm.lookup_result),X80,_xlpm.lookup_result)),X80) -> 86740 | I80: =IFERROR(_xlfn.LET(_xlpm.lookup_result,_xlfn.XLOOKUP($C80,'دیده بان بازار'!$A$5:$A$3994,'دیده بان بازار'!P$5:P$3994),IF(ISERROR(_xlpm.lookup_result),Y80,_xlpm.lookup_result)),Y80) -> 13150 | J80: =IFERROR(_xlfn.LET(_xlpm.lookup_result,_xlfn.XLOOKUP($C80,'دیده بان بازار'!$A$5:$A$3994,'دیده بان بازار'!Q$5:Q$3994),IF(ISERROR(_xlpm.lookup_result),Z80,_xlpm.lookup_result)),Z80) -> 6.6 | K80: =_xlfn.XLOOKUP(C80,MOPFRA!$R$7:$R$56,MOPFRA!$T$7:$T$56,"")/1000 -> 52.044 | L80: =_xlfn.XLOOKUP(C80,'MOPFRA Portfolio'!$P$8:$P$78,'MOPFRA Portfolio'!$AT$8:$AT$78,"") -> 40000 | M80: =_xlfn.XLOOKUP(C80,'MOPFRA Portfolio'!$P$8:$P$78,'MOPFRA Portfolio'!$AU$8:$AU$78,"") -> 343906.75 | P80: =IF(AND(Q80>=0,R80>=0,Q80>R80),Q80-R80,"") | Q80: =IFERROR(((K80-AA80)*100)/ABS($K$106),"") -> 0.84665245 | R80: =IFERROR((($AB80*$G80*0.9912*0.0001)-AC80)*100/ABS($AC$108),"") -> 0.94192848 | V80: 81770 | W80: 84220 | X80: 84220 | Y80: 13150 | Z80: 6.4 | AA80: 50.532 | AB80: 40000 | AC80: 333915.46
A81: =IFERROR(MATCH(C81,'دیده بان بازار'!$A$5:$A$3994,0 )+4,"Closed") -> Closed | B81: نفت‌ بهران‌ | C81: شبهرن | D81: =_xlfn.XLOOKUP(C81,MOPFRA!$R$7:$R$56,MOPFRA!$P$7:$P$56,"") -> L | F81: =IFERROR(_xlfn.LET(_xlpm.lookup_result,_xlfn.XLOOKUP($C81,'دیده بان بازار'!$A$5:$A$3994,'دیده بان بازار'!F$5:F$3994),IF(ISERROR(_xlpm.lookup_result),V81,_xlpm.lookup_result)),V81) -> 35790 | G81: =IFERROR(_xlfn.LET(_xlpm.lookup_result,_xlfn.XLOOKUP($C81,'دیده بان بازار'!$A$5:$A$3994,'دیده بان بازار'!H$5:H$3994),IF(ISERROR(_xlpm.lookup_result),W81,_xlpm.lookup_result)),W81) -> 32300 | H81: =IFERROR(_xlfn.LET(_xlpm.lookup_result,_xlfn.XLOOKUP($C81,'دیده بان بازار'!$A$5:$A$3994,'دیده بان بازار'!K$5:K$3994),IF(ISERROR(_xlpm.lookup_result),X81,_xlpm.lookup_result)),X81) -> 32300 | I81: =IFERROR(_xlfn.LET(_xlpm.lookup_result,_xlfn.XLOOKUP($C81,'دیده بان بازار'!$A$5:$A$3994,'دیده بان بازار'!P$5:P$3994),IF(ISERROR(_xlpm.lookup_result),Y81,_xlpm.lookup_result)),Y81) -> 4271 | J81: =IFERROR(_xlfn.LET(_xlpm.lookup_result,_xlfn.XLOOKUP($C81,'دیده بان بازار'!$A$5:$A$3994,'دیده بان بازار'!Q$5:Q$3994),IF(ISERROR(_xlpm.lookup_result),Z81,_xlpm.lookup_result)),Z81) -> 8.27 | K81: =_xlfn.XLOOKUP(C81,MOPFRA!$R$7:$R$56,MOPFRA!$T$7:$T$56,"")/1000 -> 58.14 | L81: =_xlfn.XLOOKUP(C81,'MOPFRA Portfolio'!$P$8:$P$78,'MOPFRA Portfolio'!$AT$8:$AT$78,"") -> 70000 | M81: =_xlfn.XLOOKUP(C81,'MOPFRA Portfolio'!$P$8:$P$78,'MOPFRA Portfolio'!$AU$8:$AU$78,"") -> 224110.32 | Q81: =IFERROR(((K81-AA81)*100)/ABS($K$106),"") -> 0 | R81: =IFERROR((($AB81*$G81*0.9912*0.0001)-AC81)*100/ABS($AC$108),"") -> 0 | V81: 35790 | W81: 32300 | X81: 32300 | Y81: 4271 | Z81: 8.27 | AA81: 58.14 | AB81: 70000 | AC81: 224110.32
A82: =IFERROR(MATCH(C82,'دیده بان بازار'!$A$5:$A$3994,0 )+4,"Closed") -> 1772 | B82: ايران‌ تاير | C82: پتاير | D82: =_xlfn.XLOOKUP(C82,MOPFRA!$R$7:$R$56,MOPFRA!$P$7:$P$56,"") -> T | F82: =IFERROR(_xlfn.LET(_xlpm.lookup_result,_xlfn.XLOOKUP($C82,'دیده بان بازار'!$A$5:$A$3994,'دیده بان بازار'!F$5:F$3994),IF(ISERROR(_xlpm.lookup_result),V82,_xlpm.lookup_result)),V82) -> 2027 | G82: =IFERROR(_xlfn.LET(_xlpm.lookup_result,_xlfn.XLOOKUP($C82,'دیده بان بازار'!$A$5:$A$3994,'دیده بان بازار'!H$5:H$3994),IF(ISERROR(_xlpm.lookup_result),W82,_xlpm.lookup_result)),W82) -> 2087 | H82: =IFERROR(_xlfn.LET(_xlpm.lookup_result,_xlfn.XLOOKUP($C82,'دیده بان بازار'!$A$5:$A$3994,'دیده بان بازار'!K$5:K$3994),IF(ISERROR(_xlpm.lookup_result),X82,_xlpm.lookup_result)),X82) -> 2087 | I82: =IFERROR(_xlfn.LET(_xlpm.lookup_result,_xlfn.XLOOKUP($C82,'دیده بان بازار'!$A$5:$A$3994,'دیده بان بازار'!P$5:P$3994),IF(ISERROR(_xlpm.lookup_result),Y82,_xlpm.lookup_result)),Y82) -> 392 | J82: =IFERROR(_xlfn.LET(_xlpm.lookup_result,_xlfn.XLOOKUP($C82,'دیده بان بازار'!$A$5:$A$3994,'دیده بان بازار'!Q$5:Q$3994),IF(ISERROR(_xlpm.lookup_result),Z82,_xlpm.lookup_result)),Z82) -> 5.32 | K82: =_xlfn.XLOOKUP(C82,MOPFRA!$R$7:$R$56,MOPFRA!$T$7:$T$56,"")/1000 -> 3.92356 | L82: =_xlfn.XLOOKUP(C82,'MOPFRA Portfolio'!$P$8:$P$78,'MOPFRA Portfolio'!$AT$8:$AT$78,"") -> 0 | M82: =_xlfn.XLOOKUP(C82,'MOPFRA Portfolio'!$P$8:$P$78,'MOPFRA Portfolio'!$AU$8:$AU$78,"") -> 0 | O82: =IF(AND(Q82<0,R82<0,Q82<R82),Q82-R82,"") | P82: =IF(AND(Q82>=0,R82>=0,Q82>R82),Q82-R82,"") -> 0.06316296 | Q82: =IFERROR(((K82-AA82)*100)/ABS($K$106),"") -> 0.06316296 | R82: =IFERROR((($AB82*$G82*0.9912*0.0001)-AC82)*100/ABS($AC$108),"") -> 0 | S82: =IF(AND(R82>0,Q82>0,R82>Q82),R82-Q82,"") | T82: =IF(AND(R82<0,Q82<0,R82<Q82),R82-Q82,"") | V82: 1968 | W82: 2027 | X82: 2027 | Y82: 392 | Z82: 5.17 | AA82: 3.81076 | AB82: 0 | AC82: 0
A83: =IFERROR(MATCH(C83,'دیده بان بازار'!$A$5:$A$3994,0 )+4,"Closed") -> 2519 | B83: كوير تاير | C83: پكوير | D83: =_xlfn.XLOOKUP(C83,MOPFRA!$R$7:$R$56,MOPFRA!$P$7:$P$56,"") -> T | F83: =IFERROR(_xlfn.LET(_xlpm.lookup_result,_xlfn.XLOOKUP($C83,'دیده بان بازار'!$A$5:$A$3994,'دیده بان بازار'!F$5:F$3994),IF(ISERROR(_xlpm.lookup_result),V83,_xlpm.lookup_result)),V83) -> 6310 | G83: =IFERROR(_xlfn.LET(_xlpm.lookup_result,_xlfn.XLOOKUP($C83,'دیده بان بازار'!$A$5:$A$3994,'دیده بان بازار'!H$5:H$3994),IF(ISERROR(_xlpm.lookup_result),W83,_xlpm.lookup_result)),W83) -> 6490 | H83: =IFERROR(_xlfn.LET(_xlpm.lookup_result,_xlfn.XLOOKUP($C83,'دیده بان بازار'!$A$5:$A$3994,'دیده بان بازار'!K$5:K$3994),IF(ISERROR(_xlpm.lookup_result),X83,_xlpm.lookup_result)),X83) -> 6460 | I83: =IFERROR(_xlfn.LET(_xlpm.lookup_result,_xlfn.XLOOKUP($C83,'دیده بان بازار'!$A$5:$A$3994,'دیده بان بازار'!P$5:P$3994),IF(ISERROR(_xlpm.lookup_result),Y83,_xlpm.lookup_result)),Y83) -> 1338 | J83: =IFERROR(_xlfn.LET(_xlpm.lookup_result,_xlfn.XLOOKUP($C83,'دیده بان بازار'!$A$5:$A$3994,'دیده بان بازار'!Q$5:Q$3994),IF(ISERROR(_xlpm.lookup_result),Z83,_xlpm.lookup_result)),Z83) -> 4.83 | K83: =_xlfn.XLOOKUP(C83,MOPFRA!$R$7:$R$56,MOPFRA!$T$7:$T$56,"")/1000 -> 8.8710512 | L83: =_xlfn.XLOOKUP(C83,'MOPFRA Portfolio'!$P$8:$P$78,'MOPFRA Portfolio'!$AT$8:$AT$78,"") -> 0 | M83: =_xlfn.XLOOKUP(C83,'MOPFRA Portfolio'!$P$8:$P$78,'MOPFRA Portfolio'!$AU$8:$AU$78,"") -> 0 | O83: =IF(AND(Q83<0,R83<0,Q83<R83),Q83-R83,"") | P83: =IF(AND(Q83>=0,R83>=0,Q83>R83),Q83-R83,"") -> 0.12246268 | Q83: =IFERROR(((K83-AA83)*100)/ABS($K$106),"") -> 0.12246268 | R83: =IFERROR((($AB83*$G83*0.9912*0.0001)-AC83)*100/ABS($AC$108),"") -> 0 | S83: =IF(AND(R83>0,Q83>0,R83>Q83),R83-Q83,"") | T83: =IF(AND(R83<0,Q83<0,R83<Q83),R83-Q83,"") | V83: 6150 | W83: 6330 | X83: 6310 | Y83: 1338 | Z83: 4.72 | AA83: 8.6523504 | AB83: 0 | AC83: 0
A84: =IFERROR(MATCH(C84,'دیده بان بازار'!$A$5:$A$3994,0 )+4,"Closed") -> 1889 | B84: ايران‌ياساتايرورابر | C84: پاسا | D84: =_xlfn.XLOOKUP(C84,MOPFRA!$R$7:$R$56,MOPFRA!$P$7:$P$56,"") -> T | F84: =IFERROR(_xlfn.LET(_xlpm.lookup_result,_xlfn.XLOOKUP($C84,'دیده بان بازار'!$A$5:$A$3994,'دیده بان بازار'!F$5:F$3994),IF(ISERROR(_xlpm.lookup_result),V84,_xlpm.lookup_result)),V84) -> 7970 | G84: =IFERROR(_xlfn.LET(_xlpm.lookup_result,_xlfn.XLOOKUP($C84,'دیده بان بازار'!$A$5:$A$3994,'دیده بان بازار'!H$5:H$3994),IF(ISERROR(_xlpm.lookup_result),W84,_xlpm.lookup_result)),W84) -> 8200 | H84: =IFERROR(_xlfn.LET(_xlpm.lookup_result,_xlfn.XLOOKUP($C84,'دیده بان بازار'!$A$5:$A$3994,'دیده بان بازار'!K$5:K$3994),IF(ISERROR(_xlpm.lookup_result),X84,_xlpm.lookup_result)),X84) -> 8200 | I84: =IFERROR(_xlfn.LET(_xlpm.lookup_result,_xlfn.XLOOKUP($C84,'دیده بان بازار'!$A$5:$A$3994,'دیده بان بازار'!P$5:P$3994),IF(ISERROR(_xlpm.lookup_result),Y84,_xlpm.lookup_result)),Y84) -> 2053 | J84: =IFERROR(_xlfn.LET(_xlpm.lookup_result,_xlfn.XLOOKUP($C84,'دیده بان بازار'!$A$5:$A$3994,'دیده بان بازار'!Q$5:Q$3994),IF(ISERROR(_xlpm.lookup_result),Z84,_xlpm.lookup_result)),Z84) -> 3.99 | K84: =_xlfn.XLOOKUP(C84,MOPFRA!$R$7:$R$56,MOPFRA!$T$7:$T$56,"")/1000 -> 3.526 | L84: =_xlfn.XLOOKUP(C84,'MOPFRA Portfolio'!$P$8:$P$78,'MOPFRA Portfolio'!$AT$8:$AT$78,"") -> 45263 | M84: =_xlfn.XLOOKUP(C84,'MOPFRA Portfolio'!$P$8:$P$78,'MOPFRA Portfolio'!$AU$8:$AU$78,"") -> 36789.042 | O84: =IF(AND(Q84<0,R84<0,Q84<R84),Q84-R84,"") | P84: =IF(AND(Q84>=0,R84>=0,Q84>R84),Q84-R84,"") | Q84: =IFERROR(((K84-AA84)*100)/ABS($K$106),"") -> 0.055379581 | R84: =IFERROR((($AB84*$G84*0.9912*0.0001)-AC84)*100/ABS($AC$108),"") -> 0.097281121 | S84: =IF(AND(R84>0,Q84>0,R84>Q84),R84-Q84,"") -> 0.041901539 | T84: =IF(AND(R84<0,Q84<0,R84<Q84),R84-Q84,"") | V84: 7740 | W84: 7970 | X84: 7970 | Y84: 2053 | Z84: 3.88 | AA84: 3.4271 | AB84: 45263 | AC84: 35757.154
A85: =IFERROR(MATCH(C85,'دیده بان بازار'!$A$5:$A$3994,0 )+4,"Closed") -> 2601 | B85: گروه‌ صنعتي‌ بارز | C85: پكرمان | D85: =_xlfn.XLOOKUP(C85,MOPFRA!$R$7:$R$56,MOPFRA!$P$7:$P$56,"") -> T | F85: =IFERROR(_xlfn.LET(_xlpm.lookup_result,_xlfn.XLOOKUP($C85,'دیده بان بازار'!$A$5:$A$3994,'دیده بان بازار'!F$5:F$3994),IF(ISERROR(_xlpm.lookup_result),V85,_xlpm.lookup_result)),V85) -> 6330 | G85: =IFERROR(_xlfn.LET(_xlpm.lookup_result,_xlfn.XLOOKUP($C85,'دیده بان بازار'!$A$5:$A$3994,'دیده بان بازار'!H$5:H$3994),IF(ISERROR(_xlpm.lookup_result),W85,_xlpm.lookup_result)),W85) -> 6510 | H85: =IFERROR(_xlfn.LET(_xlpm.lookup_result,_xlfn.XLOOKUP($C85,'دیده بان بازار'!$A$5:$A$3994,'دیده بان بازار'!K$5:K$3994),IF(ISERROR(_xlpm.lookup_result),X85,_xlpm.lookup_result)),X85) -> 6470 | I85: =IFERROR(_xlfn.LET(_xlpm.lookup_result,_xlfn.XLOOKUP($C85,'دیده بان بازار'!$A$5:$A$3994,'دیده بان بازار'!P$5:P$3994),IF(ISERROR(_xlpm.lookup_result),Y85,_xlpm.lookup_result)),Y85) -> 953 | J85: =IFERROR(_xlfn.LET(_xlpm.lookup_result,_xlfn.XLOOKUP($C85,'دیده بان بازار'!$A$5:$A$3994,'دیده بان بازار'!Q$5:Q$3994),IF(ISERROR(_xlpm.lookup_result),Z85,_xlpm.lookup_result)),Z85) -> 6.79 | K85: =_xlfn.XLOOKUP(C85,MOPFRA!$R$7:$R$56,MOPFRA!$T$7:$T$56,"")/1000 -> 11.973344 | L85: =_xlfn.XLOOKUP(C85,'MOPFRA Portfolio'!$P$8:$P$78,'MOPFRA Portfolio'!$AT$8:$AT$78,"") -> 0 | M85: =_xlfn.XLOOKUP(C85,'MOPFRA Portfolio'!$P$8:$P$78,'MOPFRA Portfolio'!$AU$8:$AU$78,"") -> 0 | O85: =IF(AND(Q85<0,R85<0,Q85<R85),Q85-R85,"") | P85: =IF(AND(Q85>=0,R85>=0,Q85>R85),Q85-R85,"") | Q85: =IFERROR(((K85-AA85)*100)/ABS($K$106),"") -> 0 | R85: =IFERROR((($AB85*$G85*0.9912*0.0001)-AC85)*100/ABS($AC$108),"") -> 0 | S85: =IF(AND(R85>0,Q85>0,R85>Q85),R85-Q85,"") | T85: =IF(AND(R85<0,Q85<0,R85<Q85),R85-Q85,"") | V85: 6160 | W85: 6340 | X85: 6330 | Y85: 953 | Z85: 6.64 | AA85: 11.973344 | AB85: 0 | AC85: 0
A86: =IFERROR(MATCH(C86,'دیده بان بازار'!$A$5:$A$3994,0 )+4,"Closed") -> 503 | B86: صندوق س. كالاي كهربا | C86: كهربا | D86: GF | F86: =IFERROR(_xlfn.LET(_xlpm.lookup_result,_xlfn.XLOOKUP($C86,'دیده بان بازار'!$A$5:$A$3994,'دیده بان بازار'!F$5:F$3994),IF(ISERROR(_xlpm.lookup_result),V86,_xlpm.lookup_result)),V86) -> 176256 | G86: =IFERROR(_xlfn.LET(_xlpm.lookup_result,_xlfn.XLOOKUP($C86,'دیده بان بازار'!$A$5:$A$3994,'دیده بان بازار'!H$5:H$3994),IF(ISERROR(_xlpm.lookup_result),W86,_xlpm.lookup_result)),W86) -> 175200 | H86: =IFERROR(_xlfn.LET(_xlpm.lookup_result,_xlfn.XLOOKUP($C86,'دیده بان بازار'!$A$5:$A$3994,'دیده بان بازار'!K$5:K$3994),IF(ISERROR(_xlpm.lookup_result),X86,_xlpm.lookup_result)),X86) -> 175399 | I86: =IFERROR(_xlfn.LET(_xlpm.lookup_result,_xlfn.XLOOKUP($C86,'دیده بان بازار'!$A$5:$A$3994,'دیده بان بازار'!P$5:P$3994),IF(ISERROR(_xlpm.lookup_result),Y86,_xlpm.lookup_result)),Y86) | J86: =IFERROR(_xlfn.LET(_xlpm.lookup_result,_xlfn.XLOOKUP($C86,'دیده بان بازار'!$A$5:$A$3994,'دیده بان بازار'!Q$5:Q$3994),IF(ISERROR(_xlpm.lookup_result),Z86,_xlpm.lookup_result)),Z86) | K86: =_xlfn.XLOOKUP(C86,'MOPFRA Portfolio'!P61:P75,'MOPFRA Portfolio'!Z61:Z75,"")/1000 -> 175.2 | L86: =_xlfn.XLOOKUP(C86,'MOPFRA Portfolio'!$P$8:$P$78,'MOPFRA Portfolio'!$AT$8:$AT$78,"") -> 300000 | M86: =_xlfn.XLOOKUP(C86,'MOPFRA Portfolio'!$P$8:$P$78,'MOPFRA Portfolio'!$AU$8:$AU$78,"") -> 5209747.2 | V86: 175626 | W86: 176281 | X86: 176256 | AA86: 176.281 | AB86: 270000 | AC86: 4717702.6
A87: =IFERROR(MATCH(C87,'دیده بان بازار'!$A$5:$A$3994,0 )+4,"Closed") -> 1887 | B87: صندوق طلاي عيار مفيد | C87: عيار | D87: GF | F87: =IFERROR(_xlfn.LET(_xlpm.lookup_result,_xlfn.XLOOKUP($C87,'دیده بان بازار'!$A$5:$A$3994,'دیده بان بازار'!F$5:F$3994),IF(ISERROR(_xlpm.lookup_result),V87,_xlpm.lookup_result)),V87) -> 508624 | G87: =IFERROR(_xlfn.LET(_xlpm.lookup_result,_xlfn.XLOOKUP($C87,'دیده بان بازار'!$A$5:$A$3994,'دیده بان بازار'!H$5:H$3994),IF(ISERROR(_xlpm.lookup_result),W87,_xlpm.lookup_result)),W87) -> 504830 | H87: =IFERROR(_xlfn.LET(_xlpm.lookup_result,_xlfn.XLOOKUP($C87,'دیده بان بازار'!$A$5:$A$3994,'دیده بان بازار'!K$5:K$3994),IF(ISERROR(_xlpm.lookup_result),X87,_xlpm.lookup_result)),X87) -> 505491 | I87: =IFERROR(_xlfn.LET(_xlpm.lookup_result,_xlfn.XLOOKUP($C87,'دیده بان بازار'!$A$5:$A$3994,'دیده بان بازار'!P$5:P$3994),IF(ISERROR(_xlpm.lookup_result),Y87,_xlpm.lookup_result)),Y87) | J87: =IFERROR(_xlfn.LET(_xlpm.lookup_result,_xlfn.XLOOKUP($C87,'دیده بان بازار'!$A$5:$A$3994,'دیده بان بازار'!Q$5:Q$3994),IF(ISERROR(_xlpm.lookup_result),Z87,_xlpm.lookup_result)),Z87) | K87: =_xlfn.XLOOKUP(C87,'MOPFRA Portfolio'!P62:P76,'MOPFRA Portfolio'!Z62:Z76,"")/1000 -> 504.83 | L87: =_xlfn.XLOOKUP(C87,'MOPFRA Portfolio'!$P$8:$P$78,'MOPFRA Portfolio'!$AT$8:$AT$78,"") -> 20000 | M87: =_xlfn.XLOOKUP(C87,'MOPFRA Portfolio'!$P$8:$P$78,'MOPFRA Portfolio'!$AU$8:$AU$78,"") -> 1000775 | V87: 506257 | W87: 508199 | X87: 508624 | AA87: 508.199 | AB87: 20000 | AC87: 1007453.7
A88: =IFERROR(MATCH(C88,'دیده بان بازار'!$A$5:$A$3994,0 )+4,"Closed") -> 1774 | B88: بانك ملت | C88: وبملت | D88: B | F88: =IFERROR(_xlfn.LET(_xlpm.lookup_result,_xlfn.XLOOKUP($C88,'دیده بان بازار'!$A$5:$A$3994,'دیده بان بازار'!F$5:F$3994),IF(ISERROR(_xlpm.lookup_result),V88,_xlpm.lookup_result)),V88) -> 1199 | G88: =IFERROR(_xlfn.LET(_xlpm.lookup_result,_xlfn.XLOOKUP($C88,'دیده بان بازار'!$A$5:$A$3994,'دیده بان بازار'!H$5:H$3994),IF(ISERROR(_xlpm.lookup_result),W88,_xlpm.lookup_result)),W88) -> 1234 | H88: =IFERROR(_xlfn.LET(_xlpm.lookup_result,_xlfn.XLOOKUP($C88,'دیده بان بازار'!$A$5:$A$3994,'دیده بان بازار'!K$5:K$3994),IF(ISERROR(_xlpm.lookup_result),X88,_xlpm.lookup_result)),X88) -> 1234 | I88: =IFERROR(_xlfn.LET(_xlpm.lookup_result,_xlfn.XLOOKUP($C88,'دیده بان بازار'!$A$5:$A$3994,'دیده بان بازار'!P$5:P$3994),IF(ISERROR(_xlpm.lookup_result),Y88,_xlpm.lookup_result)),Y88) -> 454 | J88: =IFERROR(_xlfn.LET(_xlpm.lookup_result,_xlfn.XLOOKUP($C88,'دیده بان بازار'!$A$5:$A$3994,'دیده بان بازار'!Q$5:Q$3994),IF(ISERROR(_xlpm.lookup_result),Z88,_xlpm.lookup_result)),Z88) -> 2.72 | K88: =_xlfn.XLOOKUP(C88,'MOPFRA Portfolio'!P64:P76,'MOPFRA Portfolio'!Z64:Z76,"")/1000 -> 417.3388 | L88: =_xlfn.XLOOKUP(C88,'MOPFRA Portfolio'!$P$8:$P$78,'MOPFRA Portfolio'!$AT$8:$AT$78,"") -> 2000000 | M88: =_xlfn.XLOOKUP(C88,'MOPFRA Portfolio'!$P$8:$P$78,'MOPFRA Portfolio'!$AU$8:$AU$78,"") -> 244628.16 | O88: =IF(AND(Q88<0,R88<0,Q88<R88),Q88-R88,"") | P88: =IF(AND(Q88>=0,R88>=0,Q88>R88),Q88-R88,"") -> 5.9740742 | Q88: =IFERROR(((K88-AA88)*100)/ABS($K$106),"") -> 6.6281912 | R88: =IFERROR((($AB88*$G88*0.9912*0.0001)-AC88)*100/ABS($AC$108),"") -> 0.654117 | S88: =IF(AND(R88>0,Q88>0,R88>Q88),R88-Q88,"") | T88: =IF(AND(R88<0,Q88<0,R88<Q88),R88-Q88,"") | V88: 1165 | W88: 1199 | X88: 1199 | Y88: 454 | Z88: 2.64 | AA88: 405.5018 | AB88: 2000000 | AC88: 237689.76
A89: =IFERROR(MATCH(C89,'دیده بان بازار'!$A$5:$A$3994,0 )+4,"Closed") -> 2649 | B89: بانك تجارت | C89: وتجارت | D89: B | F89: =IFERROR(_xlfn.LET(_xlpm.lookup_result,_xlfn.XLOOKUP($C89,'دیده بان بازار'!$A$5:$A$3994,'دیده بان بازار'!F$5:F$3994),IF(ISERROR(_xlpm.lookup_result),V89,_xlpm.lookup_result)),V89) -> 642 | G89: =IFERROR(_xlfn.LET(_xlpm.lookup_result,_xlfn.XLOOKUP($C89,'دیده بان بازار'!$A$5:$A$3994,'دیده بان بازار'!H$5:H$3994),IF(ISERROR(_xlpm.lookup_result),W89,_xlpm.lookup_result)),W89) -> 661 | H89: =IFERROR(_xlfn.LET(_xlpm.lookup_result,_xlfn.XLOOKUP($C89,'دیده بان بازار'!$A$5:$A$3994,'دیده بان بازار'!K$5:K$3994),IF(ISERROR(_xlpm.lookup_result),X89,_xlpm.lookup_result)),X89) -> 661 | I89: =IFERROR(_xlfn.LET(_xlpm.lookup_result,_xlfn.XLOOKUP($C89,'دیده بان بازار'!$A$5:$A$3994,'دیده بان بازار'!P$5:P$3994),IF(ISERROR(_xlpm.lookup_result),Y89,_xlpm.lookup_result)),Y89) -> 105 | J89: =IFERROR(_xlfn.LET(_xlpm.lookup_result,_xlfn.XLOOKUP($C89,'دیده بان بازار'!$A$5:$A$3994,'دیده بان بازار'!Q$5:Q$3994),IF(ISERROR(_xlpm.lookup_result),Z89,_xlpm.lookup_result)),Z89) -> 6.3 | K89: =_xlfn.XLOOKUP(C89,'MOPFRA Portfolio'!P65:P78,'MOPFRA Portfolio'!Z65:Z78,"")/1000 -> 105.13866 | L89: =_xlfn.XLOOKUP(C89,'MOPFRA Portfolio'!$P$8:$P$78,'MOPFRA Portfolio'!$AT$8:$AT$78,"") -> 859705 | M89: =_xlfn.XLOOKUP(C89,'MOPFRA Portfolio'!$P$8:$P$78,'MOPFRA Portfolio'!$AU$8:$AU$78,"") -> 56326.427 | O89: =IF(AND(Q89<0,R89<0,Q89<R89),Q89-R89,"") | P89: =IF(AND(Q89>=0,R89>=0,Q89>R89),Q89-R89,"") -> 1.5396262 | Q89: =IFERROR(((K89-AA89)*100)/ABS($K$106),"") -> 1.6922634 | R89: =IFERROR((($AB89*$G89*0.9912*0.0001)-AC89)*100/ABS($AC$108),"") -> 0.15263722 | S89: =IF(AND(R89>0,Q89>0,R89>Q89),R89-Q89,"") | T89: =IF(AND(R89<0,Q89<0,R89<Q89),R89-Q89,"") | V89: 624 | W89: 642 | X89: 642 | Y89: 105 | Z89: 6.11 | AA89: 102.11652 | AB89: 859705 | AC89: 54707.362
A90: =IFERROR(MATCH(C90,'دیده بان بازار'!$A$5:$A$3994,0 )+4,"Closed") -> 2170 | B90: بانك سامان | C90: سامان | D90: B | F90: =IFERROR(_xlfn.LET(_xlpm.lookup_result,_xlfn.XLOOKUP($C90,'دیده بان بازار'!$A$5:$A$3994,'دیده بان بازار'!F$5:F$3994),IF(ISERROR(_xlpm.lookup_result),V90,_xlpm.lookup_result)),V90) -> 7420 | G90: =IFERROR(_xlfn.LET(_xlpm.lookup_result,_xlfn.XLOOKUP($C90,'دیده بان بازار'!$A$5:$A$3994,'دیده بان بازار'!H$5:H$3994),IF(ISERROR(_xlpm.lookup_result),W90,_xlpm.lookup_result)),W90) -> 7640 | H90: =IFERROR(_xlfn.LET(_xlpm.lookup_result,_xlfn.XLOOKUP($C90,'دیده بان بازار'!$A$5:$A$3994,'دیده بان بازار'!K$5:K$3994),IF(ISERROR(_xlpm.lookup_result),X90,_xlpm.lookup_result)),X90) -> 7640 | I90: =IFERROR(_xlfn.LET(_xlpm.lookup_result,_xlfn.XLOOKUP($C90,'دیده بان بازار'!$A$5:$A$3994,'دیده بان بازار'!P$5:P$3994),IF(ISERROR(_xlpm.lookup_result),Y90,_xlpm.lookup_result)),Y90) -> 1396 | J90: =IFERROR(_xlfn.LET(_xlpm.lookup_result,_xlfn.XLOOKUP($C90,'دیده بان بازار'!$A$5:$A$3994,'دیده بان بازار'!Q$5:Q$3994),IF(ISERROR(_xlpm.lookup_result),Z90,_xlpm.lookup_result)),Z90) -> 5.47 | K90: =_xlfn.XLOOKUP(C90,'MOPFRA Portfolio'!P66:P79,'MOPFRA Portfolio'!Z66:Z79,"")/1000 -> 120.712 | L90: =_xlfn.XLOOKUP(C90,'MOPFRA Portfolio'!$P$8:$P$78,'MOPFRA Portfolio'!$AT$8:$AT$78,"") -> 70000 | M90: =_xlfn.XLOOKUP(C90,'MOPFRA Portfolio'!$P$8:$P$78,'MOPFRA Portfolio'!$AU$8:$AU$78,"") -> 53009.376 | O90: =IF(AND(Q90<0,R90<0,Q90<R90),Q90-R90,"") | P90: =IF(AND(Q90>=0,R90>=0,Q90>R90),Q90-R90,"") -> 1.802499 | Q90: =IFERROR(((K90-AA90)*100)/ABS($K$106),"") -> 1.9464047 | R90: =IFERROR((($AB90*$G90*0.9912*0.0001)-AC90)*100/ABS($AC$108),"") -> 0.14390574 | S90: =IF(AND(R90>0,Q90>0,R90>Q90),R90-Q90,"") | T90: =IF(AND(R90<0,Q90<0,R90<Q90),R90-Q90,"") | V90: 7210 | W90: 7420 | X90: 7420 | Y90: 1396 | Z90: 5.32 | AA90: 117.236 | AB90: 70000 | AC90: 51482.928
A91: =IFERROR(MATCH(C91,'دیده بان بازار'!$A$5:$A$3994,0 )+4,"Closed") -> 1443 | B91: بانك سينا | C91: وسينا | D91: B | F91: =IFERROR(_xlfn.LET(_xlpm.lookup_result,_xlfn.XLOOKUP($C91,'دیده بان بازار'!$A$5:$A$3994,'دیده بان بازار'!F$5:F$3994),IF(ISERROR(_xlpm.lookup_result),V91,_xlpm.lookup_result)),V91) -> 2718 | G91: =IFERROR(_xlfn.LET(_xlpm.lookup_result,_xlfn.XLOOKUP($C91,'دیده بان بازار'!$A$5:$A$3994,'دیده بان بازار'!H$5:H$3994),IF(ISERROR(_xlpm.lookup_result),W91,_xlpm.lookup_result)),W91) -> 2799 | H91: =IFERROR(_xlfn.LET(_xlpm.lookup_result,_xlfn.XLOOKUP($C91,'دیده بان بازار'!$A$5:$A$3994,'دیده بان بازار'!K$5:K$3994),IF(ISERROR(_xlpm.lookup_result),X91,_xlpm.lookup_result)),X91) -> 2799 | I91: =IFERROR(_xlfn.LET(_xlpm.lookup_result,_xlfn.XLOOKUP($C91,'دیده بان بازار'!$A$5:$A$3994,'دیده بان بازار'!P$5:P$3994),IF(ISERROR(_xlpm.lookup_result),Y91,_xlpm.lookup_result)),Y91) -> 584 | J91: =IFERROR(_xlfn.LET(_xlpm.lookup_result,_xlfn.XLOOKUP($C91,'دیده بان بازار'!$A$5:$A$3994,'دیده بان بازار'!Q$5:Q$3994),IF(ISERROR(_xlpm.lookup_result),Z91,_xlpm.lookup_result)),Z91) -> 4.79 | K91: =_xlfn.XLOOKUP(C91,'MOPFRA Portfolio'!P67:P80,'MOPFRA Portfolio'!Z67:Z80,"")/1000 -> 21.868587 | L91: =_xlfn.XLOOKUP(C91,'MOPFRA Portfolio'!$P$8:$P$78,'MOPFRA Portfolio'!$AT$8:$AT$78,"") -> 120000 | M91: =_xlfn.XLOOKUP(C91,'MOPFRA Portfolio'!$P$8:$P$78,'MOPFRA Portfolio'!$AU$8:$AU$78,"") -> 33292.426 | O91: =IF(AND(Q91<0,R91<0,Q91<R91),Q91-R91,"") | P91: =IF(AND(Q91>=0,R91>=0,Q91>R91),Q91-R91,"") -> 0.26354059 | Q91: =IFERROR(((K91-AA91)*100)/ABS($K$106),"") -> 0.35436941 | R91: =IFERROR((($AB91*$G91*0.9912*0.0001)-AC91)*100/ABS($AC$108),"") -> 0.090828817 | S91: =IF(AND(R91>0,Q91>0,R91>Q91),R91-Q91,"") | T91: =IF(AND(R91<0,Q91<0,R91<Q91),R91-Q91,"") | V91: 2639 | W91: 2718 | X91: 2718 | Y91: 584 | Z91: 4.65 | AA91: 21.235734 | AB91: 120000 | AC91: 32328.979
A92: =IFERROR(MATCH(C92,'دیده بان بازار'!$A$5:$A$3994,0 )+4,"Closed") -> 1921 | B92: صندوق س صنايع انديشه صبا2-بخشي | C92: بنكر | D92: BF | F92: =IFERROR(_xlfn.LET(_xlpm.lookup_result,_xlfn.XLOOKUP($C92,'دیده بان بازار'!$A$5:$A$3994,'دیده بان بازار'!F$5:F$3994),IF(ISERROR(_xlpm.lookup_result),V92,_xlpm.lookup_result)),V92) -> 16497 | G92: =IFERROR(_xlfn.LET(_xlpm.lookup_result,_xlfn.XLOOKUP($C92,'دیده بان بازار'!$A$5:$A$3994,'دیده بان بازار'!H$5:H$3994),IF(ISERROR(_xlpm.lookup_result),W92,_xlpm.lookup_result)),W92) -> 16991 | H92: =IFERROR(_xlfn.LET(_xlpm.lookup_result,_xlfn.XLOOKUP($C92,'دیده بان بازار'!$A$5:$A$3994,'دیده بان بازار'!K$5:K$3994),IF(ISERROR(_xlpm.lookup_result),X92,_xlpm.lookup_result)),X92) -> 16991 | I92: =IFERROR(_xlfn.LET(_xlpm.lookup_result,_xlfn.XLOOKUP($C92,'دیده بان بازار'!$A$5:$A$3994,'دیده بان بازار'!P$5:P$3994),IF(ISERROR(_xlpm.lookup_result),Y92,_xlpm.lookup_result)),Y92) | J92: =IFERROR(_xlfn.LET(_xlpm.lookup_result,_xlfn.XLOOKUP($C92,'دیده بان بازار'!$A$5:$A$3994,'دیده بان بازار'!Q$5:Q$3994),IF(ISERROR(_xlpm.lookup_result),Z92,_xlpm.lookup_result)),Z92) | K92: =_xlfn.XLOOKUP(C92,'MOPFRA Portfolio'!P63:P80,'MOPFRA Portfolio'!Z63:Z80,"")/1000 -> 16.991 | L92: =_xlfn.XLOOKUP(C92,'MOPFRA Portfolio'!$P$8:$P$78,'MOPFRA Portfolio'!$AT$8:$AT$78,"") -> 270000 | M92: =_xlfn.XLOOKUP(C92,'MOPFRA Portfolio'!$P$8:$P$78,'MOPFRA Portfolio'!$AU$8:$AU$78,"") -> 454719.94 | V92: 16081 | W92: 16550 | X92: 16497 | AA92: 16.55 | AB92: 270000 | AC92: 442917.72
A93: =IFERROR(MATCH(C93,'دیده بان بازار'!$A$5:$A$3994,0 )+4,"Closed") -> 2909 | B93: صندوق س. بخشي صنايع دانايان1-ب | C93: نبات | D93: F | F93: =IFERROR(_xlfn.LET(_xlpm.lookup_result,_xlfn.XLOOKUP($C93,'دیده بان بازار'!$A$5:$A$3994,'دیده بان بازار'!F$5:F$3994),IF(ISERROR(_xlpm.lookup_result),V93,_xlpm.lookup_result)),V93) -> 16363 | G93: =IFERROR(_xlfn.LET(_xlpm.lookup_result,_xlfn.XLOOKUP($C93,'دیده بان بازار'!$A$5:$A$3994,'دیده بان بازار'!H$5:H$3994),IF(ISERROR(_xlpm.lookup_result),W93,_xlpm.lookup_result)),W93) -> 16845 | H93: =IFERROR(_xlfn.LET(_xlpm.lookup_result,_xlfn.XLOOKUP($C93,'دیده بان بازار'!$A$5:$A$3994,'دیده بان بازار'!K$5:K$3994),IF(ISERROR(_xlpm.lookup_result),X93,_xlpm.lookup_result)),X93) -> 16838 | I93: =IFERROR(_xlfn.LET(_xlpm.lookup_result,_xlfn.XLOOKUP($C93,'دیده بان بازار'!$A$5:$A$3994,'دیده بان بازار'!P$5:P$3994),IF(ISERROR(_xlpm.lookup_result),Y93,_xlpm.lookup_result)),Y93) | J93: =IFERROR(_xlfn.LET(_xlpm.lookup_result,_xlfn.XLOOKUP($C93,'دیده بان بازار'!$A$5:$A$3994,'دیده بان بازار'!Q$5:Q$3994),IF(ISERROR(_xlpm.lookup_result),Z93,_xlpm.lookup_result)),Z93) | K93: =_xlfn.XLOOKUP(C93,'MOPFRA Portfolio'!P64:P81,'MOPFRA Portfolio'!Z64:Z81,"")/1000 -> 16.845 | L93: =_xlfn.XLOOKUP(C93,'MOPFRA Portfolio'!$P$8:$P$78,'MOPFRA Portfolio'!$AT$8:$AT$78,"") -> 50000 | M93: =_xlfn.XLOOKUP(C93,'MOPFRA Portfolio'!$P$8:$P$78,'MOPFRA Portfolio'!$AU$8:$AU$78,"") -> 83483.82 | V93: 15898 | W93: 16374 | X93: 16363 | AA93: 16.374 | AB93: 50000 | AC93: 81149.544
A94: =IFERROR(MATCH(C94,'دیده بان بازار'!$A$5:$A$3994,0 )+4,"Closed") -> 713 | B94: فرآورده هاي دامي ولبني دالاهو | C94: غانيزان | D94: F | F94: =IFERROR(_xlfn.LET(_xlpm.lookup_result,_xlfn.XLOOKUP($C94,'دیده بان بازار'!$A$5:$A$3994,'دیده بان بازار'!F$5:F$3994),IF(ISERROR(_xlpm.lookup_result),V94,_xlpm.lookup_result)),V94) -> 6920 | G94: =IFERROR(_xlfn.LET(_xlpm.lookup_result,_xlfn.XLOOKUP($C94,'دیده بان بازار'!$A$5:$A$3994,'دیده بان بازار'!H$5:H$3994),IF(ISERROR(_xlpm.lookup_result),W94,_xlpm.lookup_result)),W94) -> 7120 | H94: =IFERROR(_xlfn.LET(_xlpm.lookup_result,_xlfn.XLOOKUP($C94,'دیده بان بازار'!$A$5:$A$3994,'دیده بان بازار'!K$5:K$3994),IF(ISERROR(_xlpm.lookup_result),X94,_xlpm.lookup_result)),X94) -> 7120 | I94: =IFERROR(_xlfn.LET(_xlpm.lookup_result,_xlfn.XLOOKUP($C94,'دیده بان بازار'!$A$5:$A$3994,'دیده بان بازار'!P$5:P$3994),IF(ISERROR(_xlpm.lookup_result),Y94,_xlpm.lookup_result)),Y94) -> 797 | J94: =IFERROR(_xlfn.LET(_xlpm.lookup_result,_xlfn.XLOOKUP($C94,'دیده بان بازار'!$A$5:$A$3994,'دیده بان بازار'!Q$5:Q$3994),IF(ISERROR(_xlpm.lookup_result),Z94,_xlpm.lookup_result)),Z94) -> 8.93 | K94: =_xlfn.XLOOKUP(C94,'MOPFRA Portfolio'!P65:P82,'MOPFRA Portfolio'!Z65:Z82,"")/1000 -> 3.47812 | L94: =_xlfn.XLOOKUP(C94,'MOPFRA Portfolio'!$P$8:$P$78,'MOPFRA Portfolio'!$AT$8:$AT$78,"") -> 30000 | M94: =_xlfn.XLOOKUP(C94,'MOPFRA Portfolio'!$P$8:$P$78,'MOPFRA Portfolio'!$AU$8:$AU$78,"") -> 21172.032 | O94: =IF(AND(Q94<0,R94<0,Q94<R94),Q94-R94,"") | P94: =IF(AND(Q94>=0,R94>=0,Q94>R94),Q94-R94,"") | Q94: =IFERROR(((K94-AA94)*100)/ABS($K$106),"") -> 0.051972253 | R94: =IFERROR((($AB94*$G94*0.9912*0.0001)-AC94)*100/ABS($AC$108),"") -> 0.053263813 | S94: =IF(AND(R94>0,Q94>0,R94>Q94),R94-Q94,"") -> 0.0012915593 | T94: =IF(AND(R94<0,Q94<0,R94<Q94),R94-Q94,"") | V94: 6730 | W94: 6930 | X94: 6920 | Y94: 797 | Z94: 8.68 | AA94: 3.385305 | AB94: 30000 | AC94: 20607.048
A95: =IFERROR(MATCH(C95,'دیده بان بازار'!$A$5:$A$3994,0 )+4,"Closed") -> 1310 | B95: كشت وصنعت و دامپروري پگاه فارس | C95: زفارس | D95: F | F95: =IFERROR(_xlfn.LET(_xlpm.lookup_result,_xlfn.XLOOKUP($C95,'دیده بان بازار'!$A$5:$A$3994,'دیده بان بازار'!F$5:F$3994),IF(ISERROR(_xlpm.lookup_result),V95,_xlpm.lookup_result)),V95) -> 18350 | G95: =IFERROR(_xlfn.LET(_xlpm.lookup_result,_xlfn.XLOOKUP($C95,'دیده بان بازار'!$A$5:$A$3994,'دیده بان بازار'!H$5:H$3994),IF(ISERROR(_xlpm.lookup_result),W95,_xlpm.lookup_result)),W95) -> 18900 | H95: =IFERROR(_xlfn.LET(_xlpm.lookup_result,_xlfn.XLOOKUP($C95,'دیده بان بازار'!$A$5:$A$3994,'دیده بان بازار'!K$5:K$3994),IF(ISERROR(_xlpm.lookup_result),X95,_xlpm.lookup_result)),X95) -> 18840 | I95: =IFERROR(_xlfn.LET(_xlpm.lookup_result,_xlfn.XLOOKUP($C95,'دیده بان بازار'!$A$5:$A$3994,'دیده بان بازار'!P$5:P$3994),IF(ISERROR(_xlpm.lookup_result),Y95,_xlpm.lookup_result)),Y95) -> 2921 | J95: =IFERROR(_xlfn.LET(_xlpm.lookup_result,_xlfn.XLOOKUP($C95,'دیده بان بازار'!$A$5:$A$3994,'دیده بان بازار'!Q$5:Q$3994),IF(ISERROR(_xlpm.lookup_result),Z95,_xlpm.lookup_result)),Z95) -> 6.45 | K95: =_xlfn.XLOOKUP(C95,'MOPFRA Portfolio'!P66:P83,'MOPFRA Portfolio'!Z66:Z83,"")/1000 -> 2.71971 | L95: =_xlfn.XLOOKUP(C95,'MOPFRA Portfolio'!$P$8:$P$78,'MOPFRA Portfolio'!$AT$8:$AT$78,"") -> 10000 | M95: =_xlfn.XLOOKUP(C95,'MOPFRA Portfolio'!$P$8:$P$78,'MOPFRA Portfolio'!$AU$8:$AU$78,"") -> 18733.68 | O95: =IF(AND(Q95<0,R95<0,Q95<R95),Q95-R95,"") | P95: =IF(AND(Q95>=0,R95>=0,Q95>R95),Q95-R95,"") | Q95: =IFERROR(((K95-AA95)*100)/ABS($K$106),"") -> 0.04512344 | R95: =IFERROR((($AB95*$G95*0.9912*0.0001)-AC95)*100/ABS($AC$108),"") -> 0.05232936 | S95: =IF(AND(R95>0,Q95>0,R95>Q95),R95-Q95,"") -> 0.00720592 | T95: =IF(AND(R95<0,Q95<0,R95<Q95),R95-Q95,"") | V95: 17860 | W95: 18340 | X95: 18350 | Y95: 2921 | Z95: 6.28 | AA95: 2.639126 | AB95: 10000 | AC95: 18178.608
A96: =IFERROR(MATCH(C96,'دیده بان بازار'!$A$5:$A$3994,0 )+4,"Closed") -> 2892 | B96: كشاورزي‌ ودامپروي‌ مگسال‌ | C96: زمگسا | D96: F | F96: =IFERROR(_xlfn.LET(_xlpm.lookup_result,_xlfn.XLOOKUP($C96,'دیده بان بازار'!$A$5:$A$3994,'دیده بان بازار'!F$5:F$3994),IF(ISERROR(_xlpm.lookup_result),V96,_xlpm.lookup_result)),V96) -> 75140 | G96: =IFERROR(_xlfn.LET(_xlpm.lookup_result,_xlfn.XLOOKUP($C96,'دیده بان بازار'!$A$5:$A$3994,'دیده بان بازار'!H$5:H$3994),IF(ISERROR(_xlpm.lookup_result),W96,_xlpm.lookup_result)),W96) -> 77390 | H96: =IFERROR(_xlfn.LET(_xlpm.lookup_result,_xlfn.XLOOKUP($C96,'دیده بان بازار'!$A$5:$A$3994,'دیده بان بازار'!K$5:K$3994),IF(ISERROR(_xlpm.lookup_result),X96,_xlpm.lookup_result)),X96) -> 77390 | I96: =IFERROR(_xlfn.LET(_xlpm.lookup_result,_xlfn.XLOOKUP($C96,'دیده بان بازار'!$A$5:$A$3994,'دیده بان بازار'!P$5:P$3994),IF(ISERROR(_xlpm.lookup_result),Y96,_xlpm.lookup_result)),Y96) -> 12169 | J96: =IFERROR(_xlfn.LET(_xlpm.lookup_result,_xlfn.XLOOKUP($C96,'دیده بان بازار'!$A$5:$A$3994,'دیده بان بازار'!Q$5:Q$3994),IF(ISERROR(_xlpm.lookup_result),Z96,_xlpm.lookup_result)),Z96) -> 6.36 | K96: =_xlfn.XLOOKUP(C96,'MOPFRA Portfolio'!P67:P84,'MOPFRA Portfolio'!Z67:Z84,"")/1000 -> 2.3217 | L96: =_xlfn.XLOOKUP(C96,'MOPFRA Portfolio'!$P$8:$P$78,'MOPFRA Portfolio'!$AT$8:$AT$78,"") -> 5000 | M96: =_xlfn.XLOOKUP(C96,'MOPFRA Portfolio'!$P$8:$P$78,'MOPFRA Portfolio'!$AU$8:$AU$78,"") -> 38354.484 | O96: =IF(AND(Q96<0,R96<0,Q96<R96),Q96-R96,"") | P96: =IF(AND(Q96>=0,R96>=0,Q96>R96),Q96-R96,"") | Q96: =IFERROR(((K96-AA96)*100)/ABS($K$106),"") -> 0.037461011 | R96: =IFERROR((($AB96*$G96*0.9912*0.0001)-AC96)*100/ABS($AC$108),"") -> 0.10419149 | S96: =IF(AND(R96>0,Q96>0,R96>Q96),R96-Q96,"") -> 0.066730482 | T96: =IF(AND(R96<0,Q96<0,R96<Q96),R96-Q96,"") | V96: 72980 | W96: 75160 | X96: 75140 | Y96: 12169 | Z96: 6.17 | AA96: 2.2548 | AB96: 5000 | AC96: 37249.296
A97: =IFERROR(MATCH(C97,'دیده بان بازار'!$A$5:$A$3994,0 )+4,"Closed") -> 2288 | B97: توليدي كوچين | C97: كوچين | D97: F | F97: =IFERROR(_xlfn.LET(_xlpm.lookup_result,_xlfn.XLOOKUP($C97,'دیده بان بازار'!$A$5:$A$3994,'دیده بان بازار'!F$5:F$3994),IF(ISERROR(_xlpm.lookup_result),V97,_xlpm.lookup_result)),V97) -> 14810 | G97: =IFERROR(_xlfn.LET(_xlpm.lookup_result,_xlfn.XLOOKUP($C97,'دیده بان بازار'!$A$5:$A$3994,'دیده بان بازار'!H$5:H$3994),IF(ISERROR(_xlpm.lookup_result),W97,_xlpm.lookup_result)),W97) -> 14950 | H97: =IFERROR(_xlfn.LET(_xlpm.lookup_result,_xlfn.XLOOKUP($C97,'دیده بان بازار'!$A$5:$A$3994,'دیده بان بازار'!K$5:K$3994),IF(ISERROR(_xlpm.lookup_result),X97,_xlpm.lookup_result)),X97) -> 15000 | I97: =IFERROR(_xlfn.LET(_xlpm.lookup_result,_xlfn.XLOOKUP($C97,'دیده بان بازار'!$A$5:$A$3994,'دیده بان بازار'!P$5:P$3994),IF(ISERROR(_xlpm.lookup_result),Y97,_xlpm.lookup_result)),Y97) -> 2531 | J97: =IFERROR(_xlfn.LET(_xlpm.lookup_result,_xlfn.XLOOKUP($C97,'دیده بان بازار'!$A$5:$A$3994,'دیده بان بازار'!Q$5:Q$3994),IF(ISERROR(_xlpm.lookup_result),Z97,_xlpm.lookup_result)),Z97) -> 5.93 | K97: =_xlfn.XLOOKUP(C97,'MOPFRA Portfolio'!P69:P85,'MOPFRA Portfolio'!Z69:Z85,"")/1000 -> 11.76266 | L97: =_xlfn.XLOOKUP(C97,'MOPFRA Portfolio'!$P$8:$P$78,'MOPFRA Portfolio'!$AT$8:$AT$78,"") -> 10000 | M97: =_xlfn.XLOOKUP(C97,'MOPFRA Portfolio'!$P$8:$P$78,'MOPFRA Portfolio'!$AU$8:$AU$78,"") -> 14818.44 | O97: =IF(AND(Q97<0,R97<0,Q97<R97),Q97-R97,"") | P97: =IF(AND(Q97>=0,R97>=0,Q97>R97),Q97-R97,"") -> 0.048597859 | Q97: =IFERROR(((K97-AA97)*100)/ABS($K$106),"") -> 0.061680199 | R97: =IFERROR((($AB97*$G97*0.9912*0.0001)-AC97)*100/ABS($AC$108),"") -> 0.01308234 | S97: =IF(AND(R97>0,Q97>0,R97>Q97),R97-Q97,"") | T97: =IF(AND(R97<0,Q97<0,R97<Q97),R97-Q97,"") | V97: 14380 | W97: 14810 | X97: 14810 | Y97: 2531 | Z97: 5.85 | AA97: 11.652508 | AB97: 10000 | AC97: 14679.672
A98: =IFERROR(MATCH(C98,'دیده بان بازار'!$A$5:$A$3994,0 )+4,"Closed") -> 722 | B98: سيمان مجد خواف | C98: سخواف | D98: C | F98: =IFERROR(_xlfn.LET(_xlpm.lookup_result,_xlfn.XLOOKUP($C98,'دیده بان بازار'!$A$5:$A$3994,'دیده بان بازار'!F$5:F$3994),IF(ISERROR(_xlpm.lookup_result),V98,_xlpm.lookup_result)),V98) -> 5790 | G98: =IFERROR(_xlfn.LET(_xlpm.lookup_result,_xlfn.XLOOKUP($C98,'دیده بان بازار'!$A$5:$A$3994,'دیده بان بازار'!H$5:H$3994),IF(ISERROR(_xlpm.lookup_result),W98,_xlpm.lookup_result)),W98) -> 5960 | H98: =IFERROR(_xlfn.LET(_xlpm.lookup_result,_xlfn.XLOOKUP($C98,'دیده بان بازار'!$A$5:$A$3994,'دیده بان بازار'!K$5:K$3994),IF(ISERROR(_xlpm.lookup_result),X98,_xlpm.lookup_result)),X98) -> 5960 | I98: =IFERROR(_xlfn.LET(_xlpm.lookup_result,_xlfn.XLOOKUP($C98,'دیده بان بازار'!$A$5:$A$3994,'دیده بان بازار'!P$5:P$3994),IF(ISERROR(_xlpm.lookup_result),Y98,_xlpm.lookup_result)),Y98) -> -54 | J98: =IFERROR(_xlfn.LET(_xlpm.lookup_result,_xlfn.XLOOKUP($C98,'دیده بان بازار'!$A$5:$A$3994,'دیده بان بازار'!Q$5:Q$3994),IF(ISERROR(_xlpm.lookup_result),Z98,_xlpm.lookup_result)),Z98) -> -110.37 | K98: =_xlfn.XLOOKUP(C98,'MOPFRA Portfolio'!P74:P84,'MOPFRA Portfolio'!Z74:Z84,"")/1000 -> 1.70754 | L98: =_xlfn.XLOOKUP(C98,'MOPFRA Portfolio'!$P$8:$P$78,'MOPFRA Portfolio'!$AT$8:$AT$78,"") -> 0 | M98: =_xlfn.XLOOKUP(C98,'MOPFRA Portfolio'!$P$8:$P$78,'MOPFRA Portfolio'!$AU$8:$AU$78,"") -> 0 | O98: =IF(AND(Q98<0,R98<0,Q98<R98),Q98-R98,"") | P98: =IF(AND(Q98>=0,R98>=0,Q98>R98),Q98-R98,"") -> 0.027272624 | Q98: =IFERROR(((K98-AA98)*100)/ABS($K$106),"") -> 0.027272624 | R98: =IFERROR((($AB98*$G98*0.9912*0.0001)-AC98)*100/ABS($AC$108),"") -> 0 | S98: =IF(AND(R98>0,Q98>0,R98>Q98),R98-Q98,"") | T98: =IF(AND(R98<0,Q98<0,R98<Q98),R98-Q98,"") | V98: 5630 | W98: 5790 | X98: 5790 | Y98: -54 | Z98: -107.22 | AA98: 1.658835 | AB98: 0 | AC98: 0
A99: =IFERROR(MATCH(C99,'دیده بان بازار'!$A$5:$A$3994,0 )+4,"Closed") -> 2900 | B99: سبحان دارو | C99: دسبحان | D99: PH | F99: =IFERROR(_xlfn.LET(_xlpm.lookup_result,_xlfn.XLOOKUP($C99,'دیده بان بازار'!$A$5:$A$3994,'دیده بان بازار'!F$5:F$3994),IF(ISERROR(_xlpm.lookup_result),V99,_xlpm.lookup_result)),V99) -> 9230 | G99: =IFERROR(_xlfn.LET(_xlpm.lookup_result,_xlfn.XLOOKUP($C99,'دیده بان بازار'!$A$5:$A$3994,'دیده بان بازار'!H$5:H$3994),IF(ISERROR(_xlpm.lookup_result),W99,_xlpm.lookup_result)),W99) -> 9500 | H99: =IFERROR(_xlfn.LET(_xlpm.lookup_result,_xlfn.XLOOKUP($C99,'دیده بان بازار'!$A$5:$A$3994,'دیده بان بازار'!K$5:K$3994),IF(ISERROR(_xlpm.lookup_result),X99,_xlpm.lookup_result)),X99) -> 9500 | I99: =IFERROR(_xlfn.LET(_xlpm.lookup_result,_xlfn.XLOOKUP($C99,'دیده بان بازار'!$A$5:$A$3994,'دیده بان بازار'!P$5:P$3994),IF(ISERROR(_xlpm.lookup_result),Y99,_xlpm.lookup_result)),Y99) -> 1442 | J99: =IFERROR(_xlfn.LET(_xlpm.lookup_result,_xlfn.XLOOKUP($C99,'دیده بان بازار'!$A$5:$A$3994,'دیده بان بازار'!Q$5:Q$3994),IF(ISERROR(_xlpm.lookup_result),Z99,_xlpm.lookup_result)),Z99) -> 6.59 | K99: =_xlfn.XLOOKUP(C99,'MOPFRA Portfolio'!P75:P85,'MOPFRA Portfolio'!Z75:Z85,"")/1000 -> 9.5 | L99: =_xlfn.XLOOKUP(C99,'MOPFRA Portfolio'!$P$8:$P$78,'MOPFRA Portfolio'!$AT$8:$AT$78,"") -> 0 | M99: =_xlfn.XLOOKUP(C99,'MOPFRA Portfolio'!$P$8:$P$78,'MOPFRA Portfolio'!$AU$8:$AU$78,"") -> 0 | O99: =IF(AND(Q99<0,R99<0,Q99<R99),Q99-R99,"") | P99: =IF(AND(Q99>=0,R99>=0,Q99>R99),Q99-R99,"") -> 0.15118794 | Q99: =IFERROR(((K99-AA99)*100)/ABS($K$106),"") -> 0.15118794 | R99: =IFERROR((($AB99*$G99*0.9912*0.0001)-AC99)*100/ABS($AC$108),"") -> 0 | S99: =IF(AND(R99>0,Q99>0,R99>Q99),R99-Q99,"") | T99: =IF(AND(R99<0,Q99<0,R99<Q99),R99-Q99,"") | V99: 8970 | W99: 9230 | X99: 9230 | Y99: 1442 | Z99: 6.4 | AA99: 9.23 | AB99: 0 | AC99: 0
A100: =IFERROR(MATCH(C100,'دیده بان بازار'!$A$5:$A$3994,0 )+4,"Closed") -> 1388 | B100: ايران‌ خودرو | C100: خودرو | D100: A | F100: =IFERROR(_xlfn.LET(_xlpm.lookup_result,_xlfn.XLOOKUP($C100,'دیده بان بازار'!$A$5:$A$3994,'دیده بان بازار'!F$5:F$3994),IF(ISERROR(_xlpm.lookup_result),V100,_xlpm.lookup_result)),V100) -> 566 | G100: =IFERROR(_xlfn.LET(_xlpm.lookup_result,_xlfn.XLOOKUP($C100,'دیده بان بازار'!$A$5:$A$3994,'دیده بان بازار'!H$5:H$3994),IF(ISERROR(_xlpm.lookup_result),W100,_xlpm.lookup_result)),W100) -> 582 | H100: =IFERROR(_xlfn.LET(_xlpm.lookup_result,_xlfn.XLOOKUP($C100,'دیده بان بازار'!$A$5:$A$3994,'دیده بان بازار'!K$5:K$3994),IF(ISERROR(_xlpm.lookup_result),X100,_xlpm.lookup_result)),X100) -> 582 | I100: =IFERROR(_xlfn.LET(_xlpm.lookup_result,_xlfn.XLOOKUP($C100,'دیده بان بازار'!$A$5:$A$3994,'دیده بان بازار'!P$5:P$3994),IF(ISERROR(_xlpm.lookup_result),Y100,_xlpm.lookup_result)),Y100) -> -49 | J100: =IFERROR(_xlfn.LET(_xlpm.lookup_result,_xlfn.XLOOKUP($C100,'دیده بان بازار'!$A$5:$A$3994,'دیده بان بازار'!Q$5:Q$3994),IF(ISERROR(_xlpm.lookup_result),Z100,_xlpm.lookup_result)),Z100) -> -11.88 | K100: =_xlfn.XLOOKUP(C100,'MOPFRA Portfolio'!P76:P85,'MOPFRA Portfolio'!Z76:Z85,"")/1000 -> 149.21002 | L100: =_xlfn.XLOOKUP(C100,'MOPFRA Portfolio'!$P$8:$P$78,'MOPFRA Portfolio'!$AT$8:$AT$78,"") -> 1500000 | M100: =_xlfn.XLOOKUP(C100,'MOPFRA Portfolio'!$P$8:$P$78,'MOPFRA Portfolio'!$AU$8:$AU$78,"") -> 86531.76 | O100: =IF(AND(Q100<0,R100<0,Q100<R100),Q100-R100,"") | P100: =IF(AND(Q100>=0,R100>=0,Q100>R100),Q100-R100,"") -> 2.0726645 | Q100: =IFERROR(((K100-AA100)*100)/ABS($K$106),"") -> 2.2969332 | R100: =IFERROR((($AB100*$G100*0.9912*0.0001)-AC100)*100/ABS($AC$108),"") -> 0.22426868 | S100: =IF(AND(R100>0,Q100>0,R100>Q100),R100-Q100,"") | T100: =IF(AND(R100<0,Q100<0,R100<Q100),R100-Q100,"") | V100: 550 | W100: 566 | X100: 566 | Y100: -49 | Z100: -11.55 | AA100: 145.10802 | AB100: 1500000 | AC100: 84152.88
A101: =IFERROR(MATCH(C101,'دیده بان بازار'!$A$5:$A$3994,0 )+4,"Closed") -> 2703 | B101: صندوق س. آوند مفيد-د | C101: آوند | F101: =IFERROR(_xlfn.LET(_xlpm.lookup_result,_xlfn.XLOOKUP($C101,'دیده بان بازار'!$A$5:$A$3994,'دیده بان بازار'!F$5:F$3994),IF(ISERROR(_xlpm.lookup_result),V101,_xlpm.lookup_result)),V101) -> 29088 | G101: =IFERROR(_xlfn.LET(_xlpm.lookup_result,_xlfn.XLOOKUP($C101,'دیده بان بازار'!$A$5:$A$3994,'دیده بان بازار'!H$5:H$3994),IF(ISERROR(_xlpm.lookup_result),W101,_xlpm.lookup_result)),W101) -> 29128 | H101: =IFERROR(_xlfn.LET(_xlpm.lookup_result,_xlfn.XLOOKUP($C101,'دیده بان بازار'!$A$5:$A$3994,'دیده بان بازار'!K$5:K$3994),IF(ISERROR(_xlpm.lookup_result),X101,_xlpm.lookup_result)),X101) -> 29116 | I101: =IFERROR(_xlfn.LET(_xlpm.lookup_result,_xlfn.XLOOKUP($C101,'دیده بان بازار'!$A$5:$A$3994,'دیده بان بازار'!P$5:P$3994),IF(ISERROR(_xlpm.lookup_result),Y101,_xlpm.lookup_result)),Y101) | J101: =IFERROR(_xlfn.LET(_xlpm.lookup_result,_xlfn.XLOOKUP($C101,'دیده بان بازار'!$A$5:$A$3994,'دیده بان بازار'!Q$5:Q$3994),IF(ISERROR(_xlpm.lookup_result),Z101,_xlpm.lookup_result)),Z101) | K101: =_xlfn.XLOOKUP(C101,'MOPFRA Portfolio'!P77:P86,'MOPFRA Portfolio'!Z77:Z86,"")/1000 -> 0 | L101: =_xlfn.XLOOKUP(C101,'MOPFRA Portfolio'!$P$8:$P$78,'MOPFRA Portfolio'!$AT$8:$AT$78,"") -> 0 | M101: =_xlfn.XLOOKUP(C101,'MOPFRA Portfolio'!$P$8:$P$78,'MOPFRA Portfolio'!$AU$8:$AU$78,"") -> 0 | V101: 29020 | W101: 29114 | X101: 29088 | AA101: 0 | AB101: 0 | AC101: 0
M102: ='Cement Portfolio'!AQ48 -> 361976 | O102: =COUNTIF(O1:O100, "<0") -> 0 | P102: =COUNTIF(P1:P100, ">0") -> 46 | Q102: =SUM(Q6:Q100)/100 -> 1.0198112 | R102: =SUM(R6:R100)/100 -> 1.0202431 | S102: =COUNTIF(S1:S100, ">0") -> 32 | T102: =COUNTIF(T1:T100, "<0") -> 0 | AC102: 361976 | AD102: آخرین موحودی نقدی
K103: HMT | M103: IHT | O103: =SUM(O7:O100) -> 0 | P103: =SUM(P7:P100) -> 82.727646 | S103: =SUM(S7:S100) -> 79.377647 | T103: =SUM(T7:T100) -> 0 | AA103: HMT | AC103: IHT
J104: =AVERAGEIF(J6:J100, ">0") -> 6.5853409 | K104: =SUM(K6:K100) -> 7688.2232 | L104: ='Cement Portfolio'!AP3 -> 35349022 | M104: =SUM(M6:M100) -> 46012942 | O104: =O103+P103 -> 82.727646 | S104: =S103+T103 -> 79.377647 | Z104: =AVERAGEIF(Z6:Z100, ">0") -> 6.4186364 | AA104: =SUM(AA6:AA100) -> 7509.6375 | AB104: 43650067 | AC104: =SUM(AC6:AC100) -> 44916553
L105: Today In/Out | M105: 0
K106: =(K104-AA104) -> 178.58568 | M106: =(M104+M102)-M105-(AC104+AC102) -> 1096389.1 | O106: تغییر ارزش پرتفوی امروز | AC106: =(SUMPRODUCT(AB6:AB100,G6:G100)*0.9912)/10000 -> 45977280
K107: =(K104-AA104)/AA104 -> 0.023780865 | M107: =(M104-AC104)/AC104 -> 0.024409466
C108: =COUNTA(C6:C100) -> 94 | F108: تعداد شرکتها | K108: Billion $ | M108: =COUNTIF(M6:M100, "<>0") -> 57 | O108: تعداد شرکتها در پرتفوی AA | Q108: =Cement!U2 -> 1405/05/14 | S108: =Cement!W2 -> 13:37:15 | AA108: Billion $ | AC108: =AC106-AC104 -> 1060727.7
K109: =(K104/Cement!$Q$38)*10^3 -> 40.67843 | AA109: =(AA104/Cement!$Q$38)*10^3 -> 39.733532
K110: =K109-AA109 -> 0.94489776 | M110: =AC108 -> 1060727.7
M114: =M104 -> 46012942
M115: =M102 -> 361976
M116: ='Cement Portfolio'!AV48 -> -1270761.4

Sheet Cement
Q1: 1 | R1: 2 | S1: 3 | T1: 4 | U1: 5 | V1: 6 | W1: 7 | Y1: 8 | Z1: 9 | AA1: 10 | AB1: 11 | AC1: 12 | AD1: 13 | AE1: 14 | AF1: 15 | AG1: 16 | AH1: 17 | AI1: 18 | AJ1: 19 | AK1: 20 | AL1: 21 | AM1: 22 | AN1: 23 | AO1: 24 | AP1: 25 | AQ1: 26 | AR1: 27 | AS1: 28 | AT1: 29 | AU1: 30 | AV1: 31 | AW1: 32 | AX1: 33 | AY1: 34 | AZ1: 35 | BA1: 36 | BB1: 37 | BC1: 38 | BD1: 39 | BE1: 40 | BF1: 41 | BG1: 42 | BI1: 43 | BJ1: 44 | BK1: 45 | BL1: 46 | BM1: 47 | BN1: 48 | BO1: 49 | BP1: 50 | BQ1: 51 | BR1: 52 | BS1: 53 | BT1: 54 | BU1: 55 | BV1: 56 | BW1: 57 | BX1: 58 | BY1: 59 | BZ1: 60 | CB1: 61 | CC1: 62 | CD1: 63 | CE1: 64 | CF1: 65 | CG1: 66 | CH1: 67 | CI1: 68 | CJ1: 69 | CK1: 70 | CL1: 71 | CM1: 72 | CN1: 73 | CO1: 74 | CP1: 75 | CQ1: 76 | CR1: 77 | CS1: 78 | CT1: 79 | CU1: 80 | CV1: 81 | CW1: 82 | CX1: 83 | CY1: 84 | CZ1: 85 | DA1: 86 | DB1: 87 | DC1: 88 | DD1: 89 | DE1: 90 | DF1: 91 | DG1: 92 | DH1: 93 | DI1: 94 | DJ1: 95 | DK1: 96 | DL1: 97 | DM1: 98 | DN1: 99 | DO1: 100 | DP1: 101 | DQ1: 102 | DR1: 103 | DS1: 104 | DT1: 105 | DU1: 106 | DV1: 107 | DW1: 108 | DX1: 109 | DY1: 110 | DZ1: 111 | EA1: 112 | EB1: 113 | EC1: 114 | ED1: 115 | EE1: 116 | EF1: 117 | EG1: 118 | EH1: 119 | EI1: 120 | EJ1: 121 | EK1: 122 | EL1: 123 | EM1: 124 | EN1: 125 | EO1: 126 | EP1: 127 | EQ1: 128 | ER1: 129 | ES1: 130 | ET1: 131 | EU1: 132 | EV1: 133 | EW1: 134 | EX1: 135 | EY1: 136 | EZ1: 137
A2: =Q38 -> 189000 | C2: =SUMPRODUCT(C7:C35,S7:S35)/S2 -> 0.16696479 | S2: =SUM(S7:S35) -> 329404.24 | T2: =(S2/AK2)*1000000 -> 6607.2458 | U2: =MID('دیده بان بازار'!A3,18,10) -> 1405/05/14 | V2: =(S2/AM2)*10000 -> 23365.112 | W2: =MID('دیده بان بازار'!A3,50,9) -> 13:37:15 | Z2: =IFERROR((S2-EX2)/EX2,"") -> 0.24133915 | AA2: 0.9 | AG2: =(S2-EN2)/EN2 -> 4.9663732 | AK2: =SUM(AK7:AK35) -> 49855000 | AL2: =SUM(AL7:AL35) -> 51895000 | AM2: =SUM(AM7:AM35)/1000000 -> 140981.24 | AN2: 45063 | AO2: =SUM(AO7:AO35) -> 101748 | AP2: =SUM(AP7:AP35) -> 89772 | AQ2: =SUM(AQ7:AQ35) -> 44685 | AR2: =SUM(AR7:AR35) -> 129053.14 | AT2: =AVERAGE(AT7:AT35) -> 2.4263227 | AV2: =SUM(AV7:AV35) -> 43276 | AW2: =SUM(AW7:AW35) -> 21203 | AX2: =AW2/AV2 -> 0.48994824 | AY2: =AQ2/AP2 -> 0.49776099 | BA2: =SUM(BA7:BA35)/COUNT(BA7:BA35) -> 0.39641379 | BC2: =AVERAGE(BC7:BC35) -> 0.4102069 | BG2: =(SUM(BG7:BG35)-MAX(BG7:BG35)-MIN(BG7:BG35))/(COUNT(BG7:BG35)-2)*100 -> 8.337037 | BI2: =AVERAGE(BI7:BI35) -> 0.074862069 | BT2: =SUMPRODUCT(BT7:BT35,AM7:AM35)/AM2 -> 4.4915906e+09 | BV2: =V2/BT2 -> 5.2019683e-06 | BW2: =IFERROR(($Q$45-BV2)*$R$45,"") -> 24.999974 | BX2: =SUM(BX7:BX35) -> 62095.02 | BY2: =SUM(BY7:BY35) -> 52089.004 | CB2: =SUMPRODUCT(CB7:CB35,CJ7:CJ35)/1000 -> 52441.138 | CC2: =S2/CB2 -> 6.281409 | CE2: 1 | CG2: =AVERAGE(CG7:CG35) -> 0.45491102 | CJ2: =SUM(CJ7:CJ35) -> 14098.124 | CK2: =SUM(CK7:CK35) -> 11035 | CL2: =SUM(CL7:CL35) -> 8298 | CN2: =SUM(CN7:CN35) -> 21158 | CO2: =SUM(CO7:CO35) -> 3167 | CP2: =SUM(CP7:CP35) -> 21630.25 | CR2: =SUM(CR7:CR35) -> 33617 | CS2: =SUM(CS7:CS35) -> -3257 | CU2: =SUM(CU7:CU35) -> 48506 | CV2: =SUM(CV7:CV35) -> 74342 | CW2: =SUM(CW7:CW35) -> 10362 | CX2: =SUM(CX7:CX35) -> 4038 | CY2: =SUM(CY7:CY35) -> 78380 | CZ2: =AVERAGE(CZ7:CZ35) -> 1.3626248 | DB2: =SUM(DB7:DB35) -> 126886 | DC2: =CY2/DB2 -> 0.61771984 | DD2: =SUM(DD7:DD35) -> 37102 | DE2: =SUM(DE7:DE35) -> 30510 | DF2: =SUM(DF7:DF35) -> 4085 | DG2: =SUM(DG7:DG35) -> 89784 | DH2: =SUM(DH7:DH35) -> 15442 | DI2: =AR2/DH2 -> 8.3572815 | DJ2: =SUM(DJ7:DJ35) -> 36171 | DK2: =SUM(DK7:DK35) -> 12278 | DL2: =SUM(DL7:DL35) -> 13628 | DM2: =AVERAGE(DM7:DM35) -> 0.60012981 | DQ2: =SUM(DQ7:DQ35) -> 20516 | DR2: =SUM(DR7:DR35) -> 7191 | DS2: G | DT2: =IFERROR(((S2/AK2)/$Q$38*1000000000),"") -> 34.958972 | DU2: =SUM(DU7:DU35) -> 460451.01 | DV2: =DU2/S2 -> 1.3978297 | DW2: =(DV2-$Q$53)*$R$53 -> 7.9565932 | DX2: =(AR2/AK2)*1000000 -> 2588.5697 | DZ2: =AVERAGE(DZ7:DZ35) -> 0.49057107 | EB2: =AVERAGE(EB7:EB35) -> 0.18093352 | EN2: =SUM(EN7:EN35) -> 55210.13 | EP2: =SUM(EP7:EP35) -> 100706 | ER2: =SUM(ER7:ER35) -> 112451 | ET2: =SUM(ET7:ET35) -> 207835 | EX2: =SUM(EX7:EX35) -> 265362 | EY2: =(EX2-EN2)/EN2 -> 3.8064006
A3: Point | B3: Point | C3: ٪ | E3: % | F3: % | G3: % | L3: Rank | O3: Control | R3: Month | S3: IBT | T3: Rial | U3: ٪ | V3: Rial | W3: ٪ | Z3: ٪ | AA3: ٪ | AB3: ٪ | AG3: % | AJ3: Date | AK3: Ton | AM3: Unit | AN3: % | AO3: Ton | AP3: B.Toman | AR3: B.Toman | AS3: Month | AU3: Point-1 | AV3: B.Toman | AW3: B.Toman | AX3: % | AY3: % | BA3: % | BB3: Point-2 | BC3: % | BD3: % | BF3: % | BG3: % | BH3: B.Toman | BJ3: Point-3 | BL3: Point-4 | BN3: Month | BP3: Rial | BQ3: Rial | BR3: Rial | BT3: Rial | BV3: Ratio | BW3: Point-5 | BX3: B.Toman | BY3: B. Toman | CB3: IBT | CC3: Ratio | CD3: Point-6 | CE3: Ratio | CF3: Point-7 | CG3: Ratio | CH3: Point-8 | CJ3: B.Toman | CN3: B.Toman | CO3: B.Toman | CP3: B.Toman | CR3: B.Toman | CS3: B.Toman | CT3: Ratio | CU3: B.Toman | CV3: B.Toman | CW3: B.Toman | CX3: B.Toman | CY3: B.Toman | CZ3: Ratio | DA3: Point-9 | DB3: B.Toman | DC3: % | DD3: B.Toman | DE3: B.Toman | DF3: B.Toman | DG3: B.Toman | DH3: B.Toman | DJ3: B.Toman | DK3: B.Toman | DL3: B.Toman | DM3: Ratio | DN3: Point-10 | DO3: Ratio | DP3: Point-11 | DQ3: B.Toman | DR3: B.Toman | DS3: G/W | DT3: USD | DU3: B.Toman | DV3: Ratio | DW3: Point-12 | DX3: H.Toman | DY3: Point-13 | DZ3: Ratio | EA3: Point-14 | EB3: Ratio | EC3: Point-15 | ED3: Rial | EE3: Rial | EG3: =Q40 -> 0.25 | EH3: Days | EI3: Rial | EW3: Rls | EX3: IBT | EY3: %
A4: جمع امتیاز بنیادی و تخصصی سیمان | B4: جمع امتیاز بنیادی | C4: بازدهی بر اساس تاریخ مجمع و پرداخت سود | D4: تغییر انتظاری P/E | E4: درصد رشد سود ناخالص عملیاتی | F4: درصد رشد سود خالص عملیاتی نسبت به دورره مشابه | G4: تغییر رشد تجمیعی دوره نسبت به ماه قبل | H4: رشد فروش تجمیعی نسبت به سال قبل Update | I4: رشد فروش در فصل بهار به زمستان | J4: رشد فروش سه ماهه اخیر | K4: رتبه رشد فروش سال در حال تداوم | L4: رتبه در جمع رتبه ها | M4: سیگنال بر اساس روند رشد فروش شرکت اصلی | N4: سیگنال رشد ارزش انتظاری شرکت | O4: توجه به تغییر در EPS و P/E | P4: نام شرکت | Q4: نماد | R4: ماه پایان سال مالی | S4: ارزش شرکت در بورس | T4: قیمت پایانی | U4: تغییر قیمت پایانی در روز | V4: آخرین قیمت معامله شده | W4: تغییر آخرین قیمت درروز | X4: EV ارزش بنگاه | Y4: TAL Signal | Z4: رشد نسبت به آخرین مجمع | AA4: میزان رشد تورمی انتظاری پس از آخرین مجمع | AB4: تفاوت درصد متوسط روزانه بعد از مجمع به رشد تورمی انتظاری | AC4: رشد نسبت به مجمع 1404 | AD4: رشد نسبت به مجمع 1403 | AE4: رشد نسبت به مجمع 1402 | AF4: رشد نسبت به مجمع 1401 | AG4: رشد نسبت به مجمع 1400 | AH4: تعداد روز مانده به مجمع عادی سالیانه | AI4: تاریخ آخرین مجمع | AJ4: تاریخ آخرین پرداخت سود | AK4: ظرفیت تولید کلینکر | AL4: ظرفیت تولید سیمان | AM4: تعداد کل سهام شرکت | AN4: میزان سهام شناور در بورس | AO4: فروش یکسال اخیر شرکت بر اساس گزارش کدال | AP4: درآمد (فروش) عملیاتی شرکت اصلی در سال مالی قبل | AQ4: سود (زیان) عملیاتی آخرین سال مالی | AR4: تخمین فروش سال مالی جدید بر اساس آخرین گزارش | AS4: آخرین ماه گزارش فروش منتشره | AT4: P/S Future | AU4: امتیاز P/S فوروارد | AV4: درآمد (فروش) عملیاتی در حال تداوم | AW4: سود (زیان) عملیاتی | AX4: نسبت سود ناخالص عملیاتی به فروش - آخرین گزارش سال مالی | AY4: نسبت سود ناخالص عملیاتی به فروش - دوره مشابه سال قبل | AZ4: نسبت سود ناخالص عملیاتی به فروش - سال مالی 1404 | BA4: نسبت سود ناخالص عملیاتی به فروش - سال مالی 1403 | BB4: امتیاز رشد حاشیه سود خالص | BC4: نسبت سود خالص عملیاتی به فروش - آخرین گزارش سال مالی | BD4: نسبت سود خالص عملیاتی به فروش - دوره مشابه سال قبل | BE4: نسبت سود خالص عملیاتی به فروش - سال مالی 1404 | BF4: نسبت سود خالص عملیاتی به فروش - سال مالی 1403 | BG4: نسبت هزینه های ITDA به فروش دوره در حال تداوم | BH4: میزان هزینه ITDA در کل سال مالی جاری | BI4: نسبت هزینه های ITDA به فروش در دوره مشابه سال قبل | BJ4: امتیاز نسبت هزینه های ITDA به فروش | BK4: پیش بینی رشد فروش دوره مالی در حال تداوم | BL4: امتیاز مقایسه پیش بینی رشد فروش به رشد قیمت | BN4: آخرین ماه گزارش صورت مالی منتشره | BO4: فصل مالی گزارش شده | BP4: سود به هر سهم در ۳ ماه اول سال مالی | BQ4: سود به هر سهم در ۶ ماه اول سال مالی | BR4: سود به هر سهم در ۹ ماه اول سال مالی | BS4: پیش بینی سود هر سهم بر اساس گزارش فروش ماهیانه | BT4: پیش بینی سود هر سهم بر اساس صورت ها‌ی مالی | BV4: P/E - fw | BW4: امتیاز P/E فوروارد | BX4: پیش بینی سود خالص شرکت | BY4: سود چهار فصل اخیر شرکت | BZ4: پیش بینی EBIT سال مالی در جریان | CA4: EV/EBIT | CB4: EPS-TTM | CC4: P/E-TTM | CD4: امتیاز P/E TTM | CE4: نسبت بدهی به تخمین سود سالیانه | CF4: امتیاز L/E | CG4: شاخص بازده سرمایه به کار گرفته شده | CH4: امتیاز ROCE | CJ4: سرمایه ثبتی شرکت | CK4: سود توزیع نشده از مجمع قبل | CL4: سود غیر عملیاتی سال مالی قبل | CM4: سود غیر عملیاتی آخرین گزارش | CN4: سود خالص عملیات درحال تداوم | CO4: تفاوت سود سهم مالکانه گزارش تلفیقی | CP4: جمع سود در حال تداوم تخمینی | CQ4: سود در حال تداوم بر اساس فروش ماهانه و حاشیه سود خالص | CR4: سود (زیان) انباشته | CS4: سهام خزانه و کسری یا اضافی های دیگر | CT4: کنترل اطلاعات بدهی و دارایی | CU4: جمع حقوق مالکانه محاسبه شده | CV4: جمع بدهی جاری | CW4: تسهیلات مالی | CX4: جمع بدهی غیر جاری | CY4: جمع کل بدهی ها | CZ4: نسبت جاری (دارایی جاری به بدهی جاری) | DA4: امتیاز نسبت جاری CA/CL | DB4: جمع کل دارائی ها | DC4: نسبت بدهی به دارایی | DD4: جمع دارائی غیر جاری | DE4: دارئی مشهود | DF4: سرمایه گذاری های بلند مدت | DG4: جمع دارائی جاری | DH4: خالص دارایی جاری | DI4: نسبت فروش به خالص دارایی جاری | DJ4: موجودی مواد و کالا | DK4: موجودی نقدی | DL4: دریافتنی های تجاری | DM4: نسبت کل بدهی‌ها به کل دارایی‌ها | DN4: امتیاز L/A | DO4: نسبت خالص بدهی تسهیلات به درآمد پیش بینی شده | DP4: امتیاز خالص بدهی تسهیلات به درآمد پیش بینی شده | DQ4: سرمایه گذاری‌های کوتاه مدت | DR4: پیش پرداختها و سایر | DS4: سیمان سفید یا خاکستری | DT4: ارزش دلاری هر تن ظرفیت تولیدی شرکت | DU4: هزینه ساخت جدید همان ظرفیت تولیدی | DV4: نسبت هزینه احداث جدید به ارزش شرکت در بورس | DW4: امتیاز RC/P | DX4: متوسط فروش سالیانه به هر تن ظرفیت | DY4: امتیاز S-fw / PC | DZ4: شاخص حاشیه سود | EA4: امتیاز شاخص P/S/ به P/E | EB4: نسبت فروش صادراتی به کل | EC4: امتیاز Ex-S / S | ED4: قیمت انتظاری TTM | EE4: قیمت انتظاری CUR | EF4: سهم از سود انباشته | EG4: قیمت سهام بر اساس انتظار سود | EH4: فاصله مجمع و پرداخت سود | EI4: آخرین سود تقسیمی برای هر سهم | EJ4: آخرین درصد سود نسبت به قیمت پایانی قبل از مجمع | EK4: آخرین افزایش سرمایه ثبت شده | EL4: افزایش سرمایه در جریان | EM4: قیمت سهام پس از مجمع سال مالی 1400 | EN4: ارزش شرکت بعد از مجمع سال مالی 1400 | EO4: قیمت سهام پس از مجمع سال مالی 1401 | EP4: ارزش شرکت بعد از مجمع سال مالی 1401 | EQ4: قیمت سهام پس از مجمع سال مالی 1402 | ER4: ارزش شرکت بعد از مجمع سال مالی 1402 | ES4: قیمت سهام پس از مجمع سال مالی 1403 | ET4: ارزش شرکت بعد از مجمع سال مالی 1403 | EU4: قیمت سهام پس از مجمع سال مالی 1404 | EV4: قیمت سهام پس از مجمع سال مالی 1404 | EW4: قیمت سهام پس از آخرین مجمع | EX4: ارزش شرکت بعد از آخرین مجمع | EY4: درصد رشد مجمع به مجمع سال مالی 1400 | EZ4: رتبه شرکت در رشد نسبت به ارزش پس از مجمع ۱۴۰۰
O5: =COUNTIF(O7:O60,">0")+COUNTIF(O7:O60,"<0") -> 0 | W5: % | AS5: =R5 -> 0 | BN5: =R5 -> 0 | CC5: 6.56
A7: =_xlfn.XLOOKUP(Q7,'Cement Ranking'!$F$7:$F$35,'Cement Ranking'!$AO$7:$AO$35, "") -> 44.669651 | B7: =_xlfn.XLOOKUP(Q7,'Cement Ranking'!$F$7:$F$35,'Cement Ranking'!$AN$7:$AN$35, "") -> 40.755421 | C7: =((((CK7*10000000000)/AM7)+CB7*0.8)/V7)/((AH7+EH7)/365) -> 0.16218429 | D7: =(CC7-BV7) -> 1.397574 | E7: =IF(OR(AX7=AY7, AX7=""), (AY7-BA7), (AX7-AY7))*100 -> 37 | F7: =IF(OR(BC7=BD7, BC7=""), (BD7-BF7), (BC7-BD7))*100 -> 37.8 | G7: {=IFERROR(_xlfn.XLOOKUP(Q7,'Sales Rec'!$E$4:$E$32,'Sales Rec'!$CU$4:$CU$32*100,""),"")} -> -10.188627 | H7: =_xlfn.XLOOKUP(Q7,'Sales Rec'!$E$4:$E$32,'Sales Rec'!$DQ$4:$DQ$32,"") -> 1.0290038 | I7: =_xlfn.XLOOKUP(Q7,'Sales History'!$C$4:$C$83,'Sales History'!$AS$4:$AS$83,"") -> 0.58571429 | J7: =_xlfn.XLOOKUP(Q7,'Sales History'!$C$4:$C$83,'Sales History'!$AW$4:$AW$83,"") -> 0.2348643 | K7: =_xlfn.XLOOKUP(Q7,'Sales Rec'!$E$4:$E$91,'Sales Rec'!$CV$4:$CV$91,"") -> 3 | L7: =_xlfn.XLOOKUP(Q7,'Cement Ranking'!$F$7:$F$35,'Cement Ranking'!$AQ$7:$AQ$35,"") -> 1 | M7: =_xlfn.XLOOKUP(Q7,'Sales Rec'!$E$4:$E$32,'Sales Rec'!$DS$4:$DS$32,"") -> BB | N7: =_xlfn.XLOOKUP(Q7,'Sales Rec'!$E$4:$E$32,'Sales Rec'!$DZ$4:$DZ$32,"") -> BB | O7: =_xlfn.XLOOKUP($Q7,'History Records'!$B$7:$B$88,'History Records'!$G$7:$G$88,"") | P7: سيمان باقران | Q7: سباقر | R7: 12 | S7: =(V7*AM7)/10000000000 -> 14568 | T7: =_xlfn.XLOOKUP($Q7,'Price Record'!$C$6:$C$85,'Price Record'!H$6:H$85,"") -> 242800 | U7: =_xlfn.XLOOKUP(Q7,'دیده بان بازار'!$A$3:$A$3542,'دیده بان بازار'!$M$3:$M$3542,"") -> 2.97 | V7: =_xlfn.XLOOKUP($Q7,'Price Record'!$C$6:$C$85,'Price Record'!G$6:G$85,"") -> 242800 | W7: =_xlfn.XLOOKUP(Q7,'دیده بان بازار'!$A$3:$A$3542,'دیده بان بازار'!$J$3:$J$3542,"") -> 2.97 | X7: =S7+CY7-DK7-DQ7 -> 16739 | Y7: =IFERROR(IF(U7-W7<-1.5,"B",IF(U7-W7>1.5,"S","")),"") | Z7: =IFERROR((S7-EX7)/EX7,"") -> 0.19194894 | AA7: =((365-AH7)/365)*$AA$2 -> 0.034520548 | AB7: =IFERROR(((AA7-Z7)*10000)/(365-AH7),"") -> -112.44885 | AC7: =IFERROR(($S7-EV7)/EV7,"") -> 0.19194894 | AD7: =IFERROR((S7-ET7)/ET7,"") -> 3.7842365 | AE7: =(S7-ER7)/ER7 -> 11.231738 | AF7: =(S7-EP7)/EP7 -> 12.255687 | AG7: =(S7-EN7)/EN7 -> 19.066116 | AH7: =IF((AI7-TODAY())>0,AI7-TODAY(),(365-(TODAY()-AI7))) -> 351 | AI7: 46225 | AJ7: 46346 | AK7: 1000000 | AL7: 1030000 | AM7: =CJ7*10000000 -> 600000000 | AN7: ? | AO7: =_xlfn.XLOOKUP(Q7,'Cem Sales'!$K$5:$K$33,'Cem Sales'!$DU$5:$DU$33,"") -> 3456 | AP7: 2832 | AQ7: 1997 | AR7: =_xlfn.XLOOKUP(Q7,'Sales Rec'!$E$4:$E$86,'Sales Rec'!$X$4:$X$86,"") -> 4991.8194 | AS7: =_xlfn.XLOOKUP(Q7,'Sales Rec'!$E$4:$E$86,'Sales Rec'!$K$4:$K$86,"") -> 4 | AT7: =(S7-(CO7*CC7))/AR7 -> 2.8921239 | AU7: =MIN(MAX(IF(($Q$42-AT7)*$R$42<-20,-20,IF(($Q$42-AT7)*$R$42>20,20,($Q$42-AT7)*$R$42)), -10), 10) -> -4.6580122 | AV7: 1221 | AW7: 887 | AX7: =ROUND(AW7/AV7,3) -> 0.726 | AY7: 0.356 | AZ7: 0.705 | BA7: 0.238 | BB7: =IF(BC7=0,0,MIN(MAX(IF(BC7=BD7,BC7-BF7,BC7-BD7)*$R$43, -10), 10)) -> 10 | BC7: =IF(CN7=0,BE7,ROUND((CN7-CM7)/AV7,3)) -> 0.725 | BD7: 0.347 | BE7: 0.699 | BF7: 0.214 | BG7: =AX7-BC7 -> 0.001 | BH7: =BG7*AV7*(4/BO7) -> 4.884 | BI7: =AY7-BD7 -> 0.009 | BJ7: 0 | BK7: =_xlfn.XLOOKUP(Q7,'Sales Rec'!$E$4:$E$91,'Sales Rec'!$Y$4:$Y$91,"") -> 0.76264808 | BL7: =IF(BK7=0,0,MIN(MAX((BK7-Z7)*$R$44,-5),5)) -> 5 | BN7: 3 | BO7: =IF((BN7-R7+12)/3>4,(BN7-R7+12)/3-4, (BN7-R7+12)/3) -> 1 | BP7: 14803 | BS7: =(_xlfn.XLOOKUP(Q7,'Sales Rec'!$E$4:$E$32,'Sales Rec'!$X$4:$X$32)*BC7+CL7)*1000/CJ7 -> 60334.484 | BT7: =IF((CN7/CJ7)*1000*(12/(12-(R7-BN7)))=0,CB7,IF(R7-BN7>=0,((CP7/CJ7)*1000*(12/(12-(R7-BN7)))),((CP7/CJ7)*1000*(12/(BN7-R7))))) -> 59200 | BV7: =IF(CN7=0,V7/BT7,(V7*2)/(BS7+BT7)) -> 4.062426 | BW7: =MIN(MAX(IF(BV7<0,-20, IF(BV7>50, -20,($Q$45-BV7)*$R$45)), -20), 20) -> 4.6878698 | BX7: =IFERROR(S7/BV7,"") -> 3586.0345 | BY7: =S7/CC7 -> 2668.1319 | BZ7: =AR7*AX7 -> 3624.0609 | CA7: =X7/BZ7 -> 4.6188518 | CB7: =_xlfn.XLOOKUP($Q7,'Price Record'!$C$6:$C$85,'Price Record'!I$6:I$85,"") -> 44486 | CC7: =_xlfn.XLOOKUP($Q7,'Price Record'!$C$6:$C$85,'Price Record'!J$6:J$85,"") -> 5.46 | CD7: =MIN(MAX(IF(CC7<0,-20, IF(CC7>50, -20,($Q$46-CC7)*$R$46)), -20), 20) -> -1.38 | CE7: =CY7/BX7 -> 0.67874416 | CF7: =MIN(MAX(($Q$47-CE7)*$R$47, -10), 10) -> 5.2850233 | CG7: =BX7/(CU7+DG7) -> 0.68162602 | CH7: =MIN(MAX((CG7-$Q$48)*$R$48, -10), 10) -> 4.2243904 | CJ7: 60 | CK7: 920 | CL7: 1 | CM7: 3 | CN7: 888 | CO7: 24 | CP7: =IF(AND(CM7>0, CL7>(CM7/(BO7/4))), CN7+CL7*BO7/4-CM7, CN7) -> 888 | CQ7: =(AR7*BC7)*(_xlfn.XLOOKUP($Q7,'Sales Rec'!$E$4:$E$32,'Sales Rec'!$L$4:$L$32,"")/12)+CO7 -> 1230.3563 | CR7: 1808 | CS7: 0 | CT7: =_xlfn.TEXTJOIN(", ",TRUE, IF(CU7/(CJ7*1.1+CR7+CS7)<=0.975,"Check EQ",""), IF(CR7<>(CN7+CK7),"Check RE","") ) | CU7: =DB7-CY7 -> 1873 | CV7: 2360 | CW7: 55 | CX7: 74 | CY7: =CV7+CX7 -> 2434 | CZ7: =DG7/CV7 -> 1.4355932 | DA7: =MIN(MAX((CZ7-$Q$50)*$R$50, -6), 6) -> 1.8847458 | DB7: =DD7+DG7 -> 4307 | DC7: =(CY7/DB7) -> 0.56512654 | DD7: 919 | DE7: 907 | DF7: 6 | DG7: 3388 | DH7: =DG7-CV7 -> 1028 | DI7: =AR7/DH7 -> 4.8558554 | DJ7: 1430 | DK7: 263 | DL7: 1266 | DM7: =CY7/DB7 -> 0.56512654 | DN7: =MIN(MAX(($Q$51-DM7)*$R$51, -6), 6) -> 0.35003274 | DO7: =(DQ7-CW7)/BZ7 -> -0.015176346 | DP7: =MIN(MAX(ROUNDDOWN(DO7*5,0),-10),5) -> 0 | DQ7: 0 | DR7: =DG7-DJ7-DK7-DQ7-DL7 -> 429 | DS7: G | DT7: =IFERROR(((S7/AK7)/$Q$38*1000000000),"") -> 77.079365 | DU7: =IF(DS7="G",(500000*$Q$57+(AK7-500000)*$R$57*$Q$57)*$Q$38/1000000000, (150000*$Q$58+(AK7-150000)*$R$58*$Q$58)*$Q$38/1000000000) -> 10135.125 | DV7: =DU7/S7 -> 0.69571149 | DW7: =MIN(MAX((DV7-$Q$53)*$R$53, -10), 10) -> -6.0857702 | DX7: =IFERROR((AR7/AK7)*1000000,"") -> 4991.8194 | DY7: =MIN(MAX(((DX7-$Q$54)/$Q$54)*$R$54, -10), 10) -> 10 | DZ7: =(S7/AR7)/BV7 -> 0.71838227 | EA7: =MIN(MAX((DZ7-$Q$55)*$R$55,-10), 10) -> 6.834336 | EB7: =_xlfn.XLOOKUP(Q7,'Cem Sales'!$K$5:$K$33,'Cem Sales'!$DN$5:$DN$33, 0) -> 0.85270354 | EC7: =MIN(MAX(EB7*$R$56, 0), 10) -> 8.5270354 | ED7: =($CB7/$Q$40)*(IF(($R7+2-$Q$39)<0,(88-$R7-2+$Q$39),(100-($R7+2-$Q$39))))/100 -> 161929.04 | EE7: =($BT7/$Q$40)*(IF(($R7+2-$Q$39)<0,(88-$R7-2+$Q$39),(100-($R7+3-$Q$39))))/100 -> 213120 | EF7: =((CR7-CN7)*10000000000)/AM7 -> 15333.333 | EG7: =(ED7+EE7+EF7)/2 -> 195191.19 | EH7: =IFERROR((AJ7-AI7),230) -> 121 | EI7: 22000 | EJ7: =EI7/(EI7+EW7) -> 0.097474524 | EM7: 12100 | EN7: 726 | EO7: 18320 | EP7: 1099 | EQ7: 19850 | ER7: 1191 | ES7: 50750 | ET7: 3045 | EU7: 203700 | EV7: 12222 | EW7: 203700 | EX7: 12222 | EY7: =IFERROR((EX7-EN7)/EN7,"") -> 15.834711 | EZ7: =RANK(EY7,$EY$7:$EY$35) -> 1
A8: =_xlfn.XLOOKUP(Q8,'Cement Ranking'!$F$7:$F$35,'Cement Ranking'!$AO$7:$AO$35, "") -> 36.791772 | B8: =_xlfn.XLOOKUP(Q8,'Cement Ranking'!$F$7:$F$35,'Cement Ranking'!$AN$7:$AN$35, "") -> 21.524547 | C8: =((((CK8*10000000000)/AM8)+CB8*0.8)/V8)/((AH8+EH8)/365) -> 0.15813583 | D8: =(CC8-BV8) -> 2.0693389 | E8: =IF(OR(AX8=AY8, AX8=""), (AY8-BA8), (AX8-AY8))*100 -> 6 | F8: =IF(OR(BC8=BD8, BC8=""), (BD8-BF8), (BC8-BD8))*100 -> 5.1 | G8: {=IFERROR(_xlfn.XLOOKUP(Q8,'Sales Rec'!$E$4:$E$32,'Sales Rec'!$CU$4:$CU$32*100,""),"")} -> 5.4065093 | H8: =_xlfn.XLOOKUP(Q8,'Sales Rec'!$E$4:$E$32,'Sales Rec'!$DQ$4:$DQ$32,"") -> 0.9046875 | I8: =_xlfn.XLOOKUP(Q8,'Sales History'!$C$4:$C$83,'Sales History'!$AS$4:$AS$83,"") -> 0.19092123 | J8: =_xlfn.XLOOKUP(Q8,'Sales History'!$C$4:$C$83,'Sales History'!$AW$4:$AW$83,"") -> 0.49928469 | K8: =_xlfn.XLOOKUP(Q8,'Sales Rec'!$E$4:$E$91,'Sales Rec'!$CV$4:$CV$91,"") -> 6 | L8: =_xlfn.XLOOKUP(Q8,'Cement Ranking'!$F$7:$F$35,'Cement Ranking'!$AQ$7:$AQ$35,"") -> 5 | M8: =_xlfn.XLOOKUP(Q8,'Sales Rec'!$E$4:$E$32,'Sales Rec'!$DS$4:$DS$32,"") -> B | N8: =_xlfn.XLOOKUP(Q8,'Sales Rec'!$E$4:$E$32,'Sales Rec'!$DZ$4:$DZ$32,"") -> BB | O8: =_xlfn.XLOOKUP($Q8,'History Records'!$B$7:$B$88,'History Records'!$G$7:$G$88,"") | P8: سيمان فارس نو | Q8: سفانو | R8: 12 | S8: =(V8*AM8)/10000000000 -> 8528 | T8: =_xlfn.XLOOKUP($Q8,'Price Record'!$C$6:$C$85,'Price Record'!H$6:H$85,"") -> 53300 | U8: =_xlfn.XLOOKUP(Q8,'دیده بان بازار'!$A$3:$A$3542,'دیده بان بازار'!$M$3:$M$3542,"") -> 3 | V8: =_xlfn.XLOOKUP($Q8,'Price Record'!$C$6:$C$85,'Price Record'!G$6:G$85,"") -> 53300 | W8: =_xlfn.XLOOKUP(Q8,'دیده بان بازار'!$A$3:$A$3542,'دیده بان بازار'!$J$3:$J$3542,"") -> 3 | X8: =S8+CY8-DK8-DQ8 -> 9424 | Y8: =IFERROR(IF(U8-W8<-1.5,"B",IF(U8-W8>1.5,"S","")),"") | Z8: =IFERROR((S8-EX8)/EX8,"") -> 0.43039249 | AA8: =((365-AH8)/365)*$AA$2 -> 0.1430137 | AB8: =IFERROR(((AA8-Z8)*10000)/(365-AH8),"") -> -49.548067 | AC8: =IFERROR(($S8-EV8)/EV8,"") -> 0.43039249 | AD8: =IFERROR((S8-ET8)/ET8,"") -> 0.62965794 | AE8: =(S8-ER8)/ER8 -> 1.3545003 | AF8: =(S8-EP8)/EP8 -> 0.77407947 | AG8: =(S8-EN8)/EN8 -> 4.0105758 | AH8: =IF((AI8-TODAY())>0,AI8-TODAY(),(365-(TODAY()-AI8))) -> 307 | AI8: 46181 | AJ8: 46193 | AK8: 1080000 | AL8: 1120000 | AM8: =CJ8*10000000 -> 1600000000 | AN8: 0.1565 | AO8: =_xlfn.XLOOKUP(Q8,'Cem Sales'!$K$5:$K$33,'Cem Sales'!$DU$5:$DU$33,"") -> 2703 | AP8: 2268 | AQ8: 1166 | AR8: =_xlfn.XLOOKUP(Q8,'Sales Rec'!$E$4:$E$86,'Sales Rec'!$X$4:$X$86,"") -> 3785.9156 | AS8: =_xlfn.XLOOKUP(Q8,'Sales Rec'!$E$4:$E$86,'Sales Rec'!$K$4:$K$86,"") -> 4 | AT8: =(S8-(CO8*CC8))/AR8 -> 2.2525594 | AU8: =MIN(MAX(IF(($Q$42-AT8)*$R$42<-20,-20,IF(($Q$42-AT8)*$R$42>20,20,($Q$42-AT8)*$R$42)), -10), 10) -> 1.7376322 | AV8: 892 | AW8: 494 | AX8: =ROUND(AW8/AV8,3) -> 0.554 | AY8: 0.494 | AZ8: 0.514 | BA8: 0.431 | BB8: =IF(BC8=0,0,MIN(MAX(IF(BC8=BD8,BC8-BF8,BC8-BD8)*$R$43, -10), 10)) -> 5.1 | BC8: =IF(CN8=0,BE8,ROUND((CN8-CM8)/AV8,3)) -> 0.46 | BD8: 0.409 | BE8: 0.43 | BF8: 0.374 | BG8: =AX8-BC8 -> 0.094 | BH8: =BG8*AV8*(4/BO8) -> 335.392 | BI8: =AY8-BD8 -> 0.085 | BJ8: 0 | BK8: =_xlfn.XLOOKUP(Q8,'Sales Rec'!$E$4:$E$91,'Sales Rec'!$Y$4:$Y$91,"") -> 0.66927497 | BL8: =IF(BK8=0,0,MIN(MAX((BK8-Z8)*$R$44,-5),5)) -> 5 | BN8: 3 | BO8: =IF((BN8-R8+12)/3>4,(BN8-R8+12)/3-4, (BN8-R8+12)/3) -> 1 | BP8: 3220 | BS8: =(_xlfn.XLOOKUP(Q8,'Sales Rec'!$E$4:$E$32,'Sales Rec'!$X$4:$X$32)*BC8+CL8)*1000/CJ8 -> 12322.007 | BT8: =IF((CN8/CJ8)*1000*(12/(12-(R8-BN8)))=0,CB8,IF(R8-BN8>=0,((CP8/CJ8)*1000*(12/(12-(R8-BN8)))),((CP8/CJ8)*1000*(12/(BN8-R8))))) -> 12875 | BV8: =IF(CN8=0,V8/BT8,(V8*2)/(BS8+BT8)) -> 4.2306611 | BW8: =MIN(MAX(IF(BV8<0,-20, IF(BV8>50, -20,($Q$45-BV8)*$R$45)), -20), 20) -> 3.8466943 | BX8: =IFERROR(S8/BV8,"") -> 2015.7606 | BY8: =S8/CC8 -> 1353.6508 | BZ8: =AR8*AX8 -> 2097.3973 | CA8: =X8/BZ8 -> 4.4931879 | CB8: =_xlfn.XLOOKUP($Q8,'Price Record'!$C$6:$C$85,'Price Record'!I$6:I$85,"") -> 8458 | CC8: =_xlfn.XLOOKUP($Q8,'Price Record'!$C$6:$C$85,'Price Record'!J$6:J$85,"") -> 6.3 | CD8: =MIN(MAX(IF(CC8<0,-20, IF(CC8>50, -20,($Q$46-CC8)*$R$46)), -20), 20) -> -3.9 | CE8: =CY8/BX8 -> 0.8602212 | CF8: =MIN(MAX(($Q$47-CE8)*$R$47, -10), 10) -> 4.5591152 | CG8: =BX8/(CU8+DG8) -> 0.72275389 | CH8: =MIN(MAX((CG8-$Q$48)*$R$48, -10), 10) -> 4.8413083 | CJ8: 160 | CK8: 96 | CL8: 230 | CM8: 105 | CN8: 515 | CP8: =IF(AND(CM8>0, CL8>(CM8/(BO8/4))), CN8+CL8*BO8/4-CM8, CN8) -> 515 | CQ8: =(AR8*BC8)*(_xlfn.XLOOKUP($Q8,'Sales Rec'!$E$4:$E$32,'Sales Rec'!$L$4:$L$32,"")/12)+CO8 -> 580.50706 | CR8: 611 | CS8: -33 | CT8: =_xlfn.TEXTJOIN(", ",TRUE, IF(CU8/(CJ8*1.1+CR8+CS8)<=0.975,"Check EQ",""), IF(CR8<>(CN8+CK8),"Check RE","") ) | CU8: =DB8-CY8 -> 804 | CV8: 1669 | CW8: 432 | CX8: 65 | CY8: =CV8+CX8 -> 1734 | CZ8: =DG8/CV8 -> 1.1893349 | DA8: =MIN(MAX((CZ8-$Q$50)*$R$50, -6), 6) -> -0.085320551 | DB8: =DD8+DG8 -> 2538 | DC8: =(CY8/DB8) -> 0.68321513 | DD8: 553 | DE8: 504 | DF8: 29 | DG8: 1985 | DH8: =DG8-CV8 -> 316 | DI8: =AR8/DH8 -> 11.980746 | DJ8: 864 | DK8: 98 | DL8: 213 | DM8: =CY8/DB8 -> 0.68321513 | DN8: =MIN(MAX(($Q$51-DM8)*$R$51, -6), 6) -> -0.83085318 | DO8: =(DQ8-CW8)/BZ8 -> 0.14684867 | DP8: =MIN(MAX(ROUNDDOWN(DO8*5,0),-10),5) -> 0 | DQ8: 740 | DR8: =DG8-DJ8-DK8-DQ8-DL8 -> 70 | DS8: G | DT8: =IFERROR(((S8/AK8)/$Q$38*1000000000),"") -> 41.779345 | DU8: =IF(DS8="G",(500000*$Q$57+(AK8-500000)*$R$57*$Q$57)*$Q$38/1000000000, (150000*$Q$58+(AK8-150000)*$R$58*$Q$58)*$Q$38/1000000000) -> 10773.945 | DV8: =DU8/S8 -> 1.2633613 | DW8: =MIN(MAX((DV8-$Q$53)*$R$53, -10), 10) -> 5.2672256 | DX8: =IFERROR((AR8/AK8)*1000000,"") -> 3505.4774 | DY8: =MIN(MAX(((DX8-$Q$54)/$Q$54)*$R$54, -10), 10) -> 10 | DZ8: =(S8/AR8)/BV8 -> 0.53243675 | EA8: =MIN(MAX((DZ8-$Q$55)*$R$55,-10), 10) -> 1.2559703 | EB8: =_xlfn.XLOOKUP(Q8,'Cem Sales'!$K$5:$K$33,'Cem Sales'!$DN$5:$DN$33, 0) -> 0 | EC8: =MIN(MAX(EB8*$R$56, 0), 10) -> 0 | ED8: =($CB8/$Q$40)*(IF(($R8+2-$Q$39)<0,(88-$R8-2+$Q$39),(100-($R8+2-$Q$39))))/100 -> 30787.12 | EE8: =($BT8/$Q$40)*(IF(($R8+2-$Q$39)<0,(88-$R8-2+$Q$39),(100-($R8+3-$Q$39))))/100 -> 46350 | EF8: =((CR8-CN8)*10000000000)/AM8 -> 600 | EG8: =(ED8+EE8+EF8)/2 -> 38868.56 | EH8: =IFERROR((AJ8-AI8),230) -> 12 | EI8: 7435 | EJ8: =EI8/(EI8+EW8) -> 0.1663311 | EM8: 34220 | EN8: 1702 | EO8: 96140 | EP8: 4807 | EQ8: 72970 | ER8: 3622 | ES8: 32705 | ET8: 5233 | EU8: 37265 | EV8: 5962 | EW8: 37265 | EX8: 5962 | EY8: =IFERROR((EX8-EN8)/EN8,"") -> 2.5029377 | EZ8: =RANK(EY8,$EY$7:$EY$35) -> 24
A9: =_xlfn.XLOOKUP(Q9,'Cement Ranking'!$F$7:$F$35,'Cement Ranking'!$AO$7:$AO$35, "") -> 35.869706 | B9: =_xlfn.XLOOKUP(Q9,'Cement Ranking'!$F$7:$F$35,'Cement Ranking'!$AN$7:$AN$35, "") -> 19.422335 | C9: =((((CK9*10000000000)/AM9)+CB9*0.8)/V9)/((AH9+EH9)/365) -> 0.14990693 | D9: =(CC9-BV9) -> 0.91259939 | E9: =IF(OR(AX9=AY9, AX9=""), (AY9-BA9), (AX9-AY9))*100 -> 2.8 | F9: =IF(OR(BC9=BD9, BC9=""), (BD9-BF9), (BC9-BD9))*100 -> 1.1 | G9: {=IFERROR(_xlfn.XLOOKUP(Q9,'Sales Rec'!$E$4:$E$32,'Sales Rec'!$CU$4:$CU$32*100,""),"")} -> -8.5860708 | H9: =_xlfn.XLOOKUP(Q9,'Sales Rec'!$E$4:$E$32,'Sales Rec'!$DQ$4:$DQ$32,"") -> 0.57489879 | I9: =_xlfn.XLOOKUP(Q9,'Sales History'!$C$4:$C$83,'Sales History'!$AS$4:$AS$83,"") -> 0.28375734 | J9: =_xlfn.XLOOKUP(Q9,'Sales History'!$C$4:$C$83,'Sales History'!$AW$4:$AW$83,"") -> 0.25992063 | K9: =_xlfn.XLOOKUP(Q9,'Sales Rec'!$E$4:$E$91,'Sales Rec'!$CV$4:$CV$91,"") -> 17 | L9: =_xlfn.XLOOKUP(Q9,'Cement Ranking'!$F$7:$F$35,'Cement Ranking'!$AQ$7:$AQ$35,"") -> 4 | M9: =_xlfn.XLOOKUP(Q9,'Sales Rec'!$E$4:$E$32,'Sales Rec'!$DS$4:$DS$32,"") -> N | N9: =_xlfn.XLOOKUP(Q9,'Sales Rec'!$E$4:$E$32,'Sales Rec'!$DZ$4:$DZ$32,"") -> B | O9: =_xlfn.XLOOKUP($Q9,'History Records'!$B$7:$B$88,'History Records'!$G$7:$G$88,"") | P9: سيمان‌ بهبهان‌ | Q9: سبهان | R9: 12 | S9: =(V9*AM9)/10000000000 -> 4040.4 | T9: =_xlfn.XLOOKUP($Q9,'Price Record'!$C$6:$C$85,'Price Record'!H$6:H$85,"") -> 5460 | U9: =_xlfn.XLOOKUP(Q9,'دیده بان بازار'!$A$3:$A$3542,'دیده بان بازار'!$M$3:$M$3542,"") -> 2.82 | V9: =_xlfn.XLOOKUP($Q9,'Price Record'!$C$6:$C$85,'Price Record'!G$6:G$85,"") -> 5460 | W9: =_xlfn.XLOOKUP(Q9,'دیده بان بازار'!$A$3:$A$3542,'دیده بان بازار'!$J$3:$J$3542,"") -> 2.82 | X9: =S9+CY9-DK9-DQ9 -> 4698.4 | Y9: =IFERROR(IF(U9-W9<-1.5,"B",IF(U9-W9>1.5,"S","")),"") | Z9: =IFERROR((S9-EX9)/EX9,"") -> 0.13271657 | AA9: =((365-AH9)/365)*$AA$2 -> 0.12821918 | AB9: =IFERROR(((AA9-Z9)*10000)/(365-AH9),"") -> -0.86488278 | AC9: =IFERROR(($S9-EV9)/EV9,"") -> 0.13271657 | AD9: =IFERROR((S9-ET9)/ET9,"") -> 0.20644969 | AE9: =(S9-ER9)/ER9 -> 1.3753086 | AF9: =(S9-EP9)/EP9 -> 1.5363465 | AG9: =(S9-EN9)/EN9 -> 3.1739669 | AH9: =IF((AI9-TODAY())>0,AI9-TODAY(),(365-(TODAY()-AI9))) -> 313 | AI9: 46187 | AJ9: 46266 | AK9: 825000 | AL9: 850000 | AM9: =CJ9*10000000 -> 7400000000 | AN9: 0.2392 | AO9: =_xlfn.XLOOKUP(Q9,'Cem Sales'!$K$5:$K$33,'Cem Sales'!$DU$5:$DU$33,"") -> 2012 | AP9: 1870 | AQ9: 583 | AR9: =_xlfn.XLOOKUP(Q9,'Sales Rec'!$E$4:$E$86,'Sales Rec'!$X$4:$X$86,"") -> 2594.5304 | AS9: =_xlfn.XLOOKUP(Q9,'Sales Rec'!$E$4:$E$86,'Sales Rec'!$K$4:$K$86,"") -> 4 | AT9: =(S9-(CO9*CC9))/AR9 -> 1.5572761 | AU9: =MIN(MAX(IF(($Q$42-AT9)*$R$42<-20,-20,IF(($Q$42-AT9)*$R$42>20,20,($Q$42-AT9)*$R$42)), -10), 10) -> 8.6904662 | AV9: 656 | AW9: 231 | AX9: =ROUND(AW9/AV9,3) -> 0.352 | AY9: 0.324 | AZ9: 0.312 | BA9: 0.314 | BB9: =IF(BC9=0,0,MIN(MAX(IF(BC9=BD9,BC9-BF9,BC9-BD9)*$R$43, -10), 10)) -> 1.1 | BC9: =IF(CN9=0,BE9,ROUND((CN9-CM9)/AV9,3)) -> 0.279 | BD9: 0.268 | BE9: 0.271 | BF9: 0.26 | BG9: =AX9-BC9 -> 0.073 | BH9: =BG9*AV9*(4/BO9) -> 191.552 | BI9: =AY9-BD9 -> 0.056 | BJ9: 0 | BK9: =_xlfn.XLOOKUP(Q9,'Sales Rec'!$E$4:$E$91,'Sales Rec'!$Y$4:$Y$91,"") -> 0.38744939 | BL9: =IF(BK9=0,0,MIN(MAX((BK9-Z9)*$R$44,-5),5)) -> 5 | BN9: 3 | BO9: =IF((BN9-R9+12)/3>4,(BN9-R9+12)/3-4, (BN9-R9+12)/3) -> 1 | BP9: 304 | BS9: =(_xlfn.XLOOKUP(Q9,'Sales Rec'!$E$4:$E$32,'Sales Rec'!$X$4:$X$32)*BC9+CL9)*1000/CJ9 -> 1153.8837 | BT9: =IF((CN9/CJ9)*1000*(12/(12-(R9-BN9)))=0,CB9,IF(R9-BN9>=0,((CP9/CJ9)*1000*(12/(12-(R9-BN9)))),((CP9/CJ9)*1000*(12/(BN9-R9))))) -> 1216.2162 | BV9: =IF(CN9=0,V9/BT9,(V9*2)/(BS9+BT9)) -> 4.6074006 | BW9: =MIN(MAX(IF(BV9<0,-20, IF(BV9>50, -20,($Q$45-BV9)*$R$45)), -20), 20) -> 1.962997 | BX9: =IFERROR(S9/BV9,"") -> 876.93699 | BY9: =S9/CC9 -> 731.95652 | BZ9: =AR9*AX9 -> 913.27469 | CA9: =X9/BZ9 -> 5.1445639 | CB9: =_xlfn.XLOOKUP($Q9,'Price Record'!$C$6:$C$85,'Price Record'!I$6:I$85,"") -> 989 | CC9: =_xlfn.XLOOKUP($Q9,'Price Record'!$C$6:$C$85,'Price Record'!J$6:J$85,"") -> 5.52 | CD9: =MIN(MAX(IF(CC9<0,-20, IF(CC9>50, -20,($Q$46-CC9)*$R$46)), -20), 20) -> -1.56 | CE9: =CY9/BX9 -> 1.2395417 | CF9: =MIN(MAX(($Q$47-CE9)*$R$47, -10), 10) -> 3.041833 | CG9: =BX9/(CU9+DG9) -> 0.39644529 | CH9: =MIN(MAX((CG9-$Q$48)*$R$48, -10), 10) -> -0.053320621 | CJ9: 740 | CK9: 65 | CL9: 130 | CM9: 42 | CN9: 225 | CP9: =IF(AND(CM9>0, CL9>(CM9/(BO9/4))), CN9+CL9*BO9/4-CM9, CN9) -> 225 | CQ9: =(AR9*BC9)*(_xlfn.XLOOKUP($Q9,'Sales Rec'!$E$4:$E$32,'Sales Rec'!$L$4:$L$32,"")/12)+CO9 -> 241.29132 | CR9: 290 | CS9: -22 | CT9: =_xlfn.TEXTJOIN(", ",TRUE, IF(CU9/(CJ9*1.1+CR9+CS9)<=0.975,"Check EQ",""), IF(CR9<>(CN9+CK9),"Check RE","") ) | CU9: =DB9-CY9 -> 1063 | CV9: 960 | CW9: 28 | CX9: 127 | CY9: =CV9+CX9 -> 1087 | CZ9: =DG9/CV9 -> 1.196875 | DA9: =MIN(MAX((CZ9-$Q$50)*$R$50, -6), 6) -> -0.025 | DB9: =DD9+DG9 -> 2150 | DC9: =(CY9/DB9) -> 0.5055814 | DD9: 1001 | DE9: 966 | DF9: 27 | DG9: 1149 | DH9: =DG9-CV9 -> 189 | DI9: =AR9/DH9 -> 13.727674 | DJ9: 469 | DK9: 277 | DL9: 202 | DM9: =CY9/DB9 -> 0.5055814 | DN9: =MIN(MAX(($Q$51-DM9)*$R$51, -6), 6) -> 0.94548417 | DO9: =(DQ9-CW9)/BZ9 -> 0.13577514 | DP9: =MIN(MAX(ROUNDDOWN(DO9*5,0),-10),5) -> 0 | DQ9: 152 | DR9: =DG9-DJ9-DK9-DQ9-DL9 -> 49 | DS9: G | DT9: =IFERROR(((S9/AK9)/$Q$38*1000000000),"") -> 25.912458 | DU9: =IF(DS9="G",(500000*$Q$57+(AK9-500000)*$R$57*$Q$57)*$Q$38/1000000000, (150000*$Q$58+(AK9-150000)*$R$58*$Q$58)*$Q$38/1000000000) -> 8737.7062 | DV9: =DU9/S9 -> 2.1625845 | DW9: =MIN(MAX((DV9-$Q$53)*$R$53, -10), 10) -> 10 | DX9: =IFERROR((AR9/AK9)*1000000,"") -> 3144.8853 | DY9: =MIN(MAX(((DX9-$Q$54)/$Q$54)*$R$54, -10), 10) -> 6.447371 | DZ9: =(S9/AR9)/BV9 -> 0.3379945 | EA9: =MIN(MAX((DZ9-$Q$55)*$R$55,-10), 10) -> -4.5772971 | EB9: =_xlfn.XLOOKUP(Q9,'Cem Sales'!$K$5:$K$33,'Cem Sales'!$DN$5:$DN$33, 0) -> 0.48971722 | EC9: =MIN(MAX(EB9*$R$56, 0), 10) -> 4.8971722 | ED9: =($CB9/$Q$40)*(IF(($R9+2-$Q$39)<0,(88-$R9-2+$Q$39),(100-($R9+2-$Q$39))))/100 -> 3599.96 | EE9: =($BT9/$Q$40)*(IF(($R9+2-$Q$39)<0,(88-$R9-2+$Q$39),(100-($R9+3-$Q$39))))/100 -> 4378.3784 | EF9: =((CR9-CN9)*10000000000)/AM9 -> 87.837838 | EG9: =(ED9+EE9+EF9)/2 -> 4033.0881 | EH9: =IFERROR((AJ9-AI9),230) -> 79 | EI9: 790 | EJ9: =EI9/(EI9+EW9) -> 0.14081996 | EK9: 37 | EM9: 48400 | EN9: 968 | EO9: 79640 | EP9: 1593 | EQ9: 85050 | ER9: 1701 | ES9: 4525 | ET9: 3349 | EU9: 4820 | EV9: 3567 | EW9: 4820 | EX9: 3567 | EY9: =IFERROR((EX9-EN9)/EN9,"") -> 2.6849174 | EZ9: =RANK(EY9,$EY$7:$EY$35) -> 23
A10: =_xlfn.XLOOKUP(Q10,'Cement Ranking'!$F$7:$F$35,'Cement Ranking'!$AO$7:$AO$35, "") -> 36.336967 | B10: =_xlfn.XLOOKUP(Q10,'Cement Ranking'!$F$7:$F$35,'Cement Ranking'!$AN$7:$AN$35, "") -> 27.7134 | C10: =((((CK10*10000000000)/AM10)+CB10*0.8)/V10)/((AH10+EH10)/365) -> 0.16309595 | D10: =(CC10-BV10) -> 2.1238768 | E10: =IF(OR(AX10=AY10, AX10=""), (AY10-BA10), (AX10-AY10))*100 -> 6 | F10: =IF(OR(BC10=BD10, BC10=""), (BD10-BF10), (BC10-BD10))*100 -> 13.6 | G10: {=IFERROR(_xlfn.XLOOKUP(Q10,'Sales Rec'!$E$4:$E$32,'Sales Rec'!$CU$4:$CU$32*100,""),"")} -> 3.3151261 | H10: =_xlfn.XLOOKUP(Q10,'Sales Rec'!$E$4:$E$32,'Sales Rec'!$DQ$4:$DQ$32,"") -> 0.71785714 | I10: =_xlfn.XLOOKUP(Q10,'Sales History'!$C$4:$C$83,'Sales History'!$AS$4:$AS$83,"") -> 0.24521739 | J10: =_xlfn.XLOOKUP(Q10,'Sales History'!$C$4:$C$83,'Sales History'!$AW$4:$AW$83,"") -> 0.55471698 | K10: =_xlfn.XLOOKUP(Q10,'Sales Rec'!$E$4:$E$91,'Sales Rec'!$CV$4:$CV$91,"") -> 10 | L10: =_xlfn.XLOOKUP(Q10,'Cement Ranking'!$F$7:$F$35,'Cement Ranking'!$AQ$7:$AQ$35,"") -> 3 | M10: =_xlfn.XLOOKUP(Q10,'Sales Rec'!$E$4:$E$32,'Sales Rec'!$DS$4:$DS$32,"") -> B | N10: =_xlfn.XLOOKUP(Q10,'Sales Rec'!$E$4:$E$32,'Sales Rec'!$DZ$4:$DZ$32,"") -> B | O10: =_xlfn.XLOOKUP($Q10,'History Records'!$B$7:$B$88,'History Records'!$G$7:$G$88,"") -> Closed | P10: سيمان‌ داراب‌ | Q10: ساراب | R10: 12 | S10: =(V10*AM10)/10000000000 -> 7705 | T10: =_xlfn.XLOOKUP($Q10,'Price Record'!$C$6:$C$85,'Price Record'!H$6:H$85,"") -> 15410 | U10: =_xlfn.XLOOKUP(Q10,'دیده بان بازار'!$A$3:$A$3542,'دیده بان بازار'!$M$3:$M$3542,"") | V10: =_xlfn.XLOOKUP($Q10,'Price Record'!$C$6:$C$85,'Price Record'!G$6:G$85,"") -> 15410 | W10: =_xlfn.XLOOKUP(Q10,'دیده بان بازار'!$A$3:$A$3542,'دیده بان بازار'!$J$3:$J$3542,"") | X10: =S10+CY10-DK10-DQ10 -> 8343 | Y10: =IFERROR(IF(U10-W10<-1.5,"B",IF(U10-W10>1.5,"S","")),"") | Z10: =IFERROR((S10-EX10)/EX10,"") -> 0.0001298027 | AA10: =((365-AH10)/365)*$AA$2 -> 0.041917808 | AB10: =IFERROR(((AA10-Z10)*10000)/(365-AH10),"") -> 24.58118 | AC10: =IFERROR(($S10-EV10)/EV10,"") -> 0.0001298027 | AD10: =IFERROR((S10-ET10)/ET10,"") -> 0.5597166 | AE10: =(S10-ER10)/ER10 -> 1.0563117 | AF10: =(S10-EP10)/EP10 -> 0.86833172 | AG10: =(S10-EN10)/EN10 -> 2.7294288 | AH10: =IF((AI10-TODAY())>0,AI10-TODAY(),(365-(TODAY()-AI10))) -> 348 | AI10: 46222 | AJ10: 46331 | AK10: 1080000 | AL10: 1120000 | AM10: =CJ10*10000000 -> 5000000000 | AN10: 0.2968 | AO10: =_xlfn.XLOOKUP(Q10,'Cem Sales'!$K$5:$K$33,'Cem Sales'!$DU$5:$DU$33,"") -> 2039 | AP10: 1751 | AQ10: 732 | AR10: =_xlfn.XLOOKUP(Q10,'Sales Rec'!$E$4:$E$86,'Sales Rec'!$X$4:$X$86,"") -> 2763.7339 | AS10: =_xlfn.XLOOKUP(Q10,'Sales Rec'!$E$4:$E$86,'Sales Rec'!$K$4:$K$86,"") -> 4 | AT10: =(S10-(CO10*CC10))/AR10 -> 2.7619048 | AU10: =MIN(MAX(IF(($Q$42-AT10)*$R$42<-20,-20,IF(($Q$42-AT10)*$R$42>20,20,($Q$42-AT10)*$R$42)), -10), 10) -> -3.3558213 | AV10: 716 | AW10: 301 | AX10: =ROUND(AW10/AV10,3) -> 0.42 | AY10: 0.36 | AZ10: 0.418 | BA10: 0.399 | BB10: =IF(BC10=0,0,MIN(MAX(IF(BC10=BD10,BC10-BF10,BC10-BD10)*$R$43, -10), 10)) -> 10 | BC10: =IF(CN10=0,BE10,ROUND((CN10-CM10)/AV10,3)) -> 0.43 | BD10: 0.294 | BE10: 0.362 | BF10: 0.342 | BG10: =AX10-BC10 -> -0.01 | BH10: =BG10*AV10*(4/BO10) -> -28.64 | BI10: =AY10-BD10 -> 0.066 | BJ10: 0 | BK10: =_xlfn.XLOOKUP(Q10,'Sales Rec'!$E$4:$E$91,'Sales Rec'!$Y$4:$Y$91,"") -> 0.5783746 | BL10: =IF(BK10=0,0,MIN(MAX((BK10-Z10)*$R$44,-5),5)) -> 5 | BN10: 3 | BO10: =IF((BN10-R10+12)/3>4,(BN10-R10+12)/3-4, (BN10-R10+12)/3) -> 1 | BP10: 3370 | BS10: =(_xlfn.XLOOKUP(Q10,'Sales Rec'!$E$4:$E$32,'Sales Rec'!$X$4:$X$32)*BC10+CL10)*1000/CJ10 -> 3146.8112 | BT10: =IF((CN10/CJ10)*1000*(12/(12-(R10-BN10)))=0,CB10,IF(R10-BN10>=0,((CP10/CJ10)*1000*(12/(12-(R10-BN10)))),((CP10/CJ10)*1000*(12/(BN10-R10))))) -> 3848 | BV10: =IF(CN10=0,V10/BT10,(V10*2)/(BS10+BT10)) -> 4.4061232 | BW10: =MIN(MAX(IF(BV10<0,-20, IF(BV10>50, -20,($Q$45-BV10)*$R$45)), -20), 20) -> 2.9693839 | BX10: =IFERROR(S10/BV10,"") -> 1748.7028 | BY10: =S10/CC10 -> 1179.9387 | BZ10: =AR10*AX10 -> 1160.7683 | CA10: =X10/BZ10 -> 7.1874812 | CB10: =_xlfn.XLOOKUP($Q10,'Price Record'!$C$6:$C$85,'Price Record'!I$6:I$85,"") -> 2361 | CC10: =_xlfn.XLOOKUP($Q10,'Price Record'!$C$6:$C$85,'Price Record'!J$6:J$85,"") -> 6.53 | CD10: =MIN(MAX(IF(CC10<0,-20, IF(CC10>50, -20,($Q$46-CC10)*$R$46)), -20), 20) -> -4.59 | CE10: =CY10/BX10 -> 0.73368671 | CF10: =MIN(MAX(($Q$47-CE10)*$R$47, -10), 10) -> 5.0652532 | CG10: =BX10/(CU10+DG10) -> 0.42239198 | CH10: =MIN(MAX((CG10-$Q$48)*$R$48, -10), 10) -> 0.33587969 | CJ10: 500 | CK10: 629 | CL10: 385 | CM10: 173 | CN10: 481 | CO10: 11 | CP10: =IF(AND(CM10>0, CL10>(CM10/(BO10/4))), CN10+CL10*BO10/4-CM10, CN10) -> 481 | CQ10: =(AR10*BC10)*(_xlfn.XLOOKUP($Q10,'Sales Rec'!$E$4:$E$32,'Sales Rec'!$L$4:$L$32,"")/12)+CO10 -> 407.1352 | CR10: 1110 | CS10: -19 | CT10: =_xlfn.TEXTJOIN(", ",TRUE, IF(CU10/(CJ10*1.1+CR10+CS10)<=0.975,"Check EQ",""), IF(CR10<>(CN10+CK10),"Check RE","") ) | CU10: =DB10-CY10 -> 1941 | CV10: 1160 | CW10: 0 | CX10: 123 | CY10: =CV10+CX10 -> 1283 | CZ10: =DG10/CV10 -> 1.8956897 | DA10: =MIN(MAX((CZ10-$Q$50)*$R$50, -6), 6) -> 5.5655172 | DB10: =DD10+DG10 -> 3224 | DC10: =(CY10/DB10) -> 0.39795285 | DD10: 1025 | DE10: 474 | DF10: 175 | DG10: 2199 | DH10: =DG10-CV10 -> 1039 | DI10: =AR10/DH10 -> 2.6599942 | DJ10: 1044 | DK10: 275 | DL10: 245 | DM10: =CY10/DB10 -> 0.39795285 | DN10: =MIN(MAX(($Q$51-DM10)*$R$51, -6), 6) -> 2.0217696 | DO10: =(DQ10-CW10)/BZ10 -> 0.31875441 | DP10: =MIN(MAX(ROUNDDOWN(DO10*5,0),-10),5) -> 1 | DQ10: 370 | DR10: =DG10-DJ10-DK10-DQ10-DL10 -> 265 | DS10: G | DT10: =IFERROR(((S10/AK10)/$Q$38*1000000000),"") -> 37.747403 | DU10: =IF(DS10="G",(500000*$Q$57+(AK10-500000)*$R$57*$Q$57)*$Q$38/1000000000, (150000*$Q$58+(AK10-150000)*$R$58*$Q$58)*$Q$38/1000000000) -> 10773.945 | DV10: =DU10/S10 -> 1.3983056 | DW10: =MIN(MAX((DV10-$Q$53)*$R$53, -10), 10) -> 7.9661129 | DX10: =IFERROR((AR10/AK10)*1000000,"") -> 2559.0129 | DY10: =MIN(MAX(((DX10-$Q$54)/$Q$54)*$R$54, -10), 10) -> -0.3425455 | DZ10: =(S10/AR10)/BV10 -> 0.63273196 | EA10: =MIN(MAX((DZ10-$Q$55)*$R$55,-10), 10) -> 4.2648268 | EB10: =_xlfn.XLOOKUP(Q10,'Cem Sales'!$K$5:$K$33,'Cem Sales'!$DN$5:$DN$33, 0) -> 0.043659044 | EC10: =MIN(MAX(EB10*$R$56, 0), 10) -> 0.43659044 | ED10: =($CB10/$Q$40)*(IF(($R10+2-$Q$39)<0,(88-$R10-2+$Q$39),(100-($R10+2-$Q$39))))/100 -> 8594.04 | EE10: =($BT10/$Q$40)*(IF(($R10+2-$Q$39)<0,(88-$R10-2+$Q$39),(100-($R10+3-$Q$39))))/100 -> 13852.8 | EF10: =((CR10-CN10)*10000000000)/AM10 -> 1258 | EG10: =(ED10+EE10+EF10)/2 -> 11852.42 | EH10: =IFERROR((AJ10-AI10),230) -> 109 | EI10: 4860 | EJ10: =EI10/(EI10+EW10) -> 0.073636364 | EM10: 16400 | EN10: 2066 | EO10: 32730 | EP10: 4124 | EQ10: 29740 | ER10: 3747 | ES10: 39210 | ET10: 4940 | EU10: 61140 | EV10: 7704 | EW10: 61140 | EX10: 7704 | EY10: =IFERROR((EX10-EN10)/EN10,"") -> 2.7289448 | EZ10: =RANK(EY10,$EY$7:$EY$35) -> 21
A11: =_xlfn.XLOOKUP(Q11,'Cement Ranking'!$F$7:$F$35,'Cement Ranking'!$AO$7:$AO$35, "") -> 26.677279 | B11: =_xlfn.XLOOKUP(Q11,'Cement Ranking'!$F$7:$F$35,'Cement Ranking'!$AN$7:$AN$35, "") -> 19.423634 | C11: =((((CK11*10000000000)/AM11)+CB11*0.8)/V11)/((AH11+EH11)/365) -> 0.14937934 | D11: =(CC11-BV11) -> 1.6808506 | E11: =IF(OR(AX11=AY11, AX11=""), (AY11-BA11), (AX11-AY11))*100 -> 43.3 | F11: =IF(OR(BC11=BD11, BC11=""), (BD11-BF11), (BC11-BD11))*100 -> 39.5 | G11: {=IFERROR(_xlfn.XLOOKUP(Q11,'Sales Rec'!$E$4:$E$32,'Sales Rec'!$CU$4:$CU$32*100,""),"")} -> 13.436985 | H11: =_xlfn.XLOOKUP(Q11,'Sales Rec'!$E$4:$E$32,'Sales Rec'!$DQ$4:$DQ$32,"") -> 1.1594595 | I11: =_xlfn.XLOOKUP(Q11,'Sales History'!$C$4:$C$83,'Sales History'!$AS$4:$AS$83,"") -> 0.4160401 | J11: =_xlfn.XLOOKUP(Q11,'Sales History'!$C$4:$C$83,'Sales History'!$AW$4:$AW$83,"") -> 0.63390663 | K11: =_xlfn.XLOOKUP(Q11,'Sales Rec'!$E$4:$E$91,'Sales Rec'!$CV$4:$CV$91,"") -> 1 | L11: =_xlfn.XLOOKUP(Q11,'Cement Ranking'!$F$7:$F$35,'Cement Ranking'!$AQ$7:$AQ$35,"") -> 7 | M11: =_xlfn.XLOOKUP(Q11,'Sales Rec'!$E$4:$E$32,'Sales Rec'!$DS$4:$DS$32,"") -> BB | N11: =_xlfn.XLOOKUP(Q11,'Sales Rec'!$E$4:$E$32,'Sales Rec'!$DZ$4:$DZ$32,"") -> BB | O11: =_xlfn.XLOOKUP($Q11,'History Records'!$B$7:$B$88,'History Records'!$G$7:$G$88,"") | P11: سيمان‌ قائن‌ | Q11: سقاين | R11: 12 | S11: =(V11*AM11)/10000000000 -> 9712 | T11: =_xlfn.XLOOKUP($Q11,'Price Record'!$C$6:$C$85,'Price Record'!H$6:H$85,"") -> 24280 | U11: =_xlfn.XLOOKUP(Q11,'دیده بان بازار'!$A$3:$A$3542,'دیده بان بازار'!$M$3:$M$3542,"") -> 2.97 | V11: =_xlfn.XLOOKUP($Q11,'Price Record'!$C$6:$C$85,'Price Record'!G$6:G$85,"") -> 24280 | W11: =_xlfn.XLOOKUP(Q11,'دیده بان بازار'!$A$3:$A$3542,'دیده بان بازار'!$J$3:$J$3542,"") -> 2.97 | X11: =S11+CY11-DK11-DQ11 -> 10392 | Y11: =IFERROR(IF(U11-W11<-1.5,"B",IF(U11-W11>1.5,"S","")),"") | Z11: =IFERROR((S11-EX11)/EX11,"") -> 0.48592411 | AA11: =((365-AH11)/365)*$AA$2 -> 0.11342466 | AB11: =IFERROR(((AA11-Z11)*10000)/(365-AH11),"") -> -80.978142 | AC11: =IFERROR(($S11-EV11)/EV11,"") -> 0.48592411 | AD11: =IFERROR((S11-ET11)/ET11,"") -> 2.5758468 | AE11: =(S11-ER11)/ER11 -> 4.047817 | AF11: =(S11-EP11)/EP11 -> 3.9576314 | AG11: =(S11-EN11)/EN11 -> 6.807074 | AH11: =IF((AI11-TODAY())>0,AI11-TODAY(),(365-(TODAY()-AI11))) -> 319 | AI11: 46193 | AJ11: 46211 | AK11: 780000 | AL11: 810000 | AM11: =CJ11*10000000 -> 4000000000 | AN11: 0.1222 | AO11: =_xlfn.XLOOKUP(Q11,'Cem Sales'!$K$5:$K$33,'Cem Sales'!$DU$5:$DU$33,"") -> 1818 | AP11: 1524 | AQ11: 987 | AR11: =_xlfn.XLOOKUP(Q11,'Sales Rec'!$E$4:$E$86,'Sales Rec'!$X$4:$X$86,"") -> 2733.0081 | AS11: =_xlfn.XLOOKUP(Q11,'Sales Rec'!$E$4:$E$86,'Sales Rec'!$K$4:$K$86,"") -> 4 | AT11: =(S11-(CO11*CC11))/AR11 -> 3.5535936 | AU11: =MIN(MAX(IF(($Q$42-AT11)*$R$42<-20,-20,IF(($Q$42-AT11)*$R$42>20,20,($Q$42-AT11)*$R$42)), -10), 10) -> -10 | AV11: 565 | AW11: 435 | AX11: =ROUND(AW11/AV11,3) -> 0.77 | AY11: 0.337 | AZ11: 0.648 | BA11: 0.165 | BB11: =IF(BC11=0,0,MIN(MAX(IF(BC11=BD11,BC11-BF11,BC11-BD11)*$R$43, -10), 10)) -> 10 | BC11: =IF(CN11=0,BE11,ROUND((CN11-CM11)/AV11,3)) -> 0.628 | BD11: 0.233 | BE11: 0.543 | BF11: 0.092 | BG11: =AX11-BC11 -> 0.142 | BH11: =BG11*AV11*(4/BO11) -> 320.92 | BI11: =AY11-BD11 -> 0.104 | BJ11: 0 | BK11: =_xlfn.XLOOKUP(Q11,'Sales Rec'!$E$4:$E$91,'Sales Rec'!$Y$4:$Y$91,"") -> 0.79331241 | BL11: =IF(BK11=0,0,MIN(MAX((BK11-Z11)*$R$44,-5),5)) -> 5 | BN11: 3 | BO11: =IF((BN11-R11+12)/3>4,(BN11-R11+12)/3-4, (BN11-R11+12)/3) -> 1 | BP11: 1312 | BS11: =(_xlfn.XLOOKUP(Q11,'Sales Rec'!$E$4:$E$32,'Sales Rec'!$X$4:$X$32)*BC11+CL11)*1000/CJ11 -> 5105.8227 | BT11: =IF((CN11/CJ11)*1000*(12/(12-(R11-BN11)))=0,CB11,IF(R11-BN11>=0,((CP11/CJ11)*1000*(12/(12-(R11-BN11)))),((CP11/CJ11)*1000*(12/(BN11-R11))))) -> 5250 | BV11: =IF(CN11=0,V11/BT11,(V11*2)/(BS11+BT11)) -> 4.6891494 | BW11: =MIN(MAX(IF(BV11<0,-20, IF(BV11>50, -20,($Q$45-BV11)*$R$45)), -20), 20) -> 1.554253 | BX11: =IFERROR(S11/BV11,"") -> 2071.1645 | BY11: =S11/CC11 -> 1524.6468 | BZ11: =AR11*AX11 -> 2104.4162 | CA11: =X11/BZ11 -> 4.9381866 | CB11: =_xlfn.XLOOKUP($Q11,'Price Record'!$C$6:$C$85,'Price Record'!I$6:I$85,"") -> 3814 | CC11: =_xlfn.XLOOKUP($Q11,'Price Record'!$C$6:$C$85,'Price Record'!J$6:J$85,"") -> 6.37 | CD11: =MIN(MAX(IF(CC11<0,-20, IF(CC11>50, -20,($Q$46-CC11)*$R$46)), -20), 20) -> -4.11 | CE11: =CY11/BX11 -> 1.0259928 | CF11: =MIN(MAX(($Q$47-CE11)*$R$47, -10), 10) -> 3.8960286 | CG11: =BX11/(CU11+DG11) -> 0.53838434 | CH11: =MIN(MAX((CG11-$Q$48)*$R$48, -10), 10) -> 2.0757651 | CJ11: 400 | CK11: 119 | CL11: 326 | CM11: 170 | CN11: 525 | CP11: =IF(AND(CM11>0, CL11>(CM11/(BO11/4))), CN11+CL11*BO11/4-CM11, CN11) -> 525 | CQ11: =(AR11*BC11)*(_xlfn.XLOOKUP($Q11,'Sales Rec'!$E$4:$E$32,'Sales Rec'!$L$4:$L$32,"")/12)+CO11 -> 572.1097 | CR11: 644 | CS11: -17 | CT11: =_xlfn.TEXTJOIN(", ",TRUE, IF(CU11/(CJ11*1.1+CR11+CS11)<=0.975,"Check EQ",""), IF(CR11<>(CN11+CK11),"Check RE","") ) | CU11: =DB11-CY11 -> 1124 | CV11: 2092 | CW11: 498 | CX11: 33 | CY11: =CV11+CX11 -> 2125 | CZ11: =DG11/CV11 -> 1.3016252 | DA11: =MIN(MAX((CZ11-$Q$50)*$R$50, -6), 6) -> 0.81300191 | DB11: =DD11+DG11 -> 3249 | DC11: =(CY11/DB11) -> 0.6540474 | DD11: 526 | DE11: 290 | DF11: 44 | DG11: 2723 | DH11: =DG11-CV11 -> 631 | DI11: =AR11/DH11 -> 4.3312331 | DJ11: 721 | DK11: 575 | DL11: 436 | DM11: =CY11/DB11 -> 0.6540474 | DN11: =MIN(MAX(($Q$51-DM11)*$R$51, -6), 6) -> -0.53917587 | DO11: =(DQ11-CW11)/BZ11 -> 0.17677111 | DP11: =MIN(MAX(ROUNDDOWN(DO11*5,0),-10),5) -> 0 | DQ11: 870 | DR11: =DG11-DJ11-DK11-DQ11-DL11 -> 121 | DS11: G | DT11: =IFERROR(((S11/AK11)/$Q$38*1000000000),"") -> 65.879799 | DU11: =IF(DS11="G",(500000*$Q$57+(AK11-500000)*$R$57*$Q$57)*$Q$38/1000000000, (150000*$Q$58+(AK11-150000)*$R$58*$Q$58)*$Q$38/1000000000) -> 8378.37 | DV11: =DU11/S11 -> 0.86268225 | DW11: =MIN(MAX((DV11-$Q$53)*$R$53, -10), 10) -> -2.746355 | DX11: =IFERROR((AR11/AK11)*1000000,"") -> 3503.8565 | DY11: =MIN(MAX(((DX11-$Q$54)/$Q$54)*$R$54, -10), 10) -> 10 | DZ11: =(S11/AR11)/BV11 -> 0.7578333 | EA11: =MIN(MAX((DZ11-$Q$55)*$R$55,-10), 10) -> 8.0178669 | EB11: =_xlfn.XLOOKUP(Q11,'Cem Sales'!$K$5:$K$33,'Cem Sales'!$DN$5:$DN$33, 0) -> 0.27158949 | EC11: =MIN(MAX(EB11*$R$56, 0), 10) -> 2.7158949 | ED11: =($CB11/$Q$40)*(IF(($R11+2-$Q$39)<0,(88-$R11-2+$Q$39),(100-($R11+2-$Q$39))))/100 -> 13882.96 | EE11: =($BT11/$Q$40)*(IF(($R11+2-$Q$39)<0,(88-$R11-2+$Q$39),(100-($R11+3-$Q$39))))/100 -> 18900 | EF11: =((CR11-CN11)*10000000000)/AM11 -> 297.5 | EG11: =(ED11+EE11+EF11)/2 -> 16540.23 | EH11: =IFERROR((AJ11-AI11),230) -> 18 | EI11: 2600 | EJ11: =EI11/(EI11+EW11) -> 0.13727561 | EK11: 15 | EM11: 49740 | EN11: 1244 | EO11: 78360 | EP11: 1959 | EQ11: 4810 | ER11: 1924 | ES11: 6791 | ET11: 2716 | EU11: 16340 | EV11: 6536 | EW11: 16340 | EX11: 6536 | EY11: =IFERROR((EX11-EN11)/EN11,"") -> 4.2540193 | EZ11: =RANK(EY11,$EY$7:$EY$35) -> 10
A12: =_xlfn.XLOOKUP(Q12,'Cement Ranking'!$F$7:$F$35,'Cement Ranking'!$AO$7:$AO$35, "") -> 25.396087 | B12: =_xlfn.XLOOKUP(Q12,'Cement Ranking'!$F$7:$F$35,'Cement Ranking'!$AN$7:$AN$35, "") -> 14.733793 | C12: =((((CK12*10000000000)/AM12)+CB12*0.8)/V12)/((AH12+EH12)/365) -> 0.10886834 | D12: =(CC12-BV12) -> 2.328977 | E12: =IF(OR(AX12=AY12, AX12=""), (AY12-BA12), (AX12-AY12))*100 -> 5.8 | F12: =IF(OR(BC12=BD12, BC12=""), (BD12-BF12), (BC12-BD12))*100 -> 6.7 | G12: {=IFERROR(_xlfn.XLOOKUP(Q12,'Sales Rec'!$E$4:$E$32,'Sales Rec'!$CU$4:$CU$32*100,""),"")} -> -16.892599 | H12: =_xlfn.XLOOKUP(Q12,'Sales Rec'!$E$4:$E$32,'Sales Rec'!$DQ$4:$DQ$32,"") -> 0.99570815 | I12: =_xlfn.XLOOKUP(Q12,'Sales History'!$C$4:$C$83,'Sales History'!$AS$4:$AS$83,"") -> 1.0540019 | J12: =_xlfn.XLOOKUP(Q12,'Sales History'!$C$4:$C$83,'Sales History'!$AW$4:$AW$83,"") -> 0.68344775 | K12: =_xlfn.XLOOKUP(Q12,'Sales Rec'!$E$4:$E$91,'Sales Rec'!$CV$4:$CV$91,"") -> 4 | L12: =_xlfn.XLOOKUP(Q12,'Cement Ranking'!$F$7:$F$35,'Cement Ranking'!$AQ$7:$AQ$35,"") -> 14 | M12: =_xlfn.XLOOKUP(Q12,'Sales Rec'!$E$4:$E$32,'Sales Rec'!$DS$4:$DS$32,"") -> B | N12: =_xlfn.XLOOKUP(Q12,'Sales Rec'!$E$4:$E$32,'Sales Rec'!$DZ$4:$DZ$32,"") -> BB | O12: =_xlfn.XLOOKUP($Q12,'History Records'!$B$7:$B$88,'History Records'!$G$7:$G$88,"") | P12: سيمان‌ شاهرود | Q12: سرود | R12: 12 | S12: =(V12*AM12)/10000000000 -> 15993.698 | T12: =_xlfn.XLOOKUP($Q12,'Price Record'!$C$6:$C$85,'Price Record'!H$6:H$85,"") -> 16660 | U12: =_xlfn.XLOOKUP(Q12,'دیده بان بازار'!$A$3:$A$3542,'دیده بان بازار'!$M$3:$M$3542,"") -> 2.97 | V12: =_xlfn.XLOOKUP($Q12,'Price Record'!$C$6:$C$85,'Price Record'!G$6:G$85,"") -> 16660 | W12: =_xlfn.XLOOKUP(Q12,'دیده بان بازار'!$A$3:$A$3542,'دیده بان بازار'!$J$3:$J$3542,"") -> 2.97 | X12: =S12+CY12-DK12-DQ12 -> 19031.698 | Y12: =IFERROR(IF(U12-W12<-1.5,"B",IF(U12-W12>1.5,"S","")),"") | Z12: =IFERROR((S12-EX12)/EX12,"") -> 0.18489393 | AA12: =((365-AH12)/365)*$AA$2 -> 0.034520548 | AB12: =IFERROR(((AA12-Z12)*10000)/(365-AH12),"") -> -107.40956 | AC12: =IFERROR(($S12-EV12)/EV12,"") -> 0.18489393 | AD12: =IFERROR((S12-ET12)/ET12,"") -> 1.5475786 | AE12: =(S12-ER12)/ER12 -> 4.1016581 | AF12: =(S12-EP12)/EP12 -> 3.8363164 | AG12: =(S12-EN12)/EN12 -> 8.4475151 | AH12: =IF((AI12-TODAY())>0,AI12-TODAY(),(365-(TODAY()-AI12))) -> 351 | AI12: 46225 | AJ12: 46346 | AK12: 1800000 | AL12: 1870000 | AM12: =CJ12*10000000 -> 9600059000 | AN12: 0.4775 | AO12: =_xlfn.XLOOKUP(Q12,'Cem Sales'!$K$5:$K$33,'Cem Sales'!$DU$5:$DU$33,"") -> 5293 | AP12: 4210 | AQ12: 1933 | AR12: =_xlfn.XLOOKUP(Q12,'Sales Rec'!$E$4:$E$86,'Sales Rec'!$X$4:$X$86,"") -> 7693.9657 | AS12: =_xlfn.XLOOKUP(Q12,'Sales Rec'!$E$4:$E$86,'Sales Rec'!$K$4:$K$86,"") -> 4 | AT12: =(S12-(CO12*CC12))/AR12 -> 2.2394561 | AU12: =MIN(MAX(IF(($Q$42-AT12)*$R$42<-20,-20,IF(($Q$42-AT12)*$R$42>20,20,($Q$42-AT12)*$R$42)), -10), 10) -> 1.8686657 | AV12: 2130 | AW12: 1119 | AX12: =ROUND(AW12/AV12,3) -> 0.525 | AY12: 0.467 | AZ12: 0.459 | BA12: 0.358 | BB12: =IF(BC12=0,0,MIN(MAX(IF(BC12=BD12,BC12-BF12,BC12-BD12)*$R$43, -10), 10)) -> 6.7 | BC12: =IF(CN12=0,BE12,ROUND((CN12-CM12)/AV12,3)) -> 0.382 | BD12: 0.315 | BE12: 0.328 | BF12: 0.203 | BG12: =AX12-BC12 -> 0.143 | BH12: =BG12*AV12*(4/BO12) -> 1218.36 | BI12: =AY12-BD12 -> 0.152 | BJ12: 0 | BK12: =_xlfn.XLOOKUP(Q12,'Sales Rec'!$E$4:$E$91,'Sales Rec'!$Y$4:$Y$91,"") -> 0.82754529 | BL12: =IF(BK12=0,0,MIN(MAX((BK12-Z12)*$R$44,-5),5)) -> 5 | BN12: 3 | BO12: =IF((BN12-R12+12)/3>4,(BN12-R12+12)/3-4, (BN12-R12+12)/3) -> 1 | BP12: 967 | BS12: =(_xlfn.XLOOKUP(Q12,'Sales Rec'!$E$4:$E$32,'Sales Rec'!$X$4:$X$32)*BC12+CL12)*1000/CJ12 -> 3470.9108 | BT12: =IF((CN12/CJ12)*1000*(12/(12-(R12-BN12)))=0,CB12,IF(R12-BN12>=0,((CP12/CJ12)*1000*(12/(12-(R12-BN12)))),((CP12/CJ12)*1000*(12/(BN12-R12))))) -> 3866.6429 | BV12: =IF(CN12=0,V12/BT12,(V12*2)/(BS12+BT12)) -> 4.541023 | BW12: =MIN(MAX(IF(BV12<0,-20, IF(BV12>50, -20,($Q$45-BV12)*$R$45)), -20), 20) -> 2.2948852 | BX12: =IFERROR(S12/BV12,"") -> 3522.0474 | BY12: =S12/CC12 -> 2328.0492 | BZ12: =AR12*AX12 -> 4039.332 | CA12: =X12/BZ12 -> 4.7115955 | CB12: =_xlfn.XLOOKUP($Q12,'Price Record'!$C$6:$C$85,'Price Record'!I$6:I$85,"") -> 2424 | CC12: =_xlfn.XLOOKUP($Q12,'Price Record'!$C$6:$C$85,'Price Record'!J$6:J$85,"") -> 6.87 | CD12: =MIN(MAX(IF(CC12<0,-20, IF(CC12>50, -20,($Q$46-CC12)*$R$46)), -20), 20) -> -5.61 | CE12: =CY12/BX12 -> 1.6927654 | CF12: =MIN(MAX(($Q$47-CE12)*$R$47, -10), 10) -> 1.2289385 | CG12: =BX12/(CU12+DG12) -> 0.44969962 | CH12: =MIN(MAX((CG12-$Q$48)*$R$48, -10), 10) -> 0.74549433 | CJ12: 960.0059 | CK12: 390 | CL12: 393 | CM12: 115 | CN12: 928 | CO12: -180 | CP12: =IF(AND(CM12>0, CL12>(CM12/(BO12/4))), CN12+CL12*BO12/4-CM12, CN12) -> 928 | CQ12: =(AR12*BC12)*(_xlfn.XLOOKUP($Q12,'Sales Rec'!$E$4:$E$32,'Sales Rec'!$L$4:$L$32,"")/12)+CO12 -> 799.69829 | CR12: 1318 | CS12: -50 | CT12: =_xlfn.TEXTJOIN(", ",TRUE, IF(CU12/(CJ12*1.1+CR12+CS12)<=0.975,"Check EQ",""), IF(CR12<>(CN12+CK12),"Check RE","") ) | CU12: =DB12-CY12 -> 2366 | CV12: 5826 | CW12: 2879 | CX12: 136 | CY12: =CV12+CX12 -> 5962 | CZ12: =DG12/CV12 -> 0.93820803 | DA12: =MIN(MAX((CZ12-$Q$50)*$R$50, -6), 6) -> -2.0943357 | DB12: =DD12+DG12 -> 8328 | DC12: =(CY12/DB12) -> 0.71589817 | DD12: 2862 | DE12: 2652 | DF12: 40 | DG12: 5466 | DH12: =DG12-CV12 -> -360 | DI12: =AR12/DH12 -> -21.372127 | DJ12: 1323 | DK12: 274 | DL12: 824 | DM12: =CY12/DB12 -> 0.71589817 | DN12: =MIN(MAX(($Q$51-DM12)*$R$51, -6), 6) -> -1.1576836 | DO12: =(DQ12-CW12)/BZ12 -> -0.056692543 | DP12: =MIN(MAX(ROUNDDOWN(DO12*5,0),-10),5) -> 0 | DQ12: 2650 | DR12: =DG12-DJ12-DK12-DQ12-DL12 -> 395 | DS12: G | DT12: =IFERROR(((S12/AK12)/$Q$38*1000000000),"") -> 47.012635 | DU12: =IF(DS12="G",(500000*$Q$57+(AK12-500000)*$R$57*$Q$57)*$Q$38/1000000000, (150000*$Q$58+(AK12-150000)*$R$58*$Q$58)*$Q$38/1000000000) -> 16523.325 | DV12: =DU12/S12 -> 1.0331147 | DW12: =MIN(MAX((DV12-$Q$53)*$R$53, -10), 10) -> 0.66229423 | DX12: =IFERROR((AR12/AK12)*1000000,"") -> 4274.4254 | DY12: =MIN(MAX(((DX12-$Q$54)/$Q$54)*$R$54, -10), 10) -> 10 | DZ12: =(S12/AR12)/BV12 -> 0.4577675 | EA12: =MIN(MAX((DZ12-$Q$55)*$R$55,-10), 10) -> -0.984107 | EB12: =_xlfn.XLOOKUP(Q12,'Cem Sales'!$K$5:$K$33,'Cem Sales'!$DN$5:$DN$33, 0) -> 0.67419355 | EC12: =MIN(MAX(EB12*$R$56, 0), 10) -> 6.7419355 | ED12: =($CB12/$Q$40)*(IF(($R12+2-$Q$39)<0,(88-$R12-2+$Q$39),(100-($R12+2-$Q$39))))/100 -> 8823.36 | EE12: =($BT12/$Q$40)*(IF(($R12+2-$Q$39)<0,(88-$R12-2+$Q$39),(100-($R12+3-$Q$39))))/100 -> 13919.914 | EF12: =((CR12-CN12)*10000000000)/AM12 -> 406.2475 | EG12: =(ED12+EE12+EF12)/2 -> 11574.761 | EH12: =IFERROR((AJ12-AI12),230) -> 121 | EI12: 1600 | EJ12: =EI12/(EI12+EW12) -> 0.10217114 | EK12: 11.85 | EM12: 20900 | EN12: 1692.9 | EO12: 40830 | EP12: 3307 | EQ12: 38700 | ER12: 3135 | ES12: 6540 | ET12: 6278 | EU12: 14060 | EV12: 13498 | EW12: 14060 | EX12: 13498 | EY12: =IFERROR((EX12-EN12)/EN12,"") -> 6.9733003 | EZ12: =RANK(EY12,$EY$7:$EY$35) -> 3
